Workbook

Sheet Supuestos
A1: SUPUESTOS — CONTROL EN VIVO · ESCENARIO Proplasa techo 3.15 MW (PR1 557 + PR2 1,565 + TAP 1,028 kWp). Edita AZUL; recalcula todo.
A2: Cifras PRE-IVA (el IVA es acreditable para GEPP). Mecánica tarifaria = fuente primaria; ahorros = motor determinista; costos/escalaciones/PPA = supuestos.
A3: Parámetro | B3: Valor | C3: Nota / Fuente
A4: EPC PV (USD/Wp) | B4: 0.75 | C4: Llave en mano CC; supuesto MX 2026
A5: Tipo de cambio (MXN/USD) | B5: 17.55 | C5: Supuesto
A6: EPC BESS (USD/kWh) | B6: 280 | C6: LFP instalado
A7: WACC / descuento | B7: 0.12 | C7: Para VPN
A8: Escalación CFE / año | B8: 0.06 | C8: Conservador (tarifa sube)
A9: Escalación PPA / año | B9: 0.05 | C9: < CFE → brecha a favor del cliente
A10: Disponibilidad (sobre ahorro BESS) | B10: 0.75 | C10: Supuesto de downtime
A11: Degradación PV / año | B11: 0.005 | C11: TOPCon/HJT
A12: Degradación BESS / año | B12: 0.0125 | C12: LFP
A13: TIR financiador objetivo | B13: 0.18 | C13: Negociable (14–18%); las tarifas PPA semilla resuelven 18%
A14: Comisión BESS financiador (default) | B14: 0.5 | C14: Ahorro compartido (override por proyecto abajo)
A15: Horizonte (años) | B15: 20 | C15: Proyección financiera
... A24: Año de inicio del proyecto | B24: 2026 | C24: Para el escalón 2032
A26: B. VARIABLES POR PROYECTO (AZUL = editable) — afectan cada hoja de sitio, el Comparativo y la Proyección
A27: Proyecto | B27: PV kWp | C27: BESS kW | D27: BESS kWh | E27: FP corr | F27: PV USD/Wp | G27: BESS USD/kWh | H27: Capacitor capex $ | I27: PPA $/kWh | J27: PPA plazo (años) | K27: Comisión BESS % | L27: BESS (años) | M27: TIR financiador | N27: TIR compra | O27: Ahorro bruto/año $ | P27: Ahorro PPA&SAAS anual | Q27: Ahorro PPA&SAAS 20 años
A28: Ixtlahuacán | B28: 2529.67 | C28: 751.5 | D28: 1470 | E28: No | F28: 0.75 | G28: 280 | H28: 0 | I28: 1.5574 | J28: 15 | K28: 0.5 | L28: 20 | M28: =Ixtlahuacán!$G$101 -> 0.18294207 | N28: =Ixtlahuacán!$G$100 -> 0.30515621 | O28: =Ixtlahuacán!$J$72 -> 11170649 | P28: =+Ixtlahuacán!K79 -> 3573170.3 | Q28: =+Ixtlahuacán!K99 -> 2.2192145e+08
A29: Acapulco | B29: 1020.305 | C29: 250.5 | D29: 490 | E29: Sí | F29: 0.75 | G29: 280 | H29: 300000 | I29: 1.5781 | J29: 15 | K29: 0.5 | L29: 20 | M29: =Acapulco!$G$101 -> 0.18679137 | N29: =Acapulco!$G$100 -> 0.43092559 | O29: =Acapulco!$J$72 -> 6212518.3 | P29: =+Acapulco!K79 -> 3353681.3 | Q29: =+Acapulco!K99 -> 1.5759175e+08
A30: Cancún | B30: 839.41 | C30: 0 | D30: 0 | E30: Sí | F30: 0.75 | G30: 280 | H30: 250000 | I30: 1.6838 | J30: 15 | K30: 0.5 | L30: 20 | M30: =Cancún!$G$101 -> 0.18090212 | N30: =Cancún!$G$100 -> 0.43596923 | O30: =Cancún!$J$72 -> 4331791.9 | P30: =+Cancún!K79 -> 2462692.9 | Q30: =+Cancún!K99 -> 1.1291961e+08
A31: Proplasa PR1 | B31: 839.41 | C31: 501 | D31: 980 | E31: No | F31: 0.75 | G31: 280 | H31: 0 | I31: 1.5891 | J31: 15 | K31: 0.5 | L31: 20 | M31: ='Proplasa PR1'!$G$101 -> 0.18105675 | N31: ='Proplasa PR1'!$G$100 -> 0.28566512 | O31: ='Proplasa PR1'!$J$72 -> 4517195.3 | P31: =+'Proplasa PR1'!K79 -> 1246444.2 | Q31: =+'Proplasa PR1'!K99 -> 68494800
A32: Proplasa PR2 | B32: 1565.135 | C32: 1252.5 | D32: 2450 | E32: No | F32: 0.75 | G32: 280 | H32: 0 | I32: 1.6117 | J32: 15 | K32: 0.5 | L32: 20 | M32: ='Proplasa PR2'!$G$101 -> 0.17995412 | N32: ='Proplasa PR2'!$G$100 -> 0.28926483 | O32: ='Proplasa PR2'!$J$72 -> 9667366.1 | P32: =+'Proplasa PR2'!K79 -> 2748991.2 | Q32: =+'Proplasa PR2'!K99 -> 1.419215e+08
A33: Proplasa Tapas | B33: 839.41 | C33: 751.5 | D33: 1470 | E33: No | F33: 0.75 | G33: 280 | H33: 0 | I33: 1.6088 | J33: 15 | K33: 0.5 | L33: 20 | M33: ='Proplasa Tapas'!$G$101 -> 0.1784488 | N33: ='Proplasa Tapas'!$G$100 -> 0.29125501 | O33: ='Proplasa Tapas'!$J$72 -> 5506797.3 | P33: =+'Proplasa Tapas'!K79 -> 1606410.1 | Q33: =+'Proplasa Tapas'!K99 -> 80297578
A34: PORTAFOLIO | B34: =SUM(B28:B33) -> 7633.34 | D34: =SUM(D28:D33) -> 6860 | H34: =SUM(H28:H33) -> 550000 | O34: =SUM(O28:O33) -> 41406317
A36: Las tarifas PPA semilla resuelven una TIR del financiador de 18% con plazo 15 años (PV se transfiere al cliente al término) + comisión BESS 20 años. Cambia cualquier celda azul y observa el efecto en vivo.

Sheet Resumen Ejecutivo
A1: GEPP — SOLUCIÓN ENERGÉTICA · ESCENARIO: Proplasa techo 3.15 MW · Resumen Ejecutivo
A2: ESCENARIO: el techo TOTAL de Proplasa (PR1+PR2+TAP) se limita a 3.15 MW por falta de espacio (vs 10.51 MW sin límite). RECOMENDACIÓN PRIORIZADA: COMPRAR — conserva el 100% del ahorro para GEPP (más que el PPA). Cifras PRE-IVA, motor determinista. Grado prefactibilidad.
A4: INDICADORES CLAVE (PRE-IVA, año 1)
A5: Gasto eléctrico actual 2025 (CFE+autoabasto) | C5: Ahorro autoabasto (Tala+ENEL) | E5: Ahorro PV+BESS+FP (proyecto) | G5: Generación solar kWh/año
A6: ='Proyección 20 años'!C5/(1+Supuestos!$B$8) -> 2.9463417e+08 | C6: =Ixtlahuacán!$B$11+Acapulco!$B$11+Cancún!$B$11+'Proplasa PR1'!$B$11+'Proplasa PR2'!$B$11+'Proplasa Tapas'!$B$11 -> 21558824 | E6: =Ixtlahuacán!$B$21+Acapulco!$B$21+Cancún!$B$21+'Proplasa PR1'!$B$21+'Proplasa PR2'!$B$21+'Proplasa Tapas'!$B$21 -> 41406317 | G6: =Ixtlahuacán!$D$17+Acapulco!$D$17+Cancún!$D$17+'Proplasa PR1'!$D$17+'Proplasa PR2'!$D$17+'Proplasa Tapas'!$D$17 -> 13063261
A8: Inversión total (compra) | C8: Beneficio GEPP año 1 (compra) | E8: Beneficio cliente año 1 (PPA) | G8: Ahorro proyecto % vs gasto actual
A9: =Ixtlahuacán!$B$106+Acapulco!$B$106+Cancún!$B$106+'Proplasa PR1'!$B$106+'Proplasa PR2'!$B$106+'Proplasa Tapas'!$B$106 -> 1.3473388e+08 | C9: ='Comparativo Comercial'!$B$22 -> 36826414 | E9: ='Comparativo Comercial'!$E$22 -> 14991390 | G9: =$E$6/$A$6 -> 0.14053467
A11: RECOMENDACIÓN POR PROYECTO
A12: Sitio | B12: Consumo GWh/a | C12: Solución | D12: Régimen LSE | E12: Ahorro bruto a1 | F12: Ahorro % | G12: Inversión | H12: TIR compra | I12: PPA $/kWh | J12: Benef. PPA a1
A13: Ixtlahuacán | B13: 22.17 | C13: PV 2.5 MWp + BESS 850 kW | D13: Autoconsumo CNE | E13: =Ixtlahuacán!$J$72 -> 11170649 | F13: =Ixtlahuacán!$C$21 -> 0.21259287 | G13: =Ixtlahuacán!$B$106 -> 40520361 | H13: =Ixtlahuacán!$G$100 -> 0.30515621 | I13: =Supuestos!$I$28 -> 1.5574 | J13: =Ixtlahuacán!$K$79 -> 3573170.3
A14: Acapulco | B14: 8.91 | C14: FP + PV 1.0 MWp + BESS 320 kW | D14: Autoconsumo CNE | E14: =Acapulco!$J$72 -> 6212518.3 | F14: =Acapulco!$C$21 -> 0.21986264 | G14: =Acapulco!$B$106 -> 16137625 | H14: =Acapulco!$G$100 -> 0.43092559 | I14: =Supuestos!$I$29 -> 1.5781 | J14: =Acapulco!$K$79 -> 3353681.3
A15: Cancún | B15: 4.75 | C15: FP + PV 0.7 MWp (sin BESS) | D15: Exento <0.7 MW | E15: =Cancún!$J$72 -> 4331791.9 | F15: =Cancún!$C$21 -> 0.27083319 | G15: =Cancún!$B$106 -> 11298734 | H15: =Cancún!$G$100 -> 0.43596923 | I15: =Supuestos!$I$30 -> 1.6838 | J15: =Cancún!$K$79 -> 2462692.9
A16: Proplasa PR1 | B16: 16.29 | C16: PV 0.56 MWp + BESS 360 kW | D16: Autoconsumo CNE | E16: ='Proplasa PR1'!$J$72 -> 4517195.3 | F16: ='Proplasa PR1'!$C$21 -> 0.14038004 | G16: ='Proplasa PR1'!$B$106 -> 15864454 | H16: ='Proplasa PR1'!$G$100 -> 0.28566512 | I16: =Supuestos!$I$31 -> 1.5891 | J16: ='Proplasa PR1'!$K$79 -> 1246444.2
A17: Proplasa PR2 | B17: 45.72 | C17: PV 1.57 MWp + BESS 1.22 MW | D17: Autoconsumo CNE | E17: ='Proplasa PR2'!$J$72 -> 9667366.1 | F17: ='Proplasa PR2'!$C$21 -> 0.094651183 | G17: ='Proplasa PR2'!$B$106 -> 32640389 | H17: ='Proplasa PR2'!$G$100 -> 0.28926483 | I17: =Supuestos!$I$32 -> 1.6117 | J17: ='Proplasa PR2'!$K$79 -> 2748991.2
A18: Proplasa Tapas | B18: 30.03 | C18: PV 1.03 MWp + BESS 790 kW | D18: Autoconsumo CNE | E18: ='Proplasa Tapas'!$J$72 -> 5506797.3 | F18: ='Proplasa Tapas'!$C$21 -> 0.086688996 | G18: ='Proplasa Tapas'!$B$106 -> 18272314 | H18: ='Proplasa Tapas'!$G$100 -> 0.29125501 | I18: =Supuestos!$I$33 -> 1.6088 | J18: ='Proplasa Tapas'!$K$79 -> 1606410.1
A19: PORTAFOLIO | B19: =SUM(B13:B18) -> 127.87 | E19: =SUM(E13:E18) -> 41406317 | G19: =SUM(G13:G18) -> 1.3473388e+08 | J19: =SUM(J13:J18) -> 14991390
A21: Comprar maximiza el ahorro de GEPP (TIR 28-44%); el PPA/ahorro compartido es la vía sin inversión. Variables por proyecto (PPA $/kWh, plazo, costo PV/BESS) en la hoja Supuestos — todo recalcula en vivo.
A24: AUTOABASTO Y EL ESCALÓN 2032
A25: En 2025 GEPP pagó $294.6M (CFE + Tala/ENEL); a tarifa CFE plena sería $316.2M — el autoabasto ahorra ~$21.6M/año PERO VENCE 2032. ENEL ya colapsó en 2026 (Proplasa ~85% CFE), así que gran parte del salto ya ocurrió. El PV/BESS reemplaza ese ahorro con generación propia que NO expira y se vuelve más valiosa conforme sube la tarifa CFE.

Sheet Ixtlahuacán
A1: IXTLAHUACÁN — Memoria de cálculo trazable y propuesta
A2: Medidor 455GR3 · GDMTH SIN · Demanda contratada 5,000 kW · AUTOCONSUMO interconectado (>0.7 MW) — permiso SIMPLIFICADO CNE
A3: GEPP pide: Combinar autoabasto (Tala) con generación solar en sitio
A5: PARÁMETROS DEL SISTEMA (desde Supuestos — edítalos allí)
A6: PV kWp | B6: =Supuestos!$B$28 -> 2529.67 | C6: BESS kW | D6: =Supuestos!$C$28 -> 751.5 | E6: BESS kWh | F6: =Supuestos!$D$28 -> 1470 | G6: Entrega útil kWh | H6: =Supuestos!$D$28*Supuestos!$B$17*SQRT(Supuestos!$B$18) -> 1382.688 | I6: FP corr. | J6: =Supuestos!$E$28 -> No | K6: Calib→recibo | L6: =$B$10/(SUM(P45:P56)+SUM(R30:R41)) -> 1.0327958
A8: 1. ESTRUCTURA DE COSTO Y AHORRO (2025, pre-IVA · datos del workbook GEPP + motor)
A9: Concepto | B9: $ / año | C9: $ / kWh | D9: kWh | E9: Nota
A10: CFE BRUTO = Tarifa Actual (todo a CFE pleno, sin autoabasto) | B10: 55226961 | C10: =B10/D10 -> 2.4908517 | D10: 22171919 | E10: Lo que pagarían 100% en CFE sin ENEL/Tala ni PV/BESS
A11: (−) Ahorro autoabasto (Tala (bagazo, zafra)) | B11: 2682168.3 | E11: Descuento Tala 10% (dato workbook)
A12: (=) Costo actual que paga GEPP hoy | B12: =B10-B11 -> 52544793 | C12: =B12/D12 -> 2.3698802 | D12: =D10 -> 22171919
A13: › CFE (tarifa CFE plena) | B13: 28405279 | C13: =B13/D13 -> 2.5373126 | D13: 11195025
A14: › Tala (neto) | B14: 24139514 | C14: =B14/D14 -> 2.1991207 | D14: 10976894
A16: Ahorros del proyecto (motor 2025, sobre la carga física):
A17: (−) Ahorro PV (energía intermedia + demanda vía umbral) | B17: =F72 -> 9332483 | D17: =C72 -> 4511666.4 | E17: Gen solar kWh/año →
A18: (−) Ahorro BESS (recorte de punta + arbitraje) | B18: =G72 -> 1838165.5
A19: (−) Ahorro FP (corrección factor de potencia) | B19: =H72 -> 0 | E19: FP sano — sin multa
A20: (=) Costo neto con proyecto (hoy) | B20: =B12-B17-B18-B19 -> 41374144
A21: Ahorro proyecto PV+BESS+FP (vs costo hoy) | B21: =B17+B18+B19 -> 11170649 | C21: =B21/B12 -> 0.21259287
A22: Ahorro TOTAL vs CFE bruto (incl. autoabasto+proyecto) | B22: =B10-B20 -> 13852817 | C22: =B22/B10 -> 0.25083431
A24: 2. CAPEX (fórmulas vivas desde Supuestos)
A25: CAPEX PV = kWp×1000×USD/Wp×FX | B25: =$B$6*1000*Supuestos!$F$28*Supuestos!$B$5 -> 33296781 | C25: CAPEX BESS = kWh×USD/kWh×FX | D25: =$F$6*Supuestos!$G$28*Supuestos!$B$5 -> 7223580
A26: CAPEX Capacitor FP (financiador en PPA) | B26: =Supuestos!$H$28 -> 0 | C26: CAPEX TOTAL (compra) | D26: =B25+D25+B26 -> 40520361 | E26: Bajo PPA, el capacitor lo paga el financiador → el cliente no desembolsa
A28: 3. ENTRADAS MENSUALES (AZUL = datos del recibo / recurso 2025)
A29: Mes | B29: kWh Base | C29: kWh Int | D29: kWh Punta | E29: Días | F29: Dem Pta kW | G29: Dem Máx kW | H29: T.Int $ | I29: T.Base $ | J29: T.Pta $ | K29: T.Cap $ | L29: T.Dist $ | M29: T.Fijo $ | N29: Rend | O29: %AC | P29: HrsP | Q29: DíasP | R29: Bonif FP
A30: Ene | B30: 526734 | C30: 883555 | D30: 248906 | E30: 31 | F30: 3356 | G30: 3473 | H30: 1.77225 | I30: 1.078225 | J30: 2.09405 | K30: 402.07 | L30: 0 | M30: 991.97 | N30: 147.1 | O30: 1 | P30: 4 | Q30: 22 | R30: -12380.66
A31: Feb | B31: 465212 | C31: 827425 | D31: 142578 | E31: 28 | F31: 3456 | G31: 3621 | H31: 1.77225 | I31: 1.078225 | J31: 2.09405 | K31: 402.07 | L31: 0 | M31: 991.97 | N31: 142.5 | O31: 1 | P31: 4 | Q31: 19 | R31: 0
A32: Mar | B32: 716956 | C32: 1033469 | D32: 168358 | E32: 31 | F32: 3932 | G32: 3934 | H32: 1.77225 | I32: 1.078225 | J32: 2.09405 | K32: 402.07 | L32: 0 | M32: 991.97 | N32: 180.5 | O32: 1 | P32: 4 | Q32: 20 | R32: -9319.35
A33: Abr | B33: 573723 | C33: 1158862 | D33: 139082 | E33: 30 | F33: 5896 | G33: 6180 | H33: 1.77225 | I33: 1.078225 | J33: 2.09405 | K33: 402.07 | L33: 0 | M33: 991.97 | N33: 168.5 | O33: 1 | P33: 2 | Q33: 22 | R33: -5439.0278
A34: May | B34: 664426 | C34: 1271980 | D34: 118279 | E34: 31 | F34: 7008 | G34: 7508 | H34: 1.77225 | I34: 1.078225 | J34: 2.09405 | K34: 402.07 | L34: 0 | M34: 991.97 | N34: 162.7 | O34: 1 | P34: 2 | Q34: 21 | R34: 0
A35: Jun | B35: 630738 | C35: 1133752 | D35: 116822 | E35: 30 | F35: 3402 | G35: 3618 | H35: 1.77225 | I35: 1.078225 | J35: 2.09405 | K35: 402.07 | L35: 0 | M35: 991.97 | N35: 148.1 | O35: 1 | P35: 2 | Q35: 21 | R35: 0
A36: Jul | B36: 534017 | C36: 1146833 | D36: 122085 | E36: 31 | F36: 3369 | G36: 3683 | H36: 1.77225 | I36: 1.078225 | J36: 2.09405 | K36: 402.07 | L36: 0 | M36: 991.97 | N36: 138.6 | O36: 1 | P36: 2 | Q36: 23 | R36: -4632.13
A37: Ago | B37: 701321 | C37: 1065260 | D37: 176568 | E37: 31 | F37: 3760 | G37: 3819 | H37: 1.77225 | I37: 1.078225 | J37: 2.09405 | K37: 402.07 | L37: 0 | M37: 991.97 | N37: 131.7 | O37: 1 | P37: 2 | Q37: 21 | R37: 14752.23
A38: Sep | B38: 593175 | C38: 941250 | D38: 167798 | E38: 30 | F38: 3451 | G38: 3551 | H38: 1.77225 | I38: 1.078225 | J38: 2.09405 | K38: 402.07 | L38: 0 | M38: 991.97 | N38: 126.7 | O38: 1 | P38: 2 | Q38: 21 | R38: -8690.45
A39: Oct | B39: 641906 | C39: 1065460 | D39: 218540 | E39: 31 | F39: 3682 | G39: 3861 | H39: 1.77225 | I39: 1.078225 | J39: 2.09405 | K39: 402.07 | L39: 0 | M39: 991.97 | N39: 146.8 | O39: 1 | P39: 2 | Q39: 23 | R39: 6997.92
A40: Nov | B40: 719936 | C40: 965437 | D40: 254095 | E40: 30 | F40: 3754 | G40: 3846 | H40: 1.77225 | I40: 1.078225 | J40: 2.09405 | K40: 402.07 | L40: 0 | M40: 991.97 | N40: 151.9 | O40: 1 | P40: 4 | Q40: 19 | R40: 33619.41
A41: Dic | B41: 704647 | C41: 1049782 | D41: 282952 | E41: 31 | F41: 5731 | G41: 5866 | H41: 1.77225 | I41: 1.078225 | J41: 2.09405 | K41: 402.07 | L41: 0 | M41: 991.97 | N41: 138.4 | O41: 1 | P41: 4 | Q41: 22 | R41: 14.15
A42: 4. CÁLCULO DE AHORRO MENSUAL (motor — fórmulas que referencian las ENTRADAS)
A43: Mes | B43: Gen kWh | C43: Umbral kW | D43: Autocons | E43: Ah PV ener | F43: Umbral post | G43: Cap base | H43: Cap pre-B | I43: Ah PV dem | J43: Recorte BESS | K43: Cap post | L43: Ah BESS dem | M43: Desc kWh | N43: Arbitraje $ | O43: Fac.AA | P43: mem $ | Q43: Ah PV+BESS
A45: =A30 -> Ene | B45: =$B$6*N30 -> 372114.46 | C45: =(B30+C30+D30)/(E30*24*Supuestos!$B$16) -> 3912.4576 | D45: =MIN(B45*O30,C30) -> 372114.46 | E45: =D45*H30*O45 -> 593531.86 | F45: =((B30+C30+D30)-D45)/(E30*24*Supuestos!$B$16) -> 3034.9947 | G45: =MIN(F30,C45) -> 3356 | H45: =MIN(F30,F45) -> 3034.9947 | I45: =(G45-H45)*K30 -> 129066.61 | J45: =IF(P30=0,0,MIN($D$6,$H$6/P30)) -> 345.67199 | K45: =MIN(MAX(F30-J45,0),F45) -> 3010.328 | L45: =(H45-K45)*K30 -> 9917.7282 | M45: =IF(P30=0,0,MIN($H$6*Q30,D30)) -> 30419.135 | N45: =M45*J30-(M45/Supuestos!$B$18)*I30 -> 29533.907 | O45: 0.9 | P45: =M30+B30*I30+C30*H30+D30*J30+G45*K30+MIN(G30,C45)*L30 -> 4005378.6 | Q45: =(E45+I45)+(L45+N45) -> 762050.11
A46: =A31 -> Feb | B46: =$B$6*N31 -> 360477.98 | C46: =(B31+C31+D31)/(E31*24*Supuestos!$B$16) -> 3746.9063 | D46: =MIN(B46*O31,C31) -> 360477.98 | E46: =D46*H31*O46 -> 574971.38 | F46: =((B31+C31+D31)-D46)/(E31*24*Supuestos!$B$16) -> 2805.8089 | G46: =MIN(F31,C46) -> 3456 | H46: =MIN(F31,F46) -> 2805.8089 | I46: =(G46-H46)*K31 -> 261422.35 | J46: =IF(P31=0,0,MIN($D$6,$H$6/P31)) -> 345.67199 | K46: =MIN(MAX(F31-J46,0),F46) -> 2805.8089 | L46: =(H46-K46)*K31 -> 0 | M46: =IF(P31=0,0,MIN($H$6*Q31,D31)) -> 26271.071 | N46: =M46*J31-(M46/Supuestos!$B$18)*I31 -> 25506.556 | O46: 0.9 | P46: =M31+B31*I31+C31*H31+D31*J31+G46*K31+MIN(G31,C46)*L31 -> 3657118.5 | Q46: =(E46+I46)+(L46+N46) -> 861900.29
A47: =A32 -> Mar | B47: =$B$6*N32 -> 456605.43 | C47: =(B32+C32+D32)/(E32*24*Supuestos!$B$16) -> 4524.5779 | D47: =MIN(B47*O32,C32) -> 456605.43 | E47: =D47*H32*O47 -> 728297.08 | F47: =((B32+C32+D32)-D47)/(E32*24*Supuestos!$B$16) -> 3447.8814 | G47: =MIN(F32,C47) -> 3932 | H47: =MIN(F32,F47) -> 3447.8814 | I47: =(G47-H47)*K32 -> 194649.55 | J47: =IF(P32=0,0,MIN($D$6,$H$6/P32)) -> 345.67199 | K47: =MIN(MAX(F32-J47,0),F47) -> 3447.8814 | L47: =(H47-K47)*K32 -> 0 | M47: =IF(P32=0,0,MIN($H$6*Q32,D32)) -> 27653.759 | N47: =M47*J32-(M47/Supuestos!$B$18)*I32 -> 26849.006 | O47: 0.9 | P47: =M32+B32*I32+C32*H32+D32*J32+G47*K32+MIN(G32,C47)*L32 -> 4539086.6 | Q47: =(E47+I47)+(L47+N47) -> 949795.64
A48: =A33 -> Abr | B48: =$B$6*N33 -> 426249.4 | C48: =(B33+C33+D33)/(E33*24*Supuestos!$B$16) -> 4560.5921 | D48: =MIN(B48*O33,C33) -> 426249.4 | E48: =D48*H33*O48 -> 679878.44 | F48: =((B33+C33+D33)-D48)/(E33*24*Supuestos!$B$16) -> 3521.9727 | G48: =MIN(F33,C48) -> 4560.5921 | H48: =MIN(F33,F48) -> 3521.9727 | I48: =(G48-H48)*K33 -> 417597.7 | J48: =IF(P33=0,0,MIN($D$6,$H$6/P33)) -> 691.34399 | K48: =MIN(MAX(F33-J48,0),F48) -> 3521.9727 | L48: =(H48-K48)*K33 -> 0 | M48: =IF(P33=0,0,MIN($H$6*Q33,D33)) -> 30419.135 | N48: =M48*J33-(M48/Supuestos!$B$18)*I33 -> 29533.907 | O48: 0.9 | P48: =M33+B33*I33+C33*H33+D33*J33+G48*K33+MIN(G33,C48)*L33 -> 4798309.6 | Q48: =(E48+I48)+(L48+N48) -> 1127010
A49: =A34 -> May | B49: =$B$6*N34 -> 411577.31 | C49: =(B34+C34+D34)/(E34*24*Supuestos!$B$16) -> 4845.041 | D49: =MIN(B49*O34,C34) -> 411577.31 | E49: =D49*H34*O49 -> 656476.1 | F49: =((B34+C34+D34)-D49)/(E34*24*Supuestos!$B$16) -> 3874.5229 | G49: =MIN(F34,C49) -> 4845.041 | H49: =MIN(F34,F49) -> 3874.5229 | I49: =(G49-H49)*K34 -> 390216.21 | J49: =IF(P34=0,0,MIN($D$6,$H$6/P34)) -> 691.34399 | K49: =MIN(MAX(F34-J49,0),F49) -> 3874.5229 | L49: =(H49-K49)*K34 -> 0 | M49: =IF(P34=0,0,MIN($H$6*Q34,D34)) -> 29036.447 | N49: =M49*J34-(M49/Supuestos!$B$18)*I34 -> 28191.457 | O49: 0.9 | P49: =M34+B34*I34+C34*H34+D34*J34+G49*K34+MIN(G34,C49)*L34 -> 5167387 | Q49: =(E49+I49)+(L49+N49) -> 1074883.8
A50: =A35 -> Jun | B50: =$B$6*N35 -> 374644.13 | C50: =(B35+C35+D35)/(E35*24*Supuestos!$B$16) -> 4584.0936 | D50: =MIN(B50*O35,C35) -> 374644.13 | E50: =D50*H35*O50 -> 663963.05 | F50: =((B35+C35+D35)-D50)/(E35*24*Supuestos!$B$16) -> 3671.218 | G50: =MIN(F35,C50) -> 3402 | H50: =MIN(F35,F50) -> 3402 | I50: =(G50-H50)*K35 -> 0 | J50: =IF(P35=0,0,MIN($D$6,$H$6/P35)) -> 691.34399 | K50: =MIN(MAX(F35-J50,0),F50) -> 2710.656 | L50: =(H50-K50)*K35 -> 277968.68 | M50: =IF(P35=0,0,MIN($H$6*Q35,D35)) -> 29036.447 | N50: =M50*J35-(M50/Supuestos!$B$18)*I35 -> 28191.457 | O50: 1 | P50: =M35+B35*I35+C35*H35+D35*J35+G50*K35+MIN(G35,C50)*L35 -> 4302834.7 | Q50: =(E50+I50)+(L50+N50) -> 970123.19
A51: =A36 -> Jul | B51: =$B$6*N36 -> 350612.26 | C51: =(B36+C36+D36)/(E36*24*Supuestos!$B$16) -> 4251.403 | D51: =MIN(B51*O36,C36) -> 350612.26 | E51: =D51*H36*O51 -> 621372.58 | F51: =((B36+C36+D36)-D51)/(E36*24*Supuestos!$B$16) -> 3424.6433 | G51: =MIN(F36,C51) -> 3369 | H51: =MIN(F36,F51) -> 3369 | I51: =(G51-H51)*K36 -> 0 | J51: =IF(P36=0,0,MIN($D$6,$H$6/P36)) -> 691.34399 | K51: =MIN(MAX(F36-J51,0),F51) -> 2677.656 | L51: =(H51-K51)*K36 -> 277968.68 | M51: =IF(P36=0,0,MIN($H$6*Q36,D36)) -> 31801.823 | N51: =M51*J36-(M51/Supuestos!$B$18)*I36 -> 30876.357 | O51: 1 | P51: =M36+B36*I36+C36*H36+D36*J36+G51*K36+MIN(G36,C51)*L36 -> 4219483.2 | Q51: =(E51+I51)+(L51+N51) -> 930217.61
A52: =A37 -> Ago | B52: =$B$6*N37 -> 333157.54 | C52: =(B37+C37+D37)/(E37*24*Supuestos!$B$16) -> 4582.0341 | D52: =MIN(B52*O37,C37) -> 333157.54 | E52: =D52*H37*O52 -> 590438.45 | F52: =((B37+C37+D37)-D52)/(E37*24*Supuestos!$B$16) -> 3796.4334 | G52: =MIN(F37,C52) -> 3760 | H52: =MIN(F37,F52) -> 3760 | I52: =(G52-H52)*K37 -> 0 | J52: =IF(P37=0,0,MIN($D$6,$H$6/P37)) -> 691.34399 | K52: =MIN(MAX(F37-J52,0),F52) -> 3068.656 | L52: =(H52-K52)*K37 -> 277968.68 | M52: =IF(P37=0,0,MIN($H$6*Q37,D37)) -> 29036.447 | N52: =M52*J37-(M52/Supuestos!$B$18)*I37 -> 28191.457 | O52: 1 | P52: =M37+B37*I37+C37*H37+D37*J37+G52*K37+MIN(G37,C52)*L37 -> 4526606.3 | Q52: =(E52+I52)+(L52+N52) -> 896598.58
A53: =A38 -> Sep | B53: =$B$6*N38 -> 320509.19 | C53: =(B38+C38+D38)/(E38*24*Supuestos!$B$16) -> 4147.7169 | D53: =MIN(B53*O38,C38) -> 320509.19 | E53: =D53*H38*O53 -> 568022.41 | F53: =((B38+C38+D38)-D53)/(E38*24*Supuestos!$B$16) -> 3366.7491 | G53: =MIN(F38,C53) -> 3451 | H53: =MIN(F38,F53) -> 3366.7491 | I53: =(G53-H53)*K38 -> 33874.779 | J53: =IF(P38=0,0,MIN($D$6,$H$6/P38)) -> 691.34399 | K53: =MIN(MAX(F38-J53,0),F53) -> 2759.656 | L53: =(H53-K53)*K38 -> 244093.9 | M53: =IF(P38=0,0,MIN($H$6*Q38,D38)) -> 29036.447 | N53: =M53*J38-(M53/Supuestos!$B$18)*I38 -> 28191.457 | O53: 1 | P53: =M38+B38*I38+C38*H38+D38*J38+G53*K38+MIN(G38,C53)*L38 -> 4047619.4 | Q53: =(E53+I53)+(L53+N53) -> 874182.54
A54: =A39 -> Oct | B54: =$B$6*N39 -> 371355.56 | C54: =(B39+C39+D39)/(E39*24*Supuestos!$B$16) -> 4541.3743 | D54: =MIN(B54*O39,C39) -> 371355.56 | E54: =D54*H39*O54 -> 658134.88 | F54: =((B39+C39+D39)-D54)/(E39*24*Supuestos!$B$16) -> 3665.7009 | G54: =MIN(F39,C54) -> 3682 | H54: =MIN(F39,F54) -> 3665.7009 | I54: =(G54-H54)*K39 -> 6553.3731 | J54: =IF(P39=0,0,MIN($D$6,$H$6/P39)) -> 691.34399 | K54: =MIN(MAX(F39-J54,0),F54) -> 2990.656 | L54: =(H54-K54)*K39 -> 271415.3 | M54: =IF(P39=0,0,MIN($H$6*Q39,D39)) -> 31801.823 | N54: =M54*J39-(M54/Supuestos!$B$18)*I39 -> 30876.357 | O54: 1 | P54: =M39+B39*I39+C39*H39+D39*J39+G54*K39+MIN(G39,C54)*L39 -> 4519428 | Q54: =(E54+I54)+(L54+N54) -> 966979.92
A55: =A40 -> Nov | B55: =$B$6*N40 -> 384256.87 | C55: =(B40+C40+D40)/(E40*24*Supuestos!$B$16) -> 4725.7992 | D55: =MIN(B55*O40,C40) -> 384256.87 | E55: =D55*H40*O55 -> 680999.24 | F55: =((B40+C40+D40)-D55)/(E40*24*Supuestos!$B$16) -> 3789.5008 | G55: =MIN(F40,C55) -> 3754 | H55: =MIN(F40,F55) -> 3754 | I55: =(G55-H55)*K40 -> 0 | J55: =IF(P40=0,0,MIN($D$6,$H$6/P40)) -> 345.67199 | K55: =MIN(MAX(F40-J55,0),F55) -> 3408.328 | L55: =(H55-K55)*K40 -> 138984.34 | M55: =IF(P40=0,0,MIN($H$6*Q40,D40)) -> 26271.071 | N55: =M55*J40-(M55/Supuestos!$B$18)*I40 -> 25506.556 | O55: 1 | P55: =M40+B40*I40+C40*H40+D40*J40+G55*K40+MIN(G40,C55)*L40 -> 4529699.1 | Q55: =(E55+I55)+(L55+N55) -> 845490.14
A56: =A41 -> Dic | B56: =$B$6*N41 -> 350106.33 | C56: =(B41+C41+D41)/(E41*24*Supuestos!$B$16) -> 4804.2374 | D56: =MIN(B56*O41,C41) -> 350106.33 | E56: =D56*H41*O56 -> 558428.35 | F56: =((B41+C41+D41)-D56)/(E41*24*Supuestos!$B$16) -> 3978.6707 | G56: =MIN(F41,C56) -> 4804.2374 | H56: =MIN(F41,F56) -> 3978.6707 | I56: =(G56-H56)*K41 -> 331935.6 | J56: =IF(P41=0,0,MIN($D$6,$H$6/P41)) -> 345.67199 | K56: =MIN(MAX(F41-J56,0),F56) -> 3978.6707 | L56: =(H56-K56)*K41 -> 0 | M56: =IF(P41=0,0,MIN($H$6*Q41,D41)) -> 30419.135 | N56: =M56*J41-(M56/Supuestos!$B$18)*I41 -> 29533.907 | O56: 0.9 | P56: =M41+B41*I41+C41*H41+D41*J41+G56*K41+MIN(G41,C56)*L41 -> 5145391.5 | Q56: =(E56+I56)+(L56+N56) -> 919897.86
A57: Recorte BESS = MIN(kW batería, entrega útil ÷ HrsP). Desc = MIN(entrega×DíasP, kWh punta). Arbitraje carga en base y descarga en punta. Fac.AA aplica el descuento de zafra (sólo Ixtlahuacán, pre-2032).
A58: 5. RESUMEN MENSUAL — Tarifa Actual (CFE pleno) / Ahorros / Costo con proyecto
A59: Mes | B59: kWh Consumo | C59: Gen PV kWh | D59: BESS desc kWh | E59: Tarifa Actual $ | F59: Ahorro PV $ | G59: Ahorro BESS $ | H59: Ahorro FP $ | I59: Costo c/proyecto $ | J59: Ahorro $ | K59: Ahorro %
A60: =A30 -> Ene | B60: =B30+C30+D30 -> 1659195 | C60: =B45 -> 372114.46 | D60: =M45 -> 30419.135 | E60: =(P45+R30)*$L$6 -> 4123951.4 | F60: =(E45+I45)*(1-IF(R30<0,-R30/P45,0)) -> 720364.91 | G60: =(L45+N45)*(1-IF(R30<0,-R30/P45,0)) -> 39329.69 | H60: =IF($J$6="Sí",MAX(0,R30),0) -> 0 | I60: =E60-F60-G60-H60 -> 3364256.8 | J60: =F60+G60+H60 -> 759694.6 | K60: =J60/E60 -> 0.18421522
A61: =A31 -> Feb | B61: =B31+C31+D31 -> 1435215 | C61: =B46 -> 360477.98 | D61: =M46 -> 26271.071 | E61: =(P46+R31)*$L$6 -> 3777056.5 | F61: =(E46+I46)*(1-IF(R31<0,-R31/P46,0)) -> 836393.73 | G61: =(L46+N46)*(1-IF(R31<0,-R31/P46,0)) -> 25506.556 | H61: =IF($J$6="Sí",MAX(0,R31),0) -> 0 | I61: =E61-F61-G61-H61 -> 2915156.2 | J61: =F61+G61+H61 -> 861900.29 | K61: =J61/E61 -> 0.22819364
A62: =A32 -> Mar | B62: =B32+C32+D32 -> 1918783 | C62: =B47 -> 456605.43 | D62: =M47 -> 27653.759 | E62: =(P47+R32)*$L$6 -> 4678324.4 | F62: =(E47+I47)*(1-IF(R32<0,-R32/P47,0)) -> 921051.7 | G62: =(L47+N47)*(1-IF(R32<0,-R32/P47,0)) -> 26793.882 | H62: =IF($J$6="Sí",MAX(0,R32),0) -> 0 | I62: =E62-F62-G62-H62 -> 3730478.9 | J62: =F62+G62+H62 -> 947845.58 | K62: =J62/E62 -> 0.20260364
A63: =A33 -> Abr | B63: =B33+C33+D33 -> 1871667 | C63: =B48 -> 426249.4 | D63: =M48 -> 30419.135 | E63: =(P48+R33)*$L$6 -> 4950056.4 | F63: =(E48+I48)*(1-IF(R33<0,-R33/P48,0)) -> 1096232.1 | G63: =(L48+N48)*(1-IF(R33<0,-R33/P48,0)) -> 29500.429 | H63: =IF($J$6="Sí",MAX(0,R33),0) -> 0 | I63: =E63-F63-G63-H63 -> 3824323.9 | J63: =F63+G63+H63 -> 1125732.5 | K63: =J63/E63 -> 0.22741812
A64: =A34 -> May | B64: =B34+C34+D34 -> 2054685 | C64: =B49 -> 411577.31 | D64: =M49 -> 29036.447 | E64: =(P49+R34)*$L$6 -> 5336855.5 | F64: =(E49+I49)*(1-IF(R34<0,-R34/P49,0)) -> 1046692.3 | G64: =(L49+N49)*(1-IF(R34<0,-R34/P49,0)) -> 28191.457 | H64: =IF($J$6="Sí",MAX(0,R34),0) -> 0 | I64: =E64-F64-G64-H64 -> 4261971.7 | J64: =F64+G64+H64 -> 1074883.8 | K64: =J64/E64 -> 0.2014077
A65: =A35 -> Jun | B65: =B35+C35+D35 -> 1881312 | C65: =B50 -> 374644.13 | D65: =M50 -> 29036.447 | E65: =(P50+R35)*$L$6 -> 4443949.4 | F65: =(E50+I50)*(1-IF(R35<0,-R35/P50,0)) -> 663963.05 | G65: =(L50+N50)*(1-IF(R35<0,-R35/P50,0)) -> 306160.13 | H65: =IF($J$6="Sí",MAX(0,R35),0) -> 0 | I65: =E65-F65-G65-H65 -> 3473826.3 | J65: =F65+G65+H65 -> 970123.19 | K65: =J65/E65 -> 0.21830203
A66: =A36 -> Jul | B66: =B36+C36+D36 -> 1802935 | C66: =B51 -> 350612.26 | D66: =M51 -> 31801.823 | E66: =(P51+R36)*$L$6 -> 4353080.3 | F66: =(E51+I51)*(1-IF(R36<0,-R36/P51,0)) -> 620690.44 | G66: =(L51+N51)*(1-IF(R36<0,-R36/P51,0)) -> 308505.98 | H66: =IF($J$6="Sí",MAX(0,R36),0) -> 0 | I66: =E66-F66-G66-H66 -> 3423883.9 | J66: =F66+G66+H66 -> 929196.43 | K66: =J66/E66 -> 0.21345722
A67: =A37 -> Ago | B67: =B37+C37+D37 -> 1943149 | C67: =B52 -> 333157.54 | D67: =M52 -> 29036.447 | E67: =(P52+R37)*$L$6 -> 4690295.8 | F67: =(E52+I52)*(1-IF(R37<0,-R37/P52,0)) -> 590438.45 | G67: =(L52+N52)*(1-IF(R37<0,-R37/P52,0)) -> 306160.13 | H67: =IF($J$6="Sí",MAX(0,R37),0) -> 0 | I67: =E67-F67-G67-H67 -> 3793697.2 | J67: =F67+G67+H67 -> 896598.58 | K67: =J67/E67 -> 0.19116035
A68: =A38 -> Sep | B68: =B38+C38+D38 -> 1702223 | C68: =B53 -> 320509.19 | D68: =M53 -> 29036.447 | E68: =(P53+R38)*$L$6 -> 4171388.7 | F68: =(E53+I53)*(1-IF(R38<0,-R38/P53,0)) -> 600604.88 | G68: =(L53+N53)*(1-IF(R38<0,-R38/P53,0)) -> 271700.74 | H68: =IF($J$6="Sí",MAX(0,R38),0) -> 0 | I68: =E68-F68-G68-H68 -> 3299083.1 | J68: =F68+G68+H68 -> 872305.63 | K68: =J68/E68 -> 0.20911636
A69: =A39 -> Oct | B69: =B39+C39+D39 -> 1925906 | C69: =B54 -> 371355.56 | D69: =M54 -> 31801.823 | E69: =(P54+R39)*$L$6 -> 4674873.5 | F69: =(E54+I54)*(1-IF(R39<0,-R39/P54,0)) -> 664688.26 | G69: =(L54+N54)*(1-IF(R39<0,-R39/P54,0)) -> 302291.66 | H69: =IF($J$6="Sí",MAX(0,R39),0) -> 0 | I69: =E69-F69-G69-H69 -> 3707893.6 | J69: =F69+G69+H69 -> 966979.92 | K69: =J69/E69 -> 0.20684622
A70: =A40 -> Nov | B70: =B40+C40+D40 -> 1939468 | C70: =B55 -> 384256.87 | D70: =M55 -> 26271.071 | E70: =(P55+R40)*$L$6 -> 4712976 | F70: =(E55+I55)*(1-IF(R40<0,-R40/P55,0)) -> 680999.24 | G70: =(L55+N55)*(1-IF(R40<0,-R40/P55,0)) -> 164490.89 | H70: =IF($J$6="Sí",MAX(0,R40),0) -> 0 | I70: =E70-F70-G70-H70 -> 3867485.9 | J70: =F70+G70+H70 -> 845490.14 | K70: =J70/E70 -> 0.17939623
A71: =A41 -> Dic | B71: =B41+C41+D41 -> 2037381 | C71: =B56 -> 350106.33 | D71: =M56 -> 30419.135 | E71: =(P56+R41)*$L$6 -> 5314153.2 | F71: =(E56+I56)*(1-IF(R41<0,-R41/P56,0)) -> 890363.95 | G71: =(L56+N56)*(1-IF(R41<0,-R41/P56,0)) -> 29533.907 | H71: =IF($J$6="Sí",MAX(0,R41),0) -> 0 | I71: =E71-F71-G71-H71 -> 4394255.3 | J71: =F71+G71+H71 -> 919897.86 | K71: =J71/E71 -> 0.17310338
A72: TOTAL | B72: =SUM(B60:B71) -> 22171919 | C72: =SUM(C60:C71) -> 4511666.4 | D72: =SUM(D60:D71) -> 351202.74 | E72: =SUM(E60:E71) -> 55226961 | F72: =SUM(F60:F71) -> 9332483 | G72: =SUM(G60:G71) -> 1838165.5 | H72: =SUM(H60:H71) -> 0 | I72: =SUM(I60:I71) -> 44056313 | J72: =SUM(J60:J71) -> 11170649 | K72: =J72/E72 -> 0.20226803
A73: Tarifa Actual (Σ) = recibo a CFE pleno $55,226,961 (dato workbook GEPP, calibrado del motor ×1.033). Ahorro = motor (golden 18/18).
A75: 6. PROYECCIÓN 20 AÑOS — Tarifa Actual con escalón 2032 · ahorros persisten · PPA se transfiere al cliente al término
A76: Bases año-0 (motor): | B76: PV con AA | C76: =F72 -> 9332483 | D76: PV CFE pleno | E76: =F72+SUMPRODUCT(E45:E56*(1/O45:O56-1)) -> 9753770.1 | F76: BESS | G76: =G72 -> 1838165.5 | H76: FP | I76: =H72 -> 0 | J76: Gen PV kWh | K76: =C72 -> 4511666.4
A77: Año | B77: Régimen | C77: Tarifa Actual $ | D77: Ah PV $ | E77: Ah BESS $ | F77: Ah FP $ | G77: Costo c/proy $ | H77: Flujo Compra $ | I77: Pago PPA $ | J77: Comisión $ | K77: Flujo Cliente PPA $ | L77: Flujo Financiador $
A78: 0 | B78: Inversión | H78: =-B26-B25-D25 -> -40520361 | K78: 0 | L78: =-B26-B25-D25 -> -40520361
A79: 1 | B79: =IF(A79<=(Supuestos!$B$22-Supuestos!$B$24),"Autoabasto","CFE pleno") -> Autoabasto | C79: =IF(A79<=(Supuestos!$B$22-Supuestos!$B$24),$B$12,$B$10)*(1+Supuestos!$B$8)^A79 -> 55697481 | D79: =IF(A79<=(Supuestos!$B$22-Supuestos!$B$24),$C$76,$E$76)*(1+Supuestos!$B$8)^A79*(1-Supuestos!$B$11)^A79 -> 9842969.9 | E79: =$G$76*(1+Supuestos!$B$8)^A79*(1-Supuestos!$B$12)^A79*Supuestos!$B$10 -> 1443074.8 | F79: =$I$76*(1+Supuestos!$B$8)^A79 -> 0 | G79: =C79-D79-E79-F79 -> 44411436 | H79: =D79+E79+F79-(Supuestos!$B$19*$B$6+Supuestos!$B$20*$F$6)*(1+Supuestos!$B$8)^(A79-1) -> 10237247 | I79: =IF(A79<=Supuestos!$J$28,$K$76*(1-Supuestos!$B$11)^A79*Supuestos!$I$28*(1+Supuestos!$B$9)^(A79-1),0) -> 6991337 | J79: =E79*Supuestos!$K$28 -> 721537.39 | K79: =D79-I79+E79-J79+F79-IF(A79<=Supuestos!$J$28,0,Supuestos!$B$19*$B$6*(1+Supuestos!$B$8)^(A79-1)) -> 3573170.3 | L79: =I79+J79-IF(A79<=Supuestos!$J$28,(Supuestos!$B$19*$B$6+Supuestos!$B$20*$F$6),Supuestos!$B$20*$F$6)*(1+Supuestos!$B$8)^(A79-1) -> 6664076.7
A80: 2 | B80: =IF(A80<=(Supuestos!$B$22-Supuestos!$B$24),"Autoabasto","CFE pleno") -> Autoabasto | C80: =IF(A80<=(Supuestos!$B$22-Supuestos!$B$24),$B$12,$B$10)*(1+Supuestos!$B$8)^A80 -> 59039329 | D80: =IF(A80<=(Supuestos!$B$22-Supuestos!$B$24),$C$76,$E$76)*(1+Supuestos!$B$8)^A80*(1-Supuestos!$B$11)^A80 -> 10381380 | E80: =$G$76*(1+Supuestos!$B$8)^A80*(1-Supuestos!$B$12)^A80*Supuestos!$B$10 -> 1510538.5 | F80: =$I$76*(1+Supuestos!$B$8)^A80 -> 0 | G80: =C80-D80-E80-F80 -> 47147410 | H80: =D80+E80+F80-(Supuestos!$B$19*$B$6+Supuestos!$B$20*$F$6)*(1+Supuestos!$B$8)^(A80-1) -> 10780193 | I80: =IF(A80<=Supuestos!$J$28,$K$76*(1-Supuestos!$B$11)^A80*Supuestos!$I$28*(1+Supuestos!$B$9)^(A80-1),0) -> 7304199.3 | J80: =E80*Supuestos!$K$28 -> 755269.26 | K80: =D80-I80+E80-J80+F80-IF(A80<=Supuestos!$J$28,0,Supuestos!$B$19*$B$6*(1+Supuestos!$B$8)^(A80-1)) -> 3832450.3 | L80: =I80+J80-IF(A80<=Supuestos!$J$28,(Supuestos!$B$19*$B$6+Supuestos!$B$20*$F$6),Supuestos!$B$20*$F$6)*(1+Supuestos!$B$8)^(A80-1) -> 6947743
A81: 3 | B81: =IF(A81<=(Supuestos!$B$22-Supuestos!$B$24),"Autoabasto","CFE pleno") -> Autoabasto | C81: =IF(A81<=(Supuestos!$B$22-Supuestos!$B$24),$B$12,$B$10)*(1+Supuestos!$B$8)^A81 -> 62581689 | D81: =IF(A81<=(Supuestos!$B$22-Supuestos!$B$24),$C$76,$E$76)*(1+Supuestos!$B$8)^A81*(1-Supuestos!$B$11)^A81 -> 10949242 | E81: =$G$76*(1+Supuestos!$B$8)^A81*(1-Supuestos!$B$12)^A81*Supuestos!$B$10 -> 1581156.2 | F81: =$I$76*(1+Supuestos!$B$8)^A81 -> 0 | G81: =C81-D81-E81-F81 -> 50051291 | H81: =D81+E81+F81-(Supuestos!$B$19*$B$6+Supuestos!$B$20*$F$6)*(1+Supuestos!$B$8)^(A81-1) -> 11351969 | I81: =IF(A81<=Supuestos!$J$28,$K$76*(1-Supuestos!$B$11)^A81*Supuestos!$I$28*(1+Supuestos!$B$9)^(A81-1),0) -> 7631062.2 | J81: =E81*Supuestos!$K$28 -> 790578.1 | K81: =D81-I81+E81-J81+F81-IF(A81<=Supuestos!$J$28,0,Supuestos!$B$19*$B$6*(1+Supuestos!$B$8)^(A81-1)) -> 4108757.7 | L81: =I81+J81-IF(A81<=Supuestos!$J$28,(Supuestos!$B$19*$B$6+Supuestos!$B$20*$F$6),Supuestos!$B$20*$F$6)*(1+Supuestos!$B$8)^(A81-1) -> 7243211.2
A82: 4 | B82: =IF(A82<=(Supuestos!$B$22-Supuestos!$B$24),"Autoabasto","CFE pleno") -> Autoabasto | C82: =IF(A82<=(Supuestos!$B$22-Supuestos!$B$24),$B$12,$B$10)*(1+Supuestos!$B$8)^A82 -> 66336590 | D82: =IF(A82<=(Supuestos!$B$22-Supuestos!$B$24),$C$76,$E$76)*(1+Supuestos!$B$8)^A82*(1-Supuestos!$B$11)^A82 -> 11548165 | E82: =$G$76*(1+Supuestos!$B$8)^A82*(1-Supuestos!$B$12)^A82*Supuestos!$B$10 -> 1655075.3 | F82: =$I$76*(1+Supuestos!$B$8)^A82 -> 0 | G82: =C82-D82-E82-F82 -> 53133350 | H82: =D82+E82+F82-(Supuestos!$B$19*$B$6+Supuestos!$B$20*$F$6)*(1+Supuestos!$B$8)^(A82-1) -> 11954106 | I82: =IF(A82<=Supuestos!$J$28,$K$76*(1-Supuestos!$B$11)^A82*Supuestos!$I$28*(1+Supuestos!$B$9)^(A82-1),0) -> 7972552.3 | J82: =E82*Supuestos!$K$28 -> 827537.63 | K82: =D82-I82+E82-J82+F82-IF(A82<=Supuestos!$J$28,0,Supuestos!$B$19*$B$6*(1+Supuestos!$B$8)^(A82-1)) -> 4403150.7 | L82: =I82+J82-IF(A82<=Supuestos!$J$28,(Supuestos!$B$19*$B$6+Supuestos!$B$20*$F$6),Supuestos!$B$20*$F$6)*(1+Supuestos!$B$8)^(A82-1) -> 7550955
A83: 5 | B83: =IF(A83<=(Supuestos!$B$22-Supuestos!$B$24),"Autoabasto","CFE pleno") -> Autoabasto | C83: =IF(A83<=(Supuestos!$B$22-Supuestos!$B$24),$B$12,$B$10)*(1+Supuestos!$B$8)^A83 -> 70316786 | D83: =IF(A83<=(Supuestos!$B$22-Supuestos!$B$24),$C$76,$E$76)*(1+Supuestos!$B$8)^A83*(1-Supuestos!$B$11)^A83 -> 12179850 | E83: =$G$76*(1+Supuestos!$B$8)^A83*(1-Supuestos!$B$12)^A83*Supuestos!$B$10 -> 1732450 | F83: =$I$76*(1+Supuestos!$B$8)^A83 -> 0 | G83: =C83-D83-E83-F83 -> 56404486 | H83: =D83+E83+F83-(Supuestos!$B$19*$B$6+Supuestos!$B$20*$F$6)*(1+Supuestos!$B$8)^(A83-1) -> 12588217 | I83: =IF(A83<=Supuestos!$J$28,$K$76*(1-Supuestos!$B$11)^A83*Supuestos!$I$28*(1+Supuestos!$B$9)^(A83-1),0) -> 8329324 | J83: =E83*Supuestos!$K$28 -> 866225.01 | K83: =D83-I83+E83-J83+F83-IF(A83<=Supuestos!$J$28,0,Supuestos!$B$19*$B$6*(1+Supuestos!$B$8)^(A83-1)) -> 4716751 | L83: =I83+J83-IF(A83<=Supuestos!$J$28,(Supuestos!$B$19*$B$6+Supuestos!$B$20*$F$6),Supuestos!$B$20*$F$6)*(1+Supuestos!$B$8)^(A83-1) -> 7871466
A84: 6 | B84: =IF(A84<=(Supuestos!$B$22-Supuestos!$B$24),"Autoabasto","CFE pleno") -> Autoabasto | C84: =IF(A84<=(Supuestos!$B$22-Supuestos!$B$24),$B$12,$B$10)*(1+Supuestos!$B$8)^A84 -> 74535793 | D84: =IF(A84<=(Supuestos!$B$22-Supuestos!$B$24),$C$76,$E$76)*(1+Supuestos!$B$8)^A84*(1-Supuestos!$B$11)^A84 -> 12846088 | E84: =$G$76*(1+Supuestos!$B$8)^A84*(1-Supuestos!$B$12)^A84*Supuestos!$B$10 -> 1813442.1 | F84: =$I$76*(1+Supuestos!$B$8)^A84 -> 0 | G84: =C84-D84-E84-F84 -> 59876263 | H84: =D84+E84+F84-(Supuestos!$B$19*$B$6+Supuestos!$B$20*$F$6)*(1+Supuestos!$B$8)^(A84-1) -> 13256002 | I84: =IF(A84<=Supuestos!$J$28,$K$76*(1-Supuestos!$B$11)^A84*Supuestos!$I$28*(1+Supuestos!$B$9)^(A84-1),0) -> 8702061.2 | J84: =E84*Supuestos!$K$28 -> 906721.03 | K84: =D84-I84+E84-J84+F84-IF(A84<=Supuestos!$J$28,0,Supuestos!$B$19*$B$6*(1+Supuestos!$B$8)^(A84-1)) -> 5050747.6 | L84: =I84+J84-IF(A84<=Supuestos!$J$28,(Supuestos!$B$19*$B$6+Supuestos!$B$20*$F$6),Supuestos!$B$20*$F$6)*(1+Supuestos!$B$8)^(A84-1) -> 8205254.3
A85: 7 | B85: =IF(A85<=(Supuestos!$B$22-Supuestos!$B$24),"Autoabasto","CFE pleno") -> CFE pleno | C85: =IF(A85<=(Supuestos!$B$22-Supuestos!$B$24),$B$12,$B$10)*(1+Supuestos!$B$8)^A85 -> 83040930 | D85: =IF(A85<=(Supuestos!$B$22-Supuestos!$B$24),$C$76,$E$76)*(1+Supuestos!$B$8)^A85*(1-Supuestos!$B$11)^A85 -> 14160387 | E85: =$G$76*(1+Supuestos!$B$8)^A85*(1-Supuestos!$B$12)^A85*Supuestos!$B$10 -> 1898220.5 | F85: =$I$76*(1+Supuestos!$B$8)^A85 -> 0 | G85: =C85-D85-E85-F85 -> 66982322 | H85: =D85+E85+F85-(Supuestos!$B$19*$B$6+Supuestos!$B$20*$F$6)*(1+Supuestos!$B$8)^(A85-1) -> 14570868 | I85: =IF(A85<=Supuestos!$J$28,$K$76*(1-Supuestos!$B$11)^A85*Supuestos!$I$28*(1+Supuestos!$B$9)^(A85-1),0) -> 9091478.5 | J85: =E85*Supuestos!$K$28 -> 949110.24 | K85: =D85-I85+E85-J85+F85-IF(A85<=Supuestos!$J$28,0,Supuestos!$B$19*$B$6*(1+Supuestos!$B$8)^(A85-1)) -> 6018019.2 | L85: =I85+J85-IF(A85<=Supuestos!$J$28,(Supuestos!$B$19*$B$6+Supuestos!$B$20*$F$6),Supuestos!$B$20*$F$6)*(1+Supuestos!$B$8)^(A85-1) -> 8552849.1
A86: 8 | B86: =IF(A86<=(Supuestos!$B$22-Supuestos!$B$24),"Autoabasto","CFE pleno") -> CFE pleno | C86: =IF(A86<=(Supuestos!$B$22-Supuestos!$B$24),$B$12,$B$10)*(1+Supuestos!$B$8)^A86 -> 88023386 | D86: =IF(A86<=(Supuestos!$B$22-Supuestos!$B$24),$C$76,$E$76)*(1+Supuestos!$B$8)^A86*(1-Supuestos!$B$11)^A86 -> 14934961 | E86: =$G$76*(1+Supuestos!$B$8)^A86*(1-Supuestos!$B$12)^A86*Supuestos!$B$10 -> 1986962.3 | F86: =$I$76*(1+Supuestos!$B$8)^A86 -> 0 | G86: =C86-D86-E86-F86 -> 71101463 | H86: =D86+E86+F86-(Supuestos!$B$19*$B$6+Supuestos!$B$20*$F$6)*(1+Supuestos!$B$8)^(A86-1) -> 15344919 | I86: =IF(A86<=Supuestos!$J$28,$K$76*(1-Supuestos!$B$11)^A86*Supuestos!$I$28*(1+Supuestos!$B$9)^(A86-1),0) -> 9498322.1 | J86: =E86*Supuestos!$K$28 -> 993481.14 | K86: =D86-I86+E86-J86+F86-IF(A86<=Supuestos!$J$28,0,Supuestos!$B$19*$B$6*(1+Supuestos!$B$8)^(A86-1)) -> 6430119.6 | L86: =I86+J86-IF(A86<=Supuestos!$J$28,(Supuestos!$B$19*$B$6+Supuestos!$B$20*$F$6),Supuestos!$B$20*$F$6)*(1+Supuestos!$B$8)^(A86-1) -> 8914799.3
A87: 9 | B87: =IF(A87<=(Supuestos!$B$22-Supuestos!$B$24),"Autoabasto","CFE pleno") -> CFE pleno | C87: =IF(A87<=(Supuestos!$B$22-Supuestos!$B$24),$B$12,$B$10)*(1+Supuestos!$B$8)^A87 -> 93304789 | D87: =IF(A87<=(Supuestos!$B$22-Supuestos!$B$24),$C$76,$E$76)*(1+Supuestos!$B$8)^A87*(1-Supuestos!$B$11)^A87 -> 15751903 | E87: =$G$76*(1+Supuestos!$B$8)^A87*(1-Supuestos!$B$12)^A87*Supuestos!$B$10 -> 2079852.8 | F87: =$I$76*(1+Supuestos!$B$8)^A87 -> 0 | G87: =C87-D87-E87-F87 -> 75473033 | H87: =D87+E87+F87-(Supuestos!$B$19*$B$6+Supuestos!$B$20*$F$6)*(1+Supuestos!$B$8)^(A87-1) -> 16160132 | I87: =IF(A87<=Supuestos!$J$28,$K$76*(1-Supuestos!$B$11)^A87*Supuestos!$I$28*(1+Supuestos!$B$9)^(A87-1),0) -> 9923372 | J87: =E87*Supuestos!$K$28 -> 1039926.4 | K87: =D87-I87+E87-J87+F87-IF(A87<=Supuestos!$J$28,0,Supuestos!$B$19*$B$6*(1+Supuestos!$B$8)^(A87-1)) -> 6868457.3 | L87: =I87+J87-IF(A87<=Supuestos!$J$28,(Supuestos!$B$19*$B$6+Supuestos!$B$20*$F$6),Supuestos!$B$20*$F$6)*(1+Supuestos!$B$8)^(A87-1) -> 9291674.2
A88: 10 | B88: =IF(A88<=(Supuestos!$B$22-Supuestos!$B$24),"Autoabasto","CFE pleno") -> CFE pleno | C88: =IF(A88<=(Supuestos!$B$22-Supuestos!$B$24),$B$12,$B$10)*(1+Supuestos!$B$8)^A88 -> 98903076 | D88: =IF(A88<=(Supuestos!$B$22-Supuestos!$B$24),$C$76,$E$76)*(1+Supuestos!$B$8)^A88*(1-Supuestos!$B$11)^A88 -> 16613532 | E88: =$G$76*(1+Supuestos!$B$8)^A88*(1-Supuestos!$B$12)^A88*Supuestos!$B$10 -> 2177085.9 | F88: =$I$76*(1+Supuestos!$B$8)^A88 -> 0 | G88: =C88-D88-E88-F88 -> 80112458 | H88: =D88+E88+F88-(Supuestos!$B$19*$B$6+Supuestos!$B$20*$F$6)*(1+Supuestos!$B$8)^(A88-1) -> 17018696 | I88: =IF(A88<=Supuestos!$J$28,$K$76*(1-Supuestos!$B$11)^A88*Supuestos!$I$28*(1+Supuestos!$B$9)^(A88-1),0) -> 10367443 | J88: =E88*Supuestos!$K$28 -> 1088542.9 | K88: =D88-I88+E88-J88+F88-IF(A88<=Supuestos!$J$28,0,Supuestos!$B$19*$B$6*(1+Supuestos!$B$8)^(A88-1)) -> 7334632.1 | L88: =I88+J88-IF(A88<=Supuestos!$J$28,(Supuestos!$B$19*$B$6+Supuestos!$B$20*$F$6),Supuestos!$B$20*$F$6)*(1+Supuestos!$B$8)^(A88-1) -> 9684064.2
A89: 11 | B89: =IF(A89<=(Supuestos!$B$22-Supuestos!$B$24),"Autoabasto","CFE pleno") -> CFE pleno | C89: =IF(A89<=(Supuestos!$B$22-Supuestos!$B$24),$B$12,$B$10)*(1+Supuestos!$B$8)^A89 -> 1.0483726e+08 | D89: =IF(A89<=(Supuestos!$B$22-Supuestos!$B$24),$C$76,$E$76)*(1+Supuestos!$B$8)^A89*(1-Supuestos!$B$11)^A89 -> 17522292 | E89: =$G$76*(1+Supuestos!$B$8)^A89*(1-Supuestos!$B$12)^A89*Supuestos!$B$10 -> 2278864.6 | F89: =$I$76*(1+Supuestos!$B$8)^A89 -> 0 | G89: =C89-D89-E89-F89 -> 85036104 | H89: =D89+E89+F89-(Supuestos!$B$19*$B$6+Supuestos!$B$20*$F$6)*(1+Supuestos!$B$8)^(A89-1) -> 17922920 | I89: =IF(A89<=Supuestos!$J$28,$K$76*(1-Supuestos!$B$11)^A89*Supuestos!$I$28*(1+Supuestos!$B$9)^(A89-1),0) -> 10831386 | J89: =E89*Supuestos!$K$28 -> 1139432.3 | K89: =D89-I89+E89-J89+F89-IF(A89<=Supuestos!$J$28,0,Supuestos!$B$19*$B$6*(1+Supuestos!$B$8)^(A89-1)) -> 7830338.6 | L89: =I89+J89-IF(A89<=Supuestos!$J$28,(Supuestos!$B$19*$B$6+Supuestos!$B$20*$F$6),Supuestos!$B$20*$F$6)*(1+Supuestos!$B$8)^(A89-1) -> 10092581
A90: 12 | B90: =IF(A90<=(Supuestos!$B$22-Supuestos!$B$24),"Autoabasto","CFE pleno") -> CFE pleno | C90: =IF(A90<=(Supuestos!$B$22-Supuestos!$B$24),$B$12,$B$10)*(1+Supuestos!$B$8)^A90 -> 1.111275e+08 | D90: =IF(A90<=(Supuestos!$B$22-Supuestos!$B$24),$C$76,$E$76)*(1+Supuestos!$B$8)^A90*(1-Supuestos!$B$11)^A90 -> 18480762 | E90: =$G$76*(1+Supuestos!$B$8)^A90*(1-Supuestos!$B$12)^A90*Supuestos!$B$10 -> 2385401.6 | F90: =$I$76*(1+Supuestos!$B$8)^A90 -> 0 | G90: =C90-D90-E90-F90 -> 90261333 | H90: =D90+E90+F90-(Supuestos!$B$19*$B$6+Supuestos!$B$20*$F$6)*(1+Supuestos!$B$8)^(A90-1) -> 18875232 | I90: =IF(A90<=Supuestos!$J$28,$K$76*(1-Supuestos!$B$11)^A90*Supuestos!$I$28*(1+Supuestos!$B$9)^(A90-1),0) -> 11316091 | J90: =E90*Supuestos!$K$28 -> 1192700.8 | K90: =D90-I90+E90-J90+F90-IF(A90<=Supuestos!$J$28,0,Supuestos!$B$19*$B$6*(1+Supuestos!$B$8)^(A90-1)) -> 8357371.9 | L90: =I90+J90-IF(A90<=Supuestos!$J$28,(Supuestos!$B$19*$B$6+Supuestos!$B$20*$F$6),Supuestos!$B$20*$F$6)*(1+Supuestos!$B$8)^(A90-1) -> 10517860
... A98: 20 | B98: =IF(A98<=(Supuestos!$B$22-Supuestos!$B$24),"Autoabasto","CFE pleno") -> CFE pleno | C98: =IF(A98<=(Supuestos!$B$22-Supuestos!$B$24),$B$12,$B$10)*(1+Supuestos!$B$8)^A98 -> 1.7712035e+08 | D98: =IF(A98<=(Supuestos!$B$22-Supuestos!$B$24),$C$76,$E$76)*(1+Supuestos!$B$8)^A98*(1-Supuestos!$B$11)^A98 -> 28297719 | E98: =$G$76*(1+Supuestos!$B$8)^A98*(1-Supuestos!$B$12)^A98*Supuestos!$B$10 -> 3437995.1 | F98: =$I$76*(1+Supuestos!$B$8)^A98 -> 0 | G98: =C98-D98-E98-F98 -> 1.4538463e+08 | H98: =D98+E98+F98-(Supuestos!$B$19*$B$6+Supuestos!$B$20*$F$6)*(1+Supuestos!$B$8)^(A98-1) -> 28562473 | I98: =IF(A98<=Supuestos!$J$28,$K$76*(1-Supuestos!$B$11)^A98*Supuestos!$I$28*(1+Supuestos!$B$9)^(A98-1),0) -> 0 | J98: =E98*Supuestos!$K$28 -> 1718997.6 | K98: =D98-I98+E98-J98+F98-IF(A98<=Supuestos!$J$28,0,Supuestos!$B$19*$B$6*(1+Supuestos!$B$8)^(A98-1)) -> 27644049 | L98: =I98+J98-IF(A98<=Supuestos!$J$28,(Supuestos!$B$19*$B$6+Supuestos!$B$20*$F$6),Supuestos!$B$20*$F$6)*(1+Supuestos!$B$8)^(A98-1) -> 918423.94
A99: Σ | H99: =SUM(H79:H98) -> 3.62027e+08 | K99: =SUM(K79:K98) -> 2.2192145e+08 | L99: =SUM(L79:L98) -> 1.4010554e+08
F100: TIR compra: | G100: =IRR(H78:H98) -> 0.30515621 | I100: VPN compra @WACC: | K100: =NPV(Supuestos!$B$7,H79:H98)+H78 -> 70517488
F101: TIR financiador: | G101: =IRR(L78:L98) -> 0.18294207 | I101: VPN cliente PPA @WACC: | K101: =NPV(Supuestos!$B$7,K79:K98)+K78 -> 53848827
A102: Régimen: Autoabasto años 1-6 (2026-2031); CFE pleno desde 2032 (escalón en Tarifa Actual). El ahorro PV/BESS/FP persiste los 20 años; tras el plazo PPA el PV se transfiere a GEPP y conserva el 100% del ahorro.
A104: 7. COMPRAR vs PPA / AHORRO COMPARTIDO
A105: Métrica | B105: GEPP COMPRA | C105: PPA / Ahorro compartido
A106: Inversión GEPP $ | B106: =B26+B25+D25 -> 40520361 | C106: 0 | D106: Financiador funda todo (incl. capacitor)
A107: Beneficio GEPP año 1 $ | B107: =H79 -> 10237247 | C107: =K79 -> 3573170.3
A108: Beneficio 20 años acum. $ | B108: =H99 -> 3.62027e+08 | C108: =SUM(K79:K98) -> 2.2192145e+08
A109: TIR (proyecto / financiador) | B109: =G100 -> 0.30515621 | C109: =G101 -> 0.18294207
A110: Tarifa PPA $/kWh (editable en Supuestos) | B110: — | C110: =Supuestos!$I$28 -> 1.5574
A111: Plazo PPA años / PV se transfiere al cliente al término | C111: =Supuestos!$J$28 -> 15
A113: 8. POR QUÉ ESTE DIMENSIONAMIENTO ES EL ÓPTIMO PARA ESTE SITIO
A114: PV 2,530 kWp se dimensiona al consumo intermedio diurno para autoconsumir sin exportar (>0.7 MW ⇒ Autoconsumo CNE). El BESS 850 kW/1,700 kWh recorta el pico de punta — la única palanca de demanda facturable bajo el umbral — sin sobredimensionar (sólo paga donde hay pico de punta facturable). No compite con Tala (estacional, zafra); la complementa y cubre el escalón 2032 al expirar el autoabasto. Más PV exportaría sin crédito de demanda; más BESS no recortaría más punta. Es el punto donde el ahorro se maximiza sin capex ocioso.

Sheet Acapulco
A1: ACAPULCO — Memoria de cálculo trazable y propuesta
A2: Medidor MX096Y · GDMTH SIN · Demanda contratada 2,271 kW · AUTOCONSUMO interconectado (>0.7 MW) — permiso SIMPLIFICADO CNE
A3: GEPP pide: Explorar PPA o Abasto Aislado
A5: PARÁMETROS DEL SISTEMA (desde Supuestos — edítalos allí)
A6: PV kWp | B6: =Supuestos!$B$29 -> 1020.305 | C6: BESS kW | D6: =Supuestos!$C$29 -> 250.5 | E6: BESS kWh | F6: =Supuestos!$D$29 -> 490 | G6: Entrega útil kWh | H6: =Supuestos!$D$29*Supuestos!$B$17*SQRT(Supuestos!$B$18) -> 460.89599 | I6: FP corr. | J6: =Supuestos!$E$29 -> Sí | K6: Calib→recibo | L6: =$B$10/(SUM(P45:P56)+SUM(R30:R41)) -> 1.0735938
A8: 1. ESTRUCTURA DE COSTO Y AHORRO (2025, pre-IVA · datos del workbook GEPP + motor)
A9: Concepto | B9: $ / año | C9: $ / kWh | D9: kWh | E9: Nota
A10: CFE BRUTO = Tarifa Actual (todo a CFE pleno, sin autoabasto) | B10: 28256362 | C10: =B10/D10 -> 3.1726605 | D10: 8906204 | E10: Lo que pagarían 100% en CFE sin ENEL/Tala ni PV/BESS
A11: (−) Ahorro autoabasto (—) | B11: 0 | E11: Sin autoabasto
A12: (=) Costo actual que paga GEPP hoy | B12: =B10-B11 -> 28256362 | C12: =B12/D12 -> 3.1726605 | D12: =D10 -> 8906204
A13: › CFE (tarifa CFE plena) | B13: 28256362 | C13: =B13/D13 -> 3.1726605 | D13: 8906204
A14: › sin autoabasto (100% CFE)
A16: Ahorros del proyecto (motor 2025, sobre la carga física):
A17: (−) Ahorro PV (energía intermedia + demanda vía umbral) | B17: =F72 -> 4175090 | D17: =C72 -> 1907358.2 | E17: Gen solar kWh/año →
A18: (−) Ahorro BESS (recorte de punta + arbitraje) | B18: =G72 -> 321375.64
A19: (−) Ahorro FP (corrección factor de potencia) | B19: =H72 -> 1716052.6 | E19: Multa FP impresa en el recibo (dato duro)
A20: (=) Costo neto con proyecto (hoy) | B20: =B12-B17-B18-B19 -> 22043843
A21: Ahorro proyecto PV+BESS+FP (vs costo hoy) | B21: =B17+B18+B19 -> 6212518.3 | C21: =B21/B12 -> 0.21986264
A22: Ahorro TOTAL vs CFE bruto (incl. autoabasto+proyecto) | B22: =B10-B20 -> 6212518.3 | C22: =B22/B10 -> 0.21986264
A24: 2. CAPEX (fórmulas vivas desde Supuestos)
A25: CAPEX PV = kWp×1000×USD/Wp×FX | B25: =$B$6*1000*Supuestos!$F$29*Supuestos!$B$5 -> 13429765 | C25: CAPEX BESS = kWh×USD/kWh×FX | D25: =$F$6*Supuestos!$G$29*Supuestos!$B$5 -> 2407860
A26: CAPEX Capacitor FP (financiador en PPA) | B26: =Supuestos!$H$29 -> 300000 | C26: CAPEX TOTAL (compra) | D26: =B25+D25+B26 -> 16137625 | E26: Bajo PPA, el capacitor lo paga el financiador → el cliente no desembolsa
A28: 3. ENTRADAS MENSUALES (AZUL = datos del recibo / recurso 2025)
A29: Mes | B29: kWh Base | C29: kWh Int | D29: kWh Punta | E29: Días | F29: Dem Pta kW | G29: Dem Máx kW | H29: T.Int $ | I29: T.Base $ | J29: T.Pta $ | K29: T.Cap $ | L29: T.Dist $ | M29: T.Fijo $ | N29: Rend | O29: %AC | P29: HrsP | Q29: DíasP | R29: Bonif FP
A30: Ene | B30: 195505 | C30: 377482 | D30: 103027 | E30: 31 | F30: 1540 | G30: 1666 | H30: 1.707525 | I30: 0.96695 | J30: 1.9327 | K30: 365.145 | L30: 221.09 | M30: 264.38 | N30: 159.7 | O30: 1 | P30: 4 | Q30: 22 | R30: 137543.92
A31: Feb | B31: 225267 | C31: 370816 | D31: 100217 | E31: 28 | F31: 1536 | G31: 1623 | H31: 1.707525 | I31: 0.96695 | J31: 1.9327 | K31: 365.145 | L31: 221.09 | M31: 264.38 | N31: 150.5 | O31: 1 | P31: 4 | Q31: 19 | R31: 134640.6
A32: Mar | B32: 312887 | C32: 449391 | D32: 103573 | E32: 31 | F32: 1493 | G32: 1605 | H32: 1.707525 | I32: 0.96695 | J32: 1.9327 | K32: 365.145 | L32: 221.09 | M32: 264.38 | N32: 184.5 | O32: 1 | P32: 4 | Q32: 20 | R32: 153664
A33: Abr | B33: 301373 | C33: 492059 | D33: 65557 | E33: 30 | F33: 1490 | G33: 1716 | H33: 1.707525 | I33: 0.96695 | J33: 1.9327 | K33: 365.145 | L33: 221.09 | M33: 264.38 | N33: 170.6 | O33: 1 | P33: 2 | Q33: 22 | R33: 148846.11
A34: May | B34: 312618 | C34: 506177 | D34: 49413 | E34: 31 | F34: 1582 | G34: 1715 | H34: 1.707525 | I34: 0.96695 | J34: 1.9327 | K34: 365.145 | L34: 221.09 | M34: 264.38 | N34: 166.4 | O34: 1 | P34: 2 | Q34: 21 | R34: 143046.14
A35: Jun | B35: 233673 | C35: 395913 | D35: 42282 | E35: 30 | F35: 1540 | G35: 1746 | H35: 1.707525 | I35: 0.96695 | J35: 1.9327 | K35: 365.145 | L35: 221.09 | M35: 264.38 | N35: 146.9 | O35: 1 | P35: 2 | Q35: 21 | R35: 139778.67
A36: Jul | B36: 213143 | C36: 485674 | D36: 56718 | E36: 31 | F36: 1627 | G36: 1781 | H36: 1.707525 | I36: 0.96695 | J36: 1.9327 | K36: 365.145 | L36: 221.09 | M36: 264.38 | N36: 157 | O36: 1 | P36: 2 | Q36: 23 | R36: 150698.91
A37: Ago | B37: 210539 | C37: 466847 | D37: 44577 | E37: 31 | F37: 1664 | G37: 1815 | H37: 1.707525 | I37: 0.96695 | J37: 1.9327 | K37: 365.145 | L37: 221.09 | M37: 264.38 | N37: 143.6 | O37: 1 | P37: 2 | Q37: 21 | R37: 147113.06
A38: Sep | B38: 197847 | C38: 411635 | D38: 49268 | E38: 30 | F38: 1692 | G38: 1776 | H38: 1.707525 | I38: 0.96695 | J38: 1.9327 | K38: 365.145 | L38: 221.09 | M38: 264.38 | N38: 129.8 | O38: 1 | P38: 2 | Q38: 21 | R38: 145342.3
A39: Oct | B39: 172712 | C39: 415203 | D39: 56344 | E39: 31 | F39: 1756 | G39: 1756 | H39: 1.707525 | I39: 0.96695 | J39: 1.9327 | K39: 365.145 | L39: 221.09 | M39: 264.38 | N39: 152.8 | O39: 1 | P39: 2 | Q39: 23 | R39: 135088.7
A40: Nov | B40: 248446 | C40: 348173 | D40: 86947 | E40: 30 | F40: 1638 | G40: 1734 | H40: 1.707525 | I40: 0.96695 | J40: 1.9327 | K40: 365.145 | L40: 221.09 | M40: 264.38 | N40: 154.3 | O40: 1 | P40: 4 | Q40: 19 | R40: 136386.42
A41: Dic | B41: 268553 | C41: 419527 | D41: 116821 | E41: 31 | F41: 1750 | G41: 1764 | H41: 1.707525 | I41: 0.96695 | J41: 1.9327 | K41: 365.145 | L41: 221.09 | M41: 264.38 | N41: 153.3 | O41: 1 | P41: 4 | Q41: 22 | R41: 143903.79
A42: 4. CÁLCULO DE AHORRO MENSUAL (motor — fórmulas que referencian las ENTRADAS)
A43: Mes | B43: Gen kWh | C43: Umbral kW | D43: Autocons | E43: Ah PV ener | F43: Umbral post | G43: Cap base | H43: Cap pre-B | I43: Ah PV dem | J43: Recorte BESS | K43: Cap post | L43: Ah BESS dem | M43: Desc kWh | N43: Arbitraje $ | O43: Fac.AA | P43: mem $ | Q43: Ah PV+BESS
A45: =A30 -> Ene | B45: =$B$6*N30 -> 162942.71 | C45: =(B30+C30+D30)/(E30*24*Supuestos!$B$16) -> 1594.0719 | D45: =MIN(B45*O30,C30) -> 162942.71 | E45: =D45*H30*O45 -> 278228.75 | F45: =((B30+C30+D30)-D45)/(E30*24*Supuestos!$B$16) -> 1209.8455 | G45: =MIN(F30,C45) -> 1540 | H45: =MIN(F30,F45) -> 1209.8455 | I45: =(G45-H45)*K30 -> 120554.25 | J45: =IF(P30=0,0,MIN($D$6,$H$6/P30)) -> 115.224 | K45: =MIN(MAX(F30-J45,0),F45) -> 1209.8455 | L45: =(H45-K45)*K30 -> 0 | M45: =IF(P30=0,0,MIN($H$6*Q30,D30)) -> 10139.712 | N45: =M45*J30-(M45/Supuestos!$B$18)*I30 -> 9383.9019 | O45: 1 | P45: =M30+B30*I30+C30*H30+D30*J30+G45*K30+MIN(G30,C45)*L30 -> 1947744.8 | Q45: =(E45+I45)+(L45+N45) -> 408166.9
A46: =A31 -> Feb | B46: =$B$6*N31 -> 153555.9 | C46: =(B31+C31+D31)/(E31*24*Supuestos!$B$16) -> 1817.8258 | D46: =MIN(B46*O31,C31) -> 153555.9 | E46: =D46*H31*O46 -> 262200.54 | F46: =((B31+C31+D31)-D46)/(E31*24*Supuestos!$B$16) -> 1416.9384 | G46: =MIN(F31,C46) -> 1536 | H46: =MIN(F31,F46) -> 1416.9384 | I46: =(G46-H46)*K31 -> 43474.736 | J46: =IF(P31=0,0,MIN($D$6,$H$6/P31)) -> 115.224 | K46: =MIN(MAX(F31-J46,0),F46) -> 1416.9384 | L46: =(H46-K46)*K31 -> 0 | M46: =IF(P31=0,0,MIN($H$6*Q31,D31)) -> 8757.0238 | N46: =M46*J31-(M46/Supuestos!$B$18)*I31 -> 8104.2789 | O46: 1 | P46: =M31+B31*I31+C31*H31+D31*J31+G46*K31+MIN(G31,C46)*L31 -> 1964645.1 | Q46: =(E46+I46)+(L46+N46) -> 313779.56
A47: =A32 -> Mar | B47: =$B$6*N32 -> 188246.27 | C47: =(B32+C32+D32)/(E32*24*Supuestos!$B$16) -> 2041.7162 | D47: =MIN(B47*O32,C32) -> 188246.27 | E47: =D47*H32*O47 -> 321435.22 | F47: =((B32+C32+D32)-D47)/(E32*24*Supuestos!$B$16) -> 1597.8229 | G47: =MIN(F32,C47) -> 1493 | H47: =MIN(F32,F47) -> 1493 | I47: =(G47-H47)*K32 -> 0 | J47: =IF(P32=0,0,MIN($D$6,$H$6/P32)) -> 115.224 | K47: =MIN(MAX(F32-J47,0),F47) -> 1377.776 | L47: =(H47-K47)*K32 -> 42073.467 | M47: =IF(P32=0,0,MIN($H$6*Q32,D32)) -> 9217.9198 | N47: =M47*J32-(M47/Supuestos!$B$18)*I32 -> 8530.8199 | O47: 1 | P47: =M32+B32*I32+C32*H32+D32*J32+G47*K32+MIN(G32,C47)*L32 -> 2170343.3 | Q47: =(E47+I47)+(L47+N47) -> 372039.5
A48: =A33 -> Abr | B48: =$B$6*N33 -> 174064.03 | C48: =(B33+C33+D33)/(E33*24*Supuestos!$B$16) -> 2093.0531 | D48: =MIN(B48*O33,C33) -> 174064.03 | E48: =D48*H33*O48 -> 297218.69 | F48: =((B33+C33+D33)-D48)/(E33*24*Supuestos!$B$16) -> 1668.9205 | G48: =MIN(F33,C48) -> 1490 | H48: =MIN(F33,F48) -> 1490 | I48: =(G48-H48)*K33 -> 0 | J48: =IF(P33=0,0,MIN($D$6,$H$6/P33)) -> 230.448 | K48: =MIN(MAX(F33-J48,0),F48) -> 1259.552 | L48: =(H48-K48)*K33 -> 84146.933 | M48: =IF(P33=0,0,MIN($H$6*Q33,D33)) -> 10139.712 | N48: =M48*J33-(M48/Supuestos!$B$18)*I33 -> 9383.9019 | O48: 1 | P48: =M33+B33*I33+C33*H33+D33*J33+G48*K33+MIN(G33,C48)*L33 -> 2182038.6 | Q48: =(E48+I48)+(L48+N48) -> 390749.52
A49: =A34 -> May | B49: =$B$6*N34 -> 169778.75 | C49: =(B34+C34+D34)/(E34*24*Supuestos!$B$16) -> 2047.2741 | D49: =MIN(B49*O34,C34) -> 169778.75 | E49: =D49*H34*O49 -> 289901.46 | F49: =((B34+C34+D34)-D49)/(E34*24*Supuestos!$B$16) -> 1646.9281 | G49: =MIN(F34,C49) -> 1582 | H49: =MIN(F34,F49) -> 1582 | I49: =(G49-H49)*K34 -> 0 | J49: =IF(P34=0,0,MIN($D$6,$H$6/P34)) -> 230.448 | K49: =MIN(MAX(F34-J49,0),F49) -> 1351.552 | L49: =(H49-K49)*K34 -> 84146.933 | M49: =IF(P34=0,0,MIN($H$6*Q34,D34)) -> 9678.8158 | N49: =M49*J34-(M49/Supuestos!$B$18)*I34 -> 8957.3609 | O49: 1 | P49: =M34+B34*I34+C34*H34+D34*J34+G49*K34+MIN(G34,C49)*L34 -> 2219189.5 | Q49: =(E49+I49)+(L49+N49) -> 383005.76
A50: =A35 -> Jun | B50: =$B$6*N35 -> 149882.8 | C50: =(B35+C35+D35)/(E35*24*Supuestos!$B$16) -> 1637.1053 | D50: =MIN(B50*O35,C35) -> 149882.8 | E50: =D50*H35*O50 -> 255928.64 | F50: =((B35+C35+D35)-D50)/(E35*24*Supuestos!$B$16) -> 1271.8938 | G50: =MIN(F35,C50) -> 1540 | H50: =MIN(F35,F50) -> 1271.8938 | I50: =(G50-H50)*K35 -> 97897.656 | J50: =IF(P35=0,0,MIN($D$6,$H$6/P35)) -> 230.448 | K50: =MIN(MAX(F35-J50,0),F50) -> 1271.8938 | L50: =(H50-K50)*K35 -> 0 | M50: =IF(P35=0,0,MIN($H$6*Q35,D35)) -> 9678.8158 | N50: =M50*J35-(M50/Supuestos!$B$18)*I35 -> 8957.3609 | O50: 1 | P50: =M35+B35*I35+C35*H35+D35*J35+G50*K35+MIN(G35,C50)*L35 -> 1908235.2 | Q50: =(E50+I50)+(L50+N50) -> 362783.65
A51: =A36 -> Jul | B51: =$B$6*N36 -> 160187.88 | C51: =(B36+C36+D36)/(E36*24*Supuestos!$B$16) -> 1781.586 | D51: =MIN(B51*O36,C36) -> 160187.88 | E51: =D51*H36*O51 -> 273524.82 | F51: =((B36+C36+D36)-D51)/(E36*24*Supuestos!$B$16) -> 1403.8557 | G51: =MIN(F36,C51) -> 1627 | H51: =MIN(F36,F51) -> 1403.8557 | I51: =(G51-H51)*K36 -> 81480.034 | J51: =IF(P36=0,0,MIN($D$6,$H$6/P36)) -> 230.448 | K51: =MIN(MAX(F36-J51,0),F51) -> 1396.552 | L51: =(H51-K51)*K36 -> 2666.8989 | M51: =IF(P36=0,0,MIN($H$6*Q36,D36)) -> 10600.608 | N51: =M51*J36-(M51/Supuestos!$B$18)*I36 -> 9810.4429 | O51: 1 | P51: =M36+B36*I36+C36*H36+D36*J36+G51*K36+MIN(G36,C51)*L36 -> 2133134.6 | Q51: =(E51+I51)+(L51+N51) -> 367482.19
A52: =A37 -> Ago | B52: =$B$6*N37 -> 146515.8 | C52: =(B37+C37+D37)/(E37*24*Supuestos!$B$16) -> 1702.4217 | D52: =MIN(B52*O37,C37) -> 146515.8 | E52: =D52*H37*O52 -> 250179.39 | F52: =((B37+C37+D37)-D52)/(E37*24*Supuestos!$B$16) -> 1356.9308 | G52: =MIN(F37,C52) -> 1664 | H52: =MIN(F37,F52) -> 1356.9308 | I52: =(G52-H52)*K37 -> 112124.79 | J52: =IF(P37=0,0,MIN($D$6,$H$6/P37)) -> 230.448 | K52: =MIN(MAX(F37-J52,0),F52) -> 1356.9308 | L52: =(H52-K52)*K37 -> 0 | M52: =IF(P37=0,0,MIN($H$6*Q37,D37)) -> 9678.8158 | N52: =M52*J37-(M52/Supuestos!$B$18)*I37 -> 8957.3609 | O52: 1 | P52: =M37+B37*I37+C37*H37+D37*J37+G52*K37+MIN(G37,C52)*L37 -> 2071141.7 | Q52: =(E52+I52)+(L52+N52) -> 371261.54
A53: =A38 -> Sep | B53: =$B$6*N38 -> 132435.59 | C53: =(B38+C38+D38)/(E38*24*Supuestos!$B$16) -> 1605.1413 | D53: =MIN(B53*O38,C38) -> 132435.59 | E53: =D53*H38*O53 -> 226137.08 | F53: =((B38+C38+D38)-D53)/(E38*24*Supuestos!$B$16) -> 1282.4425 | G53: =MIN(F38,C53) -> 1605.1413 | H53: =MIN(F38,F53) -> 1282.4425 | I53: =(G53-H53)*K38 -> 117831.85 | J53: =IF(P38=0,0,MIN($D$6,$H$6/P38)) -> 230.448 | K53: =MIN(MAX(F38-J53,0),F53) -> 1282.4425 | L53: =(H53-K53)*K38 -> 0 | M53: =IF(P38=0,0,MIN($H$6*Q38,D38)) -> 9678.8158 | N53: =M53*J38-(M53/Supuestos!$B$18)*I38 -> 8957.3609 | O53: 1 | P53: =M38+B38*I38+C38*H38+D38*J38+G53*K38+MIN(G38,C53)*L38 -> 1930659.9 | Q53: =(E53+I53)+(L53+N53) -> 352926.29
A54: =A39 -> Oct | B54: =$B$6*N39 -> 155902.6 | C54: =(B39+C39+D39)/(E39*24*Supuestos!$B$16) -> 1519.1921 | D54: =MIN(B54*O39,C39) -> 155902.6 | E54: =D54*H39*O54 -> 266207.59 | F54: =((B39+C39+D39)-D54)/(E39*24*Supuestos!$B$16) -> 1151.5667 | G54: =MIN(F39,C54) -> 1519.1921 | H54: =MIN(F39,F54) -> 1151.5667 | I54: =(G54-H54)*K39 -> 134236.6 | J54: =IF(P39=0,0,MIN($D$6,$H$6/P39)) -> 230.448 | K54: =MIN(MAX(F39-J54,0),F54) -> 1151.5667 | L54: =(H54-K54)*K39 -> 0 | M54: =IF(P39=0,0,MIN($H$6*Q39,D39)) -> 10600.608 | N54: =M54*J39-(M54/Supuestos!$B$18)*I39 -> 9810.4429 | O54: 1 | P54: =M39+B39*I39+C39*H39+D39*J39+G54*K39+MIN(G39,C54)*L39 -> 1875737.4 | Q54: =(E54+I54)+(L54+N54) -> 410254.63
A55: =A40 -> Nov | B55: =$B$6*N40 -> 157433.06 | C55: =(B40+C40+D40)/(E40*24*Supuestos!$B$16) -> 1665.6092 | D55: =MIN(B55*O40,C40) -> 157433.06 | E55: =D55*H40*O55 -> 268820.89 | F55: =((B40+C40+D40)-D55)/(E40*24*Supuestos!$B$16) -> 1282.0003 | G55: =MIN(F40,C55) -> 1638 | H55: =MIN(F40,F55) -> 1282.0003 | I55: =(G55-H55)*K40 -> 129991.5 | J55: =IF(P40=0,0,MIN($D$6,$H$6/P40)) -> 115.224 | K55: =MIN(MAX(F40-J55,0),F55) -> 1282.0003 | L55: =(H55-K55)*K40 -> 0 | M55: =IF(P40=0,0,MIN($H$6*Q40,D40)) -> 8757.0238 | N55: =M55*J40-(M55/Supuestos!$B$18)*I40 -> 8104.2789 | O55: 1 | P55: =M40+B40*I40+C40*H40+D40*J40+G55*K40+MIN(G40,C55)*L40 -> 1969412.8 | Q55: =(E55+I55)+(L55+N55) -> 406916.66
A56: =A41 -> Dic | B56: =$B$6*N41 -> 156412.76 | C56: =(B41+C41+D41)/(E41*24*Supuestos!$B$16) -> 1897.9933 | D56: =MIN(B56*O41,C41) -> 156412.76 | E56: =D56*H41*O56 -> 267078.69 | F56: =((B41+C41+D41)-D56)/(E41*24*Supuestos!$B$16) -> 1529.1649 | G56: =MIN(F41,C56) -> 1750 | H56: =MIN(F41,F56) -> 1529.1649 | I56: =(G56-H56)*K41 -> 80636.839 | J56: =IF(P41=0,0,MIN($D$6,$H$6/P41)) -> 115.224 | K56: =MIN(MAX(F41-J56,0),F56) -> 1529.1649 | L56: =(H56-K56)*K41 -> 0 | M56: =IF(P41=0,0,MIN($H$6*Q41,D41)) -> 10139.712 | N56: =M56*J41-(M56/Supuestos!$B$18)*I41 -> 9383.9019 | O56: 1 | P56: =M41+B41*I41+C41*H41+D41*J41+G56*K41+MIN(G41,C56)*L41 -> 2231081 | Q56: =(E56+I56)+(L56+N56) -> 357099.43
A57: Recorte BESS = MIN(kW batería, entrega útil ÷ HrsP). Desc = MIN(entrega×DíasP, kWh punta). Arbitraje carga en base y descarga en punta. Fac.AA aplica el descuento de zafra (sólo Ixtlahuacán, pre-2032).
A58: 5. RESUMEN MENSUAL — Tarifa Actual (CFE pleno) / Ahorros / Costo con proyecto
A59: Mes | B59: kWh Consumo | C59: Gen PV kWh | D59: BESS desc kWh | E59: Tarifa Actual $ | F59: Ahorro PV $ | G59: Ahorro BESS $ | H59: Ahorro FP $ | I59: Costo c/proyecto $ | J59: Ahorro $ | K59: Ahorro %
A60: =A30 -> Ene | B60: =B30+C30+D30 -> 676014 | C60: =B45 -> 162942.71 | D60: =M45 -> 10139.712 | E60: =(P45+R30)*$L$6 -> 2238753 | F60: =(E45+I45)*(1-IF(R30<0,-R30/P45,0)) -> 398783 | G60: =(L45+N45)*(1-IF(R30<0,-R30/P45,0)) -> 9383.9019 | H60: =IF($J$6="Sí",MAX(0,R30),0) -> 137543.92 | I60: =E60-F60-G60-H60 -> 1693042.2 | J60: =F60+G60+H60 -> 545710.82 | K60: =J60/E60 -> 0.2437566
A61: =A31 -> Feb | B61: =B31+C31+D31 -> 696300 | C61: =B46 -> 153555.9 | D61: =M46 -> 8757.0238 | E61: =(P46+R31)*$L$6 -> 2253780 | F61: =(E46+I46)*(1-IF(R31<0,-R31/P46,0)) -> 305675.28 | G61: =(L46+N46)*(1-IF(R31<0,-R31/P46,0)) -> 8104.2789 | H61: =IF($J$6="Sí",MAX(0,R31),0) -> 134640.6 | I61: =E61-F61-G61-H61 -> 1805359.9 | J61: =F61+G61+H61 -> 448420.16 | K61: =J61/E61 -> 0.19896359
A62: =A32 -> Mar | B62: =B32+C32+D32 -> 865851 | C62: =B47 -> 188246.27 | D62: =M47 -> 9217.9198 | E62: =(P47+R32)*$L$6 -> 2495039.8 | F62: =(E47+I47)*(1-IF(R32<0,-R32/P47,0)) -> 321435.22 | G62: =(L47+N47)*(1-IF(R32<0,-R32/P47,0)) -> 50604.286 | H62: =IF($J$6="Sí",MAX(0,R32),0) -> 153664 | I62: =E62-F62-G62-H62 -> 1969336.3 | J62: =F62+G62+H62 -> 525703.5 | K62: =J62/E62 -> 0.21069945
A63: =A33 -> Abr | B63: =B33+C33+D33 -> 858989 | C63: =B48 -> 174064.03 | D63: =M48 -> 10139.712 | E63: =(P48+R33)*$L$6 -> 2502423.3 | F63: =(E48+I48)*(1-IF(R33<0,-R33/P48,0)) -> 297218.69 | G63: =(L48+N48)*(1-IF(R33<0,-R33/P48,0)) -> 93530.835 | H63: =IF($J$6="Sí",MAX(0,R33),0) -> 148846.11 | I63: =E63-F63-G63-H63 -> 1962827.6 | J63: =F63+G63+H63 -> 539595.63 | K63: =J63/E63 -> 0.21562924
A64: =A34 -> May | B64: =B34+C34+D34 -> 868208 | C64: =B49 -> 169778.75 | D64: =M49 -> 9678.8158 | E64: =(P49+R34)*$L$6 -> 2536081.5 | F64: =(E49+I49)*(1-IF(R34<0,-R34/P49,0)) -> 289901.46 | G64: =(L49+N49)*(1-IF(R34<0,-R34/P49,0)) -> 93104.294 | H64: =IF($J$6="Sí",MAX(0,R34),0) -> 143046.14 | I64: =E64-F64-G64-H64 -> 2010029.6 | J64: =F64+G64+H64 -> 526051.9 | K64: =J64/E64 -> 0.20742705
A65: =A35 -> Jun | B65: =B35+C35+D35 -> 671868 | C65: =B50 -> 149882.8 | D65: =M50 -> 9678.8158 | E65: =(P50+R35)*$L$6 -> 2198734.9 | F65: =(E50+I50)*(1-IF(R35<0,-R35/P50,0)) -> 353826.29 | G65: =(L50+N50)*(1-IF(R35<0,-R35/P50,0)) -> 8957.3609 | H65: =IF($J$6="Sí",MAX(0,R35),0) -> 139778.67 | I65: =E65-F65-G65-H65 -> 1696172.6 | J65: =F65+G65+H65 -> 502562.32 | K65: =J65/E65 -> 0.22856886
A66: =A36 -> Jul | B66: =B36+C36+D36 -> 755535 | C66: =B51 -> 160187.88 | D66: =M51 -> 10600.608 | E66: =(P51+R36)*$L$6 -> 2451909.4 | F66: =(E51+I51)*(1-IF(R36<0,-R36/P51,0)) -> 355004.85 | G66: =(L51+N51)*(1-IF(R36<0,-R36/P51,0)) -> 12477.342 | H66: =IF($J$6="Sí",MAX(0,R36),0) -> 150698.91 | I66: =E66-F66-G66-H66 -> 1933728.3 | J66: =F66+G66+H66 -> 518181.1 | K66: =J66/E66 -> 0.21133778
A67: =A37 -> Ago | B67: =B37+C37+D37 -> 721963 | C67: =B52 -> 146515.8 | D67: =M52 -> 9678.8158 | E67: =(P52+R37)*$L$6 -> 2381504.5 | F67: =(E52+I52)*(1-IF(R37<0,-R37/P52,0)) -> 362304.18 | G67: =(L52+N52)*(1-IF(R37<0,-R37/P52,0)) -> 8957.3609 | H67: =IF($J$6="Sí",MAX(0,R37),0) -> 147113.06 | I67: =E67-F67-G67-H67 -> 1863129.9 | J67: =F67+G67+H67 -> 518374.6 | K67: =J67/E67 -> 0.21766686
A68: =A38 -> Sep | B68: =B38+C38+D38 -> 658750 | C68: =B53 -> 132435.59 | D68: =M53 -> 9678.8158 | E68: =(P53+R38)*$L$6 -> 2228783 | F68: =(E53+I53)*(1-IF(R38<0,-R38/P53,0)) -> 343968.93 | G68: =(L53+N53)*(1-IF(R38<0,-R38/P53,0)) -> 8957.3609 | H68: =IF($J$6="Sí",MAX(0,R38),0) -> 145342.3 | I68: =E68-F68-G68-H68 -> 1730514.4 | J68: =F68+G68+H68 -> 498268.59 | K68: =J68/E68 -> 0.22356084
A69: =A39 -> Oct | B69: =B39+C39+D39 -> 644259 | C69: =B54 -> 155902.6 | D69: =M54 -> 10600.608 | E69: =(P54+R39)*$L$6 -> 2158810.4 | F69: =(E54+I54)*(1-IF(R39<0,-R39/P54,0)) -> 400444.19 | G69: =(L54+N54)*(1-IF(R39<0,-R39/P54,0)) -> 9810.4429 | H69: =IF($J$6="Sí",MAX(0,R39),0) -> 135088.7 | I69: =E69-F69-G69-H69 -> 1613467.1 | J69: =F69+G69+H69 -> 545343.33 | K69: =J69/E69 -> 0.25261289
A70: =A40 -> Nov | B70: =B40+C40+D40 -> 683566 | C70: =B55 -> 157433.06 | D70: =M55 -> 8757.0238 | E70: =(P55+R40)*$L$6 -> 2260773 | F70: =(E55+I55)*(1-IF(R40<0,-R40/P55,0)) -> 398812.39 | G70: =(L55+N55)*(1-IF(R40<0,-R40/P55,0)) -> 8104.2789 | H70: =IF($J$6="Sí",MAX(0,R40),0) -> 136386.42 | I70: =E70-F70-G70-H70 -> 1717469.9 | J70: =F70+G70+H70 -> 543303.08 | K70: =J70/E70 -> 0.2403174
A71: =A41 -> Dic | B71: =B41+C41+D41 -> 804901 | C71: =B56 -> 156412.76 | D71: =M56 -> 10139.712 | E71: =(P56+R41)*$L$6 -> 2549768.9 | F71: =(E56+I56)*(1-IF(R41<0,-R41/P56,0)) -> 347715.53 | G71: =(L56+N56)*(1-IF(R41<0,-R41/P56,0)) -> 9383.9019 | H71: =IF($J$6="Sí",MAX(0,R41),0) -> 143903.79 | I71: =E71-F71-G71-H71 -> 2048765.7 | J71: =F71+G71+H71 -> 501003.22 | K71: =J71/E71 -> 0.19648966
A72: TOTAL | B72: =SUM(B60:B71) -> 8906204 | C72: =SUM(C60:C71) -> 1907358.2 | D72: =SUM(D60:D71) -> 117067.58 | E72: =SUM(E60:E71) -> 28256362 | F72: =SUM(F60:F71) -> 4175090 | G72: =SUM(G60:G71) -> 321375.64 | H72: =SUM(H60:H71) -> 1716052.6 | I72: =SUM(I60:I71) -> 22043843 | J72: =SUM(J60:J71) -> 6212518.3 | K72: =J72/E72 -> 0.21986264
A73: Tarifa Actual (Σ) = recibo a CFE pleno $28,256,362 (dato workbook GEPP, calibrado del motor ×1.074). Ahorro = motor (golden 18/18).
A75: 6. PROYECCIÓN 20 AÑOS — Tarifa Actual con escalón 2032 · ahorros persisten · PPA se transfiere al cliente al término
A76: Bases año-0 (motor): | B76: PV con AA | C76: =F72 -> 4175090 | D76: PV CFE pleno | E76: =F72+SUMPRODUCT(E45:E56*(1/O45:O56-1)) -> 4175090 | F76: BESS | G76: =G72 -> 321375.64 | H76: FP | I76: =H72 -> 1716052.6 | J76: Gen PV kWh | K76: =C72 -> 1907358.2
A77: Año | B77: Régimen | C77: Tarifa Actual $ | D77: Ah PV $ | E77: Ah BESS $ | F77: Ah FP $ | G77: Costo c/proy $ | H77: Flujo Compra $ | I77: Pago PPA $ | J77: Comisión $ | K77: Flujo Cliente PPA $ | L77: Flujo Financiador $
A78: 0 | B78: Inversión | H78: =-B26-B25-D25 -> -16137625 | K78: 0 | L78: =-B26-B25-D25 -> -16137625
A79: 1 | B79: =IF(A79<=(Supuestos!$B$22-Supuestos!$B$24),"Autoabasto","CFE pleno") -> Autoabasto | C79: =IF(A79<=(Supuestos!$B$22-Supuestos!$B$24),$B$12,$B$10)*(1+Supuestos!$B$8)^A79 -> 29951743 | D79: =IF(A79<=(Supuestos!$B$22-Supuestos!$B$24),$C$76,$E$76)*(1+Supuestos!$B$8)^A79*(1-Supuestos!$B$11)^A79 -> 4403467.4 | E79: =$G$76*(1+Supuestos!$B$8)^A79*(1-Supuestos!$B$12)^A79*Supuestos!$B$10 -> 252299.97 | F79: =$I$76*(1+Supuestos!$B$8)^A79 -> 1819015.8 | G79: =C79-D79-E79-F79 -> 23476960 | H79: =D79+E79+F79-(Supuestos!$B$19*$B$6+Supuestos!$B$20*$F$6)*(1+Supuestos!$B$8)^(A79-1) -> 6070288.6 | I79: =IF(A79<=Supuestos!$J$29,$K$76*(1-Supuestos!$B$11)^A79*Supuestos!$I$29*(1+Supuestos!$B$9)^(A79-1),0) -> 2994951.9 | J79: =E79*Supuestos!$K$29 -> 126149.98 | K79: =D79-I79+E79-J79+F79-IF(A79<=Supuestos!$J$29,0,Supuestos!$B$19*$B$6*(1+Supuestos!$B$8)^(A79-1)) -> 3353681.3 | L79: =I79+J79-IF(A79<=Supuestos!$J$29,(Supuestos!$B$19*$B$6+Supuestos!$B$20*$F$6),Supuestos!$B$20*$F$6)*(1+Supuestos!$B$8)^(A79-1) -> 2716607.3
A80: 2 | B80: =IF(A80<=(Supuestos!$B$22-Supuestos!$B$24),"Autoabasto","CFE pleno") -> Autoabasto | C80: =IF(A80<=(Supuestos!$B$22-Supuestos!$B$24),$B$12,$B$10)*(1+Supuestos!$B$8)^A80 -> 31748848 | D80: =IF(A80<=(Supuestos!$B$22-Supuestos!$B$24),$C$76,$E$76)*(1+Supuestos!$B$8)^A80*(1-Supuestos!$B$11)^A80 -> 4644337.1 | E80: =$G$76*(1+Supuestos!$B$8)^A80*(1-Supuestos!$B$12)^A80*Supuestos!$B$10 -> 264094.99 | F80: =$I$76*(1+Supuestos!$B$8)^A80 -> 1928156.7 | G80: =C80-D80-E80-F80 -> 24912259 | H80: =D80+E80+F80-(Supuestos!$B$19*$B$6+Supuestos!$B$20*$F$6)*(1+Supuestos!$B$8)^(A80-1) -> 6407824.6 | I80: =IF(A80<=Supuestos!$J$29,$K$76*(1-Supuestos!$B$11)^A80*Supuestos!$I$29*(1+Supuestos!$B$9)^(A80-1),0) -> 3128976 | J80: =E80*Supuestos!$K$29 -> 132047.5 | K80: =D80-I80+E80-J80+F80-IF(A80<=Supuestos!$J$29,0,Supuestos!$B$19*$B$6*(1+Supuestos!$B$8)^(A80-1)) -> 3575565.3 | L80: =I80+J80-IF(A80<=Supuestos!$J$29,(Supuestos!$B$19*$B$6+Supuestos!$B$20*$F$6),Supuestos!$B$20*$F$6)*(1+Supuestos!$B$8)^(A80-1) -> 2832259.3
A81: 3 | B81: =IF(A81<=(Supuestos!$B$22-Supuestos!$B$24),"Autoabasto","CFE pleno") -> Autoabasto | C81: =IF(A81<=(Supuestos!$B$22-Supuestos!$B$24),$B$12,$B$10)*(1+Supuestos!$B$8)^A81 -> 33653779 | D81: =IF(A81<=(Supuestos!$B$22-Supuestos!$B$24),$C$76,$E$76)*(1+Supuestos!$B$8)^A81*(1-Supuestos!$B$11)^A81 -> 4898382.3 | E81: =$G$76*(1+Supuestos!$B$8)^A81*(1-Supuestos!$B$12)^A81*Supuestos!$B$10 -> 276441.43 | F81: =$I$76*(1+Supuestos!$B$8)^A81 -> 2043846.1 | G81: =C81-D81-E81-F81 -> 26435109 | H81: =D81+E81+F81-(Supuestos!$B$19*$B$6+Supuestos!$B$20*$F$6)*(1+Supuestos!$B$8)^(A81-1) -> 6764179.8 | I81: =IF(A81<=Supuestos!$J$29,$K$76*(1-Supuestos!$B$11)^A81*Supuestos!$I$29*(1+Supuestos!$B$9)^(A81-1),0) -> 3268997.7 | J81: =E81*Supuestos!$K$29 -> 138220.72 | K81: =D81-I81+E81-J81+F81-IF(A81<=Supuestos!$J$29,0,Supuestos!$B$19*$B$6*(1+Supuestos!$B$8)^(A81-1)) -> 3811451.5 | L81: =I81+J81-IF(A81<=Supuestos!$J$29,(Supuestos!$B$19*$B$6+Supuestos!$B$20*$F$6),Supuestos!$B$20*$F$6)*(1+Supuestos!$B$8)^(A81-1) -> 2952728.3
A82: 4 | B82: =IF(A82<=(Supuestos!$B$22-Supuestos!$B$24),"Autoabasto","CFE pleno") -> Autoabasto | C82: =IF(A82<=(Supuestos!$B$22-Supuestos!$B$24),$B$12,$B$10)*(1+Supuestos!$B$8)^A82 -> 35673006 | D82: =IF(A82<=(Supuestos!$B$22-Supuestos!$B$24),$C$76,$E$76)*(1+Supuestos!$B$8)^A82*(1-Supuestos!$B$11)^A82 -> 5166323.9 | E82: =$G$76*(1+Supuestos!$B$8)^A82*(1-Supuestos!$B$12)^A82*Supuestos!$B$10 -> 289365.07 | F82: =$I$76*(1+Supuestos!$B$8)^A82 -> 2166476.9 | G82: =C82-D82-E82-F82 -> 28050840 | H82: =D82+E82+F82-(Supuestos!$B$19*$B$6+Supuestos!$B$20*$F$6)*(1+Supuestos!$B$8)^(A82-1) -> 7140406.3 | I82: =IF(A82<=Supuestos!$J$29,$K$76*(1-Supuestos!$B$11)^A82*Supuestos!$I$29*(1+Supuestos!$B$9)^(A82-1),0) -> 3415285.3 | J82: =E82*Supuestos!$K$29 -> 144682.53 | K82: =D82-I82+E82-J82+F82-IF(A82<=Supuestos!$J$29,0,Supuestos!$B$19*$B$6*(1+Supuestos!$B$8)^(A82-1)) -> 4062198 | L82: =I82+J82-IF(A82<=Supuestos!$J$29,(Supuestos!$B$19*$B$6+Supuestos!$B$20*$F$6),Supuestos!$B$20*$F$6)*(1+Supuestos!$B$8)^(A82-1) -> 3078208.4
A83: 5 | B83: =IF(A83<=(Supuestos!$B$22-Supuestos!$B$24),"Autoabasto","CFE pleno") -> Autoabasto | C83: =IF(A83<=(Supuestos!$B$22-Supuestos!$B$24),$B$12,$B$10)*(1+Supuestos!$B$8)^A83 -> 37813386 | D83: =IF(A83<=(Supuestos!$B$22-Supuestos!$B$24),$C$76,$E$76)*(1+Supuestos!$B$8)^A83*(1-Supuestos!$B$11)^A83 -> 5448921.8 | E83: =$G$76*(1+Supuestos!$B$8)^A83*(1-Supuestos!$B$12)^A83*Supuestos!$B$10 -> 302892.88 | F83: =$I$76*(1+Supuestos!$B$8)^A83 -> 2296465.5 | G83: =C83-D83-E83-F83 -> 29765106 | H83: =D83+E83+F83-(Supuestos!$B$19*$B$6+Supuestos!$B$20*$F$6)*(1+Supuestos!$B$8)^(A83-1) -> 7537615.1 | I83: =IF(A83<=Supuestos!$J$29,$K$76*(1-Supuestos!$B$11)^A83*Supuestos!$I$29*(1+Supuestos!$B$9)^(A83-1),0) -> 3568119.4 | J83: =E83*Supuestos!$K$29 -> 151446.44 | K83: =D83-I83+E83-J83+F83-IF(A83<=Supuestos!$J$29,0,Supuestos!$B$19*$B$6*(1+Supuestos!$B$8)^(A83-1)) -> 4328714.4 | L83: =I83+J83-IF(A83<=Supuestos!$J$29,(Supuestos!$B$19*$B$6+Supuestos!$B$20*$F$6),Supuestos!$B$20*$F$6)*(1+Supuestos!$B$8)^(A83-1) -> 3208900.7
A84: 6 | B84: =IF(A84<=(Supuestos!$B$22-Supuestos!$B$24),"Autoabasto","CFE pleno") -> Autoabasto | C84: =IF(A84<=(Supuestos!$B$22-Supuestos!$B$24),$B$12,$B$10)*(1+Supuestos!$B$8)^A84 -> 40082189 | D84: =IF(A84<=(Supuestos!$B$22-Supuestos!$B$24),$C$76,$E$76)*(1+Supuestos!$B$8)^A84*(1-Supuestos!$B$11)^A84 -> 5746977.8 | E84: =$G$76*(1+Supuestos!$B$8)^A84*(1-Supuestos!$B$12)^A84*Supuestos!$B$10 -> 317053.13 | F84: =$I$76*(1+Supuestos!$B$8)^A84 -> 2434253.4 | G84: =C84-D84-E84-F84 -> 31583905 | H84: =D84+E84+F84-(Supuestos!$B$19*$B$6+Supuestos!$B$20*$F$6)*(1+Supuestos!$B$8)^(A84-1) -> 7956979.4 | I84: =IF(A84<=Supuestos!$J$29,$K$76*(1-Supuestos!$B$11)^A84*Supuestos!$I$29*(1+Supuestos!$B$9)^(A84-1),0) -> 3727792.7 | J84: =E84*Supuestos!$K$29 -> 158526.56 | K84: =D84-I84+E84-J84+F84-IF(A84<=Supuestos!$J$29,0,Supuestos!$B$19*$B$6*(1+Supuestos!$B$8)^(A84-1)) -> 4611965.1 | L84: =I84+J84-IF(A84<=Supuestos!$J$29,(Supuestos!$B$19*$B$6+Supuestos!$B$20*$F$6),Supuestos!$B$20*$F$6)*(1+Supuestos!$B$8)^(A84-1) -> 3345014.3
A85: 7 | B85: =IF(A85<=(Supuestos!$B$22-Supuestos!$B$24),"Autoabasto","CFE pleno") -> CFE pleno | C85: =IF(A85<=(Supuestos!$B$22-Supuestos!$B$24),$B$12,$B$10)*(1+Supuestos!$B$8)^A85 -> 42487120 | D85: =IF(A85<=(Supuestos!$B$22-Supuestos!$B$24),$C$76,$E$76)*(1+Supuestos!$B$8)^A85*(1-Supuestos!$B$11)^A85 -> 6061337.5 | E85: =$G$76*(1+Supuestos!$B$8)^A85*(1-Supuestos!$B$12)^A85*Supuestos!$B$10 -> 331875.36 | F85: =$I$76*(1+Supuestos!$B$8)^A85 -> 2580308.6 | G85: =C85-D85-E85-F85 -> 33513599 | H85: =D85+E85+F85-(Supuestos!$B$19*$B$6+Supuestos!$B$20*$F$6)*(1+Supuestos!$B$8)^(A85-1) -> 8399738.2 | I85: =IF(A85<=Supuestos!$J$29,$K$76*(1-Supuestos!$B$11)^A85*Supuestos!$I$29*(1+Supuestos!$B$9)^(A85-1),0) -> 3894611.4 | J85: =E85*Supuestos!$K$29 -> 165937.68 | K85: =D85-I85+E85-J85+F85-IF(A85<=Supuestos!$J$29,0,Supuestos!$B$19*$B$6*(1+Supuestos!$B$8)^(A85-1)) -> 4912972.4 | L85: =I85+J85-IF(A85<=Supuestos!$J$29,(Supuestos!$B$19*$B$6+Supuestos!$B$20*$F$6),Supuestos!$B$20*$F$6)*(1+Supuestos!$B$8)^(A85-1) -> 3486765.8
A86: 8 | B86: =IF(A86<=(Supuestos!$B$22-Supuestos!$B$24),"Autoabasto","CFE pleno") -> CFE pleno | C86: =IF(A86<=(Supuestos!$B$22-Supuestos!$B$24),$B$12,$B$10)*(1+Supuestos!$B$8)^A86 -> 45036348 | D86: =IF(A86<=(Supuestos!$B$22-Supuestos!$B$24),$C$76,$E$76)*(1+Supuestos!$B$8)^A86*(1-Supuestos!$B$11)^A86 -> 6392892.6 | E86: =$G$76*(1+Supuestos!$B$8)^A86*(1-Supuestos!$B$12)^A86*Supuestos!$B$10 -> 347390.53 | F86: =$I$76*(1+Supuestos!$B$8)^A86 -> 2735127.2 | G86: =C86-D86-E86-F86 -> 35560937 | H86: =D86+E86+F86-(Supuestos!$B$19*$B$6+Supuestos!$B$20*$F$6)*(1+Supuestos!$B$8)^(A86-1) -> 8867200.1 | I86: =IF(A86<=Supuestos!$J$29,$K$76*(1-Supuestos!$B$11)^A86*Supuestos!$I$29*(1+Supuestos!$B$9)^(A86-1),0) -> 4068895.3 | J86: =E86*Supuestos!$K$29 -> 173695.27 | K86: =D86-I86+E86-J86+F86-IF(A86<=Supuestos!$J$29,0,Supuestos!$B$19*$B$6*(1+Supuestos!$B$8)^(A86-1)) -> 5232819.8 | L86: =I86+J86-IF(A86<=Supuestos!$J$29,(Supuestos!$B$19*$B$6+Supuestos!$B$20*$F$6),Supuestos!$B$20*$F$6)*(1+Supuestos!$B$8)^(A86-1) -> 3634380.3
A87: 9 | B87: =IF(A87<=(Supuestos!$B$22-Supuestos!$B$24),"Autoabasto","CFE pleno") -> CFE pleno | C87: =IF(A87<=(Supuestos!$B$22-Supuestos!$B$24),$B$12,$B$10)*(1+Supuestos!$B$8)^A87 -> 47738528 | D87: =IF(A87<=(Supuestos!$B$22-Supuestos!$B$24),$C$76,$E$76)*(1+Supuestos!$B$8)^A87*(1-Supuestos!$B$11)^A87 -> 6742583.9 | E87: =$G$76*(1+Supuestos!$B$8)^A87*(1-Supuestos!$B$12)^A87*Supuestos!$B$10 -> 363631.04 | F87: =$I$76*(1+Supuestos!$B$8)^A87 -> 2899234.8 | G87: =C87-D87-E87-F87 -> 37733079 | H87: =D87+E87+F87-(Supuestos!$B$19*$B$6+Supuestos!$B$20*$F$6)*(1+Supuestos!$B$8)^(A87-1) -> 9360746.8 | I87: =IF(A87<=Supuestos!$J$29,$K$76*(1-Supuestos!$B$11)^A87*Supuestos!$I$29*(1+Supuestos!$B$9)^(A87-1),0) -> 4250978.3 | J87: =E87*Supuestos!$K$29 -> 181815.52 | K87: =D87-I87+E87-J87+F87-IF(A87<=Supuestos!$J$29,0,Supuestos!$B$19*$B$6*(1+Supuestos!$B$8)^(A87-1)) -> 5572655.8 | L87: =I87+J87-IF(A87<=Supuestos!$J$29,(Supuestos!$B$19*$B$6+Supuestos!$B$20*$F$6),Supuestos!$B$20*$F$6)*(1+Supuestos!$B$8)^(A87-1) -> 3788091
A88: 10 | B88: =IF(A88<=(Supuestos!$B$22-Supuestos!$B$24),"Autoabasto","CFE pleno") -> CFE pleno | C88: =IF(A88<=(Supuestos!$B$22-Supuestos!$B$24),$B$12,$B$10)*(1+Supuestos!$B$8)^A88 -> 50602840 | D88: =IF(A88<=(Supuestos!$B$22-Supuestos!$B$24),$C$76,$E$76)*(1+Supuestos!$B$8)^A88*(1-Supuestos!$B$11)^A88 -> 7111403.2 | E88: =$G$76*(1+Supuestos!$B$8)^A88*(1-Supuestos!$B$12)^A88*Supuestos!$B$10 -> 380630.79 | F88: =$I$76*(1+Supuestos!$B$8)^A88 -> 3073188.9 | G88: =C88-D88-E88-F88 -> 40037617 | H88: =D88+E88+F88-(Supuestos!$B$19*$B$6+Supuestos!$B$20*$F$6)*(1+Supuestos!$B$8)^(A88-1) -> 9881837.9 | I88: =IF(A88<=Supuestos!$J$29,$K$76*(1-Supuestos!$B$11)^A88*Supuestos!$I$29*(1+Supuestos!$B$9)^(A88-1),0) -> 4441209.6 | J88: =E88*Supuestos!$K$29 -> 190315.4 | K88: =D88-I88+E88-J88+F88-IF(A88<=Supuestos!$J$29,0,Supuestos!$B$19*$B$6*(1+Supuestos!$B$8)^(A88-1)) -> 5933697.9 | L88: =I88+J88-IF(A88<=Supuestos!$J$29,(Supuestos!$B$19*$B$6+Supuestos!$B$20*$F$6),Supuestos!$B$20*$F$6)*(1+Supuestos!$B$8)^(A88-1) -> 3948140
A89: 11 | B89: =IF(A89<=(Supuestos!$B$22-Supuestos!$B$24),"Autoabasto","CFE pleno") -> CFE pleno | C89: =IF(A89<=(Supuestos!$B$22-Supuestos!$B$24),$B$12,$B$10)*(1+Supuestos!$B$8)^A89 -> 53639011 | D89: =IF(A89<=(Supuestos!$B$22-Supuestos!$B$24),$C$76,$E$76)*(1+Supuestos!$B$8)^A89*(1-Supuestos!$B$11)^A89 -> 7500397 | E89: =$G$76*(1+Supuestos!$B$8)^A89*(1-Supuestos!$B$12)^A89*Supuestos!$B$10 -> 398425.28 | F89: =$I$76*(1+Supuestos!$B$8)^A89 -> 3257580.2 | G89: =C89-D89-E89-F89 -> 42482608 | H89: =D89+E89+F89-(Supuestos!$B$19*$B$6+Supuestos!$B$20*$F$6)*(1+Supuestos!$B$8)^(A89-1) -> 10432014 | I89: =IF(A89<=Supuestos!$J$29,$K$76*(1-Supuestos!$B$11)^A89*Supuestos!$I$29*(1+Supuestos!$B$9)^(A89-1),0) -> 4639953.8 | J89: =E89*Supuestos!$K$29 -> 199212.64 | K89: =D89-I89+E89-J89+F89-IF(A89<=Supuestos!$J$29,0,Supuestos!$B$19*$B$6*(1+Supuestos!$B$8)^(A89-1)) -> 6317236.1 | L89: =I89+J89-IF(A89<=Supuestos!$J$29,(Supuestos!$B$19*$B$6+Supuestos!$B$20*$F$6),Supuestos!$B$20*$F$6)*(1+Supuestos!$B$8)^(A89-1) -> 4114778.3
A90: 12 | B90: =IF(A90<=(Supuestos!$B$22-Supuestos!$B$24),"Autoabasto","CFE pleno") -> CFE pleno | C90: =IF(A90<=(Supuestos!$B$22-Supuestos!$B$24),$B$12,$B$10)*(1+Supuestos!$B$8)^A90 -> 56857351 | D90: =IF(A90<=(Supuestos!$B$22-Supuestos!$B$24),$C$76,$E$76)*(1+Supuestos!$B$8)^A90*(1-Supuestos!$B$11)^A90 -> 7910668.7 | E90: =$G$76*(1+Supuestos!$B$8)^A90*(1-Supuestos!$B$12)^A90*Supuestos!$B$10 -> 417051.66 | F90: =$I$76*(1+Supuestos!$B$8)^A90 -> 3453035 | G90: =C90-D90-E90-F90 -> 45076596 | H90: =D90+E90+F90-(Supuestos!$B$19*$B$6+Supuestos!$B$20*$F$6)*(1+Supuestos!$B$8)^(A90-1) -> 11012904 | I90: =IF(A90<=Supuestos!$J$29,$K$76*(1-Supuestos!$B$11)^A90*Supuestos!$I$29*(1+Supuestos!$B$9)^(A90-1),0) -> 4847591.7 | J90: =E90*Supuestos!$K$29 -> 208525.83 | K90: =D90-I90+E90-J90+F90-IF(A90<=Supuestos!$J$29,0,Supuestos!$B$19*$B$6*(1+Supuestos!$B$8)^(A90-1)) -> 6724637.9 | L90: =I90+J90-IF(A90<=Supuestos!$J$29,(Supuestos!$B$19*$B$6+Supuestos!$B$20*$F$6),Supuestos!$B$20*$F$6)*(1+Supuestos!$B$8)^(A90-1) -> 4288266.1
... A98: 20 | B98: =IF(A98<=(Supuestos!$B$22-Supuestos!$B$24),"Autoabasto","CFE pleno") -> CFE pleno | C98: =IF(A98<=(Supuestos!$B$22-Supuestos!$B$24),$B$12,$B$10)*(1+Supuestos!$B$8)^A98 -> 90621980 | D98: =IF(A98<=(Supuestos!$B$22-Supuestos!$B$24),$C$76,$E$76)*(1+Supuestos!$B$8)^A98*(1-Supuestos!$B$11)^A98 -> 12112806 | E98: =$G$76*(1+Supuestos!$B$8)^A98*(1-Supuestos!$B$12)^A98*Supuestos!$B$10 -> 601081.85 | F98: =$I$76*(1+Supuestos!$B$8)^A98 -> 5503613.2 | G98: =C98-D98-E98-F98 -> 72404478 | H98: =D98+E98+F98-(Supuestos!$B$19*$B$6+Supuestos!$B$20*$F$6)*(1+Supuestos!$B$8)^(A98-1) -> 16993663 | I98: =IF(A98<=Supuestos!$J$29,$K$76*(1-Supuestos!$B$11)^A98*Supuestos!$I$29*(1+Supuestos!$B$9)^(A98-1),0) -> 0 | J98: =E98*Supuestos!$K$29 -> 300540.93 | K98: =D98-I98+E98-J98+F98-IF(A98<=Supuestos!$J$29,0,Supuestos!$B$19*$B$6*(1+Supuestos!$B$8)^(A98-1)) -> 16959980 | L98: =I98+J98-IF(A98<=Supuestos!$J$29,(Supuestos!$B$19*$B$6+Supuestos!$B$20*$F$6),Supuestos!$B$20*$F$6)*(1+Supuestos!$B$8)^(A98-1) -> 33683.049
A99: Σ | H99: =SUM(H79:H98) -> 2.1314701e+08 | K99: =SUM(K79:K98) -> 1.5759175e+08 | L99: =SUM(L79:L98) -> 55555258
F100: TIR compra: | G100: =IRR(H78:H98) -> 0.43092559 | I100: VPN compra @WACC: | K100: =NPV(Supuestos!$B$7,H79:H98)+H78 -> 49306389
F101: TIR financiador: | G101: =IRR(L78:L98) -> 0.18679137 | I101: VPN cliente PPA @WACC: | K101: =NPV(Supuestos!$B$7,K79:K98)+K78 -> 42333387
A102: Régimen: Autoabasto años 1-6 (2026-2031); CFE pleno desde 2032 (escalón en Tarifa Actual). El ahorro PV/BESS/FP persiste los 20 años; tras el plazo PPA el PV se transfiere a GEPP y conserva el 100% del ahorro.
A104: 7. COMPRAR vs PPA / AHORRO COMPARTIDO
A105: Métrica | B105: GEPP COMPRA | C105: PPA / Ahorro compartido
A106: Inversión GEPP $ | B106: =B26+B25+D25 -> 16137625 | C106: 0 | D106: Financiador funda todo (incl. capacitor)
A107: Beneficio GEPP año 1 $ | B107: =H79 -> 6070288.6 | C107: =K79 -> 3353681.3
A108: Beneficio 20 años acum. $ | B108: =H99 -> 2.1314701e+08 | C108: =SUM(K79:K98) -> 1.5759175e+08
A109: TIR (proyecto / financiador) | B109: =G100 -> 0.43092559 | C109: =G101 -> 0.18679137
A110: Tarifa PPA $/kWh (editable en Supuestos) | B110: — | C110: =Supuestos!$I$29 -> 1.5781
A111: Plazo PPA años / PV se transfiere al cliente al término | C111: =Supuestos!$J$29 -> 15
A113: 8. POR QUÉ ESTE DIMENSIONAMIENTO ES EL ÓPTIMO PARA ESTE SITIO
A114: FP es la palanca #1 (multa $1.7M/año por FP 85-86%, payback de meses, capex trivial $300k) — se hace primero, independiente de todo. PV 1,020 kWp cubre el consumo diurno; el BESS se mantiene chico (320 kW/640 kWh) porque el umbral satura la demanda facturable casi todo el año: una batería mayor no recortaría más demanda. TIR compra 42%. El trío FP+PV+BESS captura ~22% del recibo sin capex ocioso.

Sheet Cancún
A1: CANCÚN — Memoria de cálculo trazable y propuesta
A2: Medidor 073EEK · GDMTH SIN · Demanda contratada 1,500 kW · GENERADOR EXENTO (<0.7 MW) — Medición Neta, sin permiso
A3: GEPP pide: Explorar PPA o Abasto Aislado
A5: PARÁMETROS DEL SISTEMA (desde Supuestos — edítalos allí)
A6: PV kWp | B6: =Supuestos!$B$30 -> 839.41 | C6: BESS kW | D6: =Supuestos!$C$30 -> 0 | E6: BESS kWh | F6: =Supuestos!$D$30 -> 0 | G6: Entrega útil kWh | H6: =Supuestos!$D$30*Supuestos!$B$17*SQRT(Supuestos!$B$18) -> 0 | I6: FP corr. | J6: =Supuestos!$E$30 -> Sí | K6: Calib→recibo | L6: =$B$10/(SUM(P45:P56)+SUM(R30:R41)) -> 1.073955
A8: 1. ESTRUCTURA DE COSTO Y AHORRO (2025, pre-IVA · datos del workbook GEPP + motor)
A9: Concepto | B9: $ / año | C9: $ / kWh | D9: kWh | E9: Nota
A10: CFE BRUTO = Tarifa Actual (todo a CFE pleno, sin autoabasto) | B10: 15994317 | C10: =B10/D10 -> 3.3656431 | D10: 4752232 | E10: Lo que pagarían 100% en CFE sin ENEL/Tala ni PV/BESS
A11: (−) Ahorro autoabasto (—) | B11: 0 | E11: Sin autoabasto
A12: (=) Costo actual que paga GEPP hoy | B12: =B10-B11 -> 15994317 | C12: =B12/D12 -> 3.3656431 | D12: =D10 -> 4752232
A13: › CFE (tarifa CFE plena) | B13: 15994317 | C13: =B13/D13 -> 3.3656431 | D13: 4752232
A14: › sin autoabasto (100% CFE)
A16: Ahorros del proyecto (motor 2025, sobre la carga física):
A17: (−) Ahorro PV (energía intermedia + demanda vía umbral) | B17: =F72 -> 3734035.9 | D17: =C72 -> 1258947.1 | E17: Gen solar kWh/año →
A18: (−) Ahorro BESS (recorte de punta + arbitraje) | B18: =G72 -> 0
A19: (−) Ahorro FP (corrección factor de potencia) | B19: =H72 -> 597755.97 | E19: Multa FP impresa en el recibo (dato duro)
A20: (=) Costo neto con proyecto (hoy) | B20: =B12-B17-B18-B19 -> 11662525
A21: Ahorro proyecto PV+BESS+FP (vs costo hoy) | B21: =B17+B18+B19 -> 4331791.9 | C21: =B21/B12 -> 0.27083319
A22: Ahorro TOTAL vs CFE bruto (incl. autoabasto+proyecto) | B22: =B10-B20 -> 4331791.9 | C22: =B22/B10 -> 0.27083319
A24: 2. CAPEX (fórmulas vivas desde Supuestos)
A25: CAPEX PV = kWp×1000×USD/Wp×FX | B25: =$B$6*1000*Supuestos!$F$30*Supuestos!$B$5 -> 11048734 | C25: CAPEX BESS = kWh×USD/kWh×FX | D25: =$F$6*Supuestos!$G$30*Supuestos!$B$5 -> 0
A26: CAPEX Capacitor FP (financiador en PPA) | B26: =Supuestos!$H$30 -> 250000 | C26: CAPEX TOTAL (compra) | D26: =B25+D25+B26 -> 11298734 | E26: Bajo PPA, el capacitor lo paga el financiador → el cliente no desembolsa
A28: 3. ENTRADAS MENSUALES (AZUL = datos del recibo / recurso 2025)
A29: Mes | B29: kWh Base | C29: kWh Int | D29: kWh Punta | E29: Días | F29: Dem Pta kW | G29: Dem Máx kW | H29: T.Int $ | I29: T.Base $ | J29: T.Pta $ | K29: T.Cap $ | L29: T.Dist $ | M29: T.Fijo $ | N29: Rend | O29: %AC | P29: HrsP | Q29: DíasP | R29: Bonif FP
A30: Ene | B30: 111992 | C30: 217041 | D30: 61651 | E30: 31 | F30: 1043 | G30: 1075 | H30: 2.08045 | I30: 1.23575 | J30: 2.321525 | K30: 392.485 | L30: 91.87 | M30: 452.58 | N30: 116.3 | O30: 1 | P30: 4 | Q30: 22 | R30: 49039.23
A31: Feb | B31: 119044 | C31: 193524 | D31: 57902 | E31: 28 | F31: 1010 | G31: 1068 | H31: 2.08045 | I31: 1.23575 | J31: 2.321525 | K31: 392.485 | L31: 91.87 | M31: 452.58 | N31: 113.8 | O31: 1 | P31: 4 | Q31: 19 | R31: 45533.52
A32: Mar | B32: 143269 | C32: 218315 | D32: 57204 | E32: 31 | F32: 930 | G32: 995 | H32: 2.08045 | I32: 1.23575 | J32: 2.321525 | K32: 392.485 | L32: 91.87 | M32: 452.58 | N32: 140.6 | O32: 1 | P32: 4 | Q32: 20 | R32: 44271.61
A33: Abr | B33: 137235 | C33: 257107 | D33: 37859 | E33: 30 | F33: 934 | G33: 986 | H33: 2.08045 | I33: 1.23575 | J33: 2.321525 | K33: 392.485 | L33: 91.87 | M33: 452.58 | N33: 139.9 | O33: 1 | P33: 2 | Q33: 22 | R33: 47050.61
A34: May | B34: 131219 | C34: 271299 | D34: 30661 | E34: 31 | F34: 1094 | G34: 1130 | H34: 2.08045 | I34: 1.23575 | J34: 2.321525 | K34: 392.485 | L34: 91.87 | M34: 452.58 | N34: 139.6 | O34: 1 | P34: 2 | Q34: 21 | R34: 48308.02
A35: Jun | B35: 135885 | C35: 268040 | D35: 30139 | E35: 30 | F35: 1049 | G35: 1092 | H35: 2.08045 | I35: 1.23575 | J35: 2.321525 | K35: 392.485 | L35: 91.87 | M35: 452.58 | N35: 127.4 | O35: 1 | P35: 2 | Q35: 21 | R35: 55431.62
A36: Jul | B36: 101439 | C36: 274792 | D36: 34785 | E36: 31 | F36: 1092 | G36: 1103 | H36: 2.08045 | I36: 1.23575 | J36: 2.321525 | K36: 392.485 | L36: 91.87 | M36: 452.58 | N36: 131.2 | O36: 1 | P36: 2 | Q36: 23 | R36: 55104.56
A37: Ago | B37: 116365 | C37: 275738 | D37: 28280 | E37: 31 | F37: 1051 | G37: 1097 | H37: 2.08045 | I37: 1.23575 | J37: 2.321525 | K37: 392.485 | L37: 91.87 | M37: 452.58 | N37: 123.3 | O37: 1 | P37: 2 | Q37: 21 | R37: 53076.82
A38: Sep | B38: 100169 | C38: 231786 | D38: 26471 | E38: 30 | F38: 1014 | G38: 1066 | H38: 2.08045 | I38: 1.23575 | J38: 2.321525 | K38: 392.485 | L38: 91.87 | M38: 452.58 | N38: 118.3 | O38: 1 | P38: 2 | Q38: 21 | R38: 49101.31
A39: Oct | B39: 98572 | C39: 224586 | D39: 35922 | E39: 31 | F39: 913 | G39: 958 | H39: 2.08045 | I39: 1.23575 | J39: 2.321525 | K39: 392.485 | L39: 91.87 | M39: 452.58 | N39: 121.8 | O39: 1 | P39: 2 | Q39: 23 | R39: 53035.23
A40: Nov | B40: 94126 | C40: 183552 | D40: 53993 | E40: 30 | F40: 939 | G40: 968 | H40: 2.08045 | I40: 1.23575 | J40: 2.321525 | K40: 392.485 | L40: 91.87 | M40: 452.58 | N40: 115 | O40: 1 | P40: 4 | Q40: 19 | R40: 47771.27
A41: Dic | B41: 102510 | C41: 225061 | D41: 64699 | E41: 31 | F41: 960 | G41: 971 | H41: 2.08045 | I41: 1.23575 | J41: 2.321525 | K41: 392.485 | L41: 91.87 | M41: 452.58 | N41: 112.6 | O41: 1 | P41: 4 | Q41: 22 | R41: 50032.17
A42: 4. CÁLCULO DE AHORRO MENSUAL (motor — fórmulas que referencian las ENTRADAS)
A43: Mes | B43: Gen kWh | C43: Umbral kW | D43: Autocons | E43: Ah PV ener | F43: Umbral post | G43: Cap base | H43: Cap pre-B | I43: Ah PV dem | J43: Recorte BESS | K43: Cap post | L43: Ah BESS dem | M43: Desc kWh | N43: Arbitraje $ | O43: Fac.AA | P43: mem $ | Q43: Ah PV+BESS
A45: =A30 -> Ene | B45: =$B$6*N30 -> 97623.383 | C45: =(B30+C30+D30)/(E30*24*Supuestos!$B$16) -> 921.25071 | D45: =MIN(B45*O30,C30) -> 97623.383 | E45: =D45*H30*O45 -> 203100.57 | F45: =((B30+C30+D30)-D45)/(E30*24*Supuestos!$B$16) -> 691.05031 | G45: =MIN(F30,C45) -> 921.25071 | H45: =MIN(F30,F45) -> 691.05031 | I45: =(G45-H45)*K30 -> 90350.202 | J45: =IF(P30=0,0,MIN($D$6,$H$6/P30)) -> 0 | K45: =MIN(MAX(F30-J45,0),F45) -> 691.05031 | L45: =(H45-K45)*K30 -> 0 | M45: =IF(P30=0,0,MIN($H$6*Q30,D30)) -> 0 | N45: =M45*J30-(M45/Supuestos!$B$18)*I30 -> 0 | O45: 1 | P45: =M30+B30*I30+C30*H30+D30*J30+G45*K30+MIN(G30,C45)*L30 -> 1179726.4 | Q45: =(E45+I45)+(L45+N45) -> 293450.77
A46: =A31 -> Feb | B46: =$B$6*N31 -> 95524.858 | C46: =(B31+C31+D31)/(E31*24*Supuestos!$B$16) -> 967.18358 | D46: =MIN(B46*O31,C31) -> 95524.858 | E46: =D46*H31*O46 -> 198734.69 | F46: =((B31+C31+D31)-D46)/(E31*24*Supuestos!$B$16) -> 717.79747 | G46: =MIN(F31,C46) -> 967.18358 | H46: =MIN(F31,F46) -> 717.79747 | I46: =(G46-H46)*K31 -> 97880.31 | J46: =IF(P31=0,0,MIN($D$6,$H$6/P31)) -> 0 | K46: =MIN(MAX(F31-J46,0),F46) -> 717.79747 | L46: =(H46-K46)*K31 -> 0 | M46: =IF(P31=0,0,MIN($H$6*Q31,D31)) -> 0 | N46: =M46*J31-(M46/Supuestos!$B$18)*I31 -> 0 | O46: 1 | P46: =M31+B31*I31+C31*H31+D31*J31+G46*K31+MIN(G31,C46)*L31 -> 1153059.4 | Q46: =(E46+I46)+(L46+N46) -> 296615
A47: =A32 -> Mar | B47: =$B$6*N32 -> 118021.05 | C47: =(B32+C32+D32)/(E32*24*Supuestos!$B$16) -> 987.52122 | D47: =MIN(B47*O32,C32) -> 118021.05 | E47: =D47*H32*O47 -> 245536.89 | F47: =((B32+C32+D32)-D47)/(E32*24*Supuestos!$B$16) -> 709.22221 | G47: =MIN(F32,C47) -> 930 | H47: =MIN(F32,F47) -> 709.22221 | I47: =(G47-H47)*K32 -> 86651.972 | J47: =IF(P32=0,0,MIN($D$6,$H$6/P32)) -> 0 | K47: =MIN(MAX(F32-J47,0),F47) -> 709.22221 | L47: =(H47-K47)*K32 -> 0 | M47: =IF(P32=0,0,MIN($H$6*Q32,D32)) -> 0 | N47: =M47*J32-(M47/Supuestos!$B$18)*I32 -> 0 | O47: 1 | P47: =M32+B32*I32+C32*H32+D32*J32+G47*K32+MIN(G32,C47)*L32 -> 1220225.8 | Q47: =(E47+I47)+(L47+N47) -> 332188.86
A48: =A33 -> Abr | B48: =$B$6*N33 -> 117433.46 | C48: =(B33+C33+D33)/(E33*24*Supuestos!$B$16) -> 1053.1213 | D48: =MIN(B48*O33,C33) -> 117433.46 | E48: =D48*H33*O48 -> 244314.44 | F48: =((B33+C33+D33)-D48)/(E33*24*Supuestos!$B$16) -> 766.97744 | G48: =MIN(F33,C48) -> 934 | H48: =MIN(F33,F48) -> 766.97744 | I48: =(G48-H48)*K33 -> 65553.85 | J48: =IF(P33=0,0,MIN($D$6,$H$6/P33)) -> 0 | K48: =MIN(MAX(F33-J48,0),F48) -> 766.97744 | L48: =(H48-K48)*K33 -> 0 | M48: =IF(P33=0,0,MIN($H$6*Q33,D33)) -> 0 | N48: =M48*J33-(M48/Supuestos!$B$18)*I33 -> 0 | O48: 1 | P48: =M33+B33*I33+C33*H33+D33*J33+G48*K33+MIN(G33,C48)*L33 -> 1249994.4 | Q48: =(E48+I48)+(L48+N48) -> 309868.29
A49: =A34 -> May | B49: =$B$6*N34 -> 117181.64 | C49: =(B34+C34+D34)/(E34*24*Supuestos!$B$16) -> 1021.4559 | D49: =MIN(B49*O34,C34) -> 117181.64 | E49: =D49*H34*O49 -> 243790.53 | F49: =((B34+C34+D34)-D49)/(E34*24*Supuestos!$B$16) -> 745.13621 | G49: =MIN(F34,C49) -> 1021.4559 | H49: =MIN(F34,F49) -> 745.13621 | I49: =(G49-H49)*K34 -> 108451.32 | J49: =IF(P34=0,0,MIN($D$6,$H$6/P34)) -> 0 | K49: =MIN(MAX(F34-J49,0),F49) -> 745.13621 | L49: =(H49-K49)*K34 -> 0 | M49: =IF(P34=0,0,MIN($H$6*Q34,D34)) -> 0 | N49: =M49*J34-(M49/Supuestos!$B$18)*I34 -> 0 | O49: 1 | P49: =M34+B34*I34+C34*H34+D34*J34+G49*K34+MIN(G34,C49)*L34 -> 1292958 | Q49: =(E49+I49)+(L49+N49) -> 352241.85
A50: =A35 -> Jun | B50: =$B$6*N35 -> 106940.83 | C50: =(B35+C35+D35)/(E35*24*Supuestos!$B$16) -> 1057.6608 | D50: =MIN(B50*O35,C35) -> 106940.83 | E50: =D50*H35*O50 -> 222485.06 | F50: =((B35+C35+D35)-D50)/(E35*24*Supuestos!$B$16) -> 797.08374 | G50: =MIN(F35,C50) -> 1049 | H50: =MIN(F35,F50) -> 797.08374 | I50: =(G50-H50)*K35 -> 98873.354 | J50: =IF(P35=0,0,MIN($D$6,$H$6/P35)) -> 0 | K50: =MIN(MAX(F35-J50,0),F50) -> 797.08374 | L50: =(H50-K50)*K35 -> 0 | M50: =IF(P35=0,0,MIN($H$6*Q35,D35)) -> 0 | N50: =M50*J35-(M50/Supuestos!$B$18)*I35 -> 0 | O50: 1 | P50: =M35+B35*I35+C35*H35+D35*J35+G50*K35+MIN(G35,C50)*L35 -> 1304868.8 | Q50: =(E50+I50)+(L50+N50) -> 321358.41
A51: =A36 -> Jul | B51: =$B$6*N36 -> 110130.59 | C51: =(B36+C36+D36)/(E36*24*Supuestos!$B$16) -> 969.19449 | D51: =MIN(B51*O36,C36) -> 110130.59 | E51: =D51*H36*O51 -> 229121.19 | F51: =((B36+C36+D36)-D51)/(E36*24*Supuestos!$B$16) -> 709.50153 | G51: =MIN(F36,C51) -> 969.19449 | H51: =MIN(F36,F51) -> 709.50153 | I51: =(G51-H51)*K36 -> 101925.59 | J51: =IF(P36=0,0,MIN($D$6,$H$6/P36)) -> 0 | K51: =MIN(MAX(F36-J51,0),F51) -> 709.50153 | L51: =(H51-K51)*K36 -> 0 | M51: =IF(P36=0,0,MIN($H$6*Q36,D36)) -> 0 | N51: =M51*J36-(M51/Supuestos!$B$18)*I36 -> 0 | O51: 1 | P51: =M36+B36*I36+C36*H36+D36*J36+G51*K36+MIN(G36,C51)*L36 -> 1247685.3 | Q51: =(E51+I51)+(L51+N51) -> 331046.78
A52: =A37 -> Ago | B52: =$B$6*N37 -> 103499.25 | C52: =(B37+C37+D37)/(E37*24*Supuestos!$B$16) -> 991.28231 | D52: =MIN(B52*O37,C37) -> 103499.25 | E52: =D52*H37*O52 -> 215325.02 | F52: =((B37+C37+D37)-D52)/(E37*24*Supuestos!$B$16) -> 747.22634 | G52: =MIN(F37,C52) -> 991.28231 | H52: =MIN(F37,F52) -> 747.22634 | I52: =(G52-H52)*K37 -> 95788.305 | J52: =IF(P37=0,0,MIN($D$6,$H$6/P37)) -> 0 | K52: =MIN(MAX(F37-J52,0),F52) -> 747.22634 | L52: =(H52-K52)*K37 -> 0 | M52: =IF(P37=0,0,MIN($H$6*Q37,D37)) -> 0 | N52: =M52*J37-(M52/Supuestos!$B$18)*I37 -> 0 | O52: 1 | P52: =M37+B37*I37+C37*H37+D37*J37+G52*K37+MIN(G37,C52)*L37 -> 1263695 | Q52: =(E52+I52)+(L52+N52) -> 311113.33
A53: =A38 -> Sep | B53: =$B$6*N38 -> 99302.203 | C53: =(B38+C38+D38)/(E38*24*Supuestos!$B$16) -> 873.3577 | D53: =MIN(B53*O38,C38) -> 99302.203 | E53: =D53*H38*O53 -> 206593.27 | F53: =((B38+C38+D38)-D53)/(E38*24*Supuestos!$B$16) -> 631.39327 | G53: =MIN(F38,C53) -> 873.3577 | H53: =MIN(F38,F53) -> 631.39327 | I53: =(G53-H53)*K38 -> 94967.41 | J53: =IF(P38=0,0,MIN($D$6,$H$6/P38)) -> 0 | K53: =MIN(MAX(F38-J53,0),F53) -> 631.39327 | L53: =(H53-K53)*K38 -> 0 | M53: =IF(P38=0,0,MIN($H$6*Q38,D38)) -> 0 | N53: =M53*J38-(M53/Supuestos!$B$18)*I38 -> 0 | O53: 1 | P53: =M38+B38*I38+C38*H38+D38*J38+G53*K38+MIN(G38,C53)*L38 -> 1090923.9 | Q53: =(E53+I53)+(L53+N53) -> 301560.68
A54: =A39 -> Oct | B54: =$B$6*N39 -> 102240.14 | C54: =(B39+C39+D39)/(E39*24*Supuestos!$B$16) -> 846.72703 | D54: =MIN(B54*O39,C39) -> 102240.14 | E54: =D54*H39*O54 -> 212705.5 | F54: =((B39+C39+D39)-D54)/(E39*24*Supuestos!$B$16) -> 605.64012 | G54: =MIN(F39,C54) -> 846.72703 | H54: =MIN(F39,F54) -> 605.64012 | I54: =(G54-H54)*K39 -> 94622.997 | J54: =IF(P39=0,0,MIN($D$6,$H$6/P39)) -> 0 | K54: =MIN(MAX(F39-J54,0),F54) -> 605.64012 | L54: =(H54-K54)*K39 -> 0 | M54: =IF(P39=0,0,MIN($H$6*Q39,D39)) -> 0 | N54: =M54*J39-(M54/Supuestos!$B$18)*I39 -> 0 | O54: 1 | P54: =M39+B39*I39+C39*H39+D39*J39+G54*K39+MIN(G39,C54)*L39 -> 1083013.2 | Q54: =(E54+I54)+(L54+N54) -> 307328.49
A55: =A40 -> Nov | B55: =$B$6*N40 -> 96532.15 | C55: =(B40+C40+D40)/(E40*24*Supuestos!$B$16) -> 808.1652 | D55: =MIN(B55*O40,C40) -> 96532.15 | E55: =D55*H40*O55 -> 200830.31 | F55: =((B40+C40+D40)-D55)/(E40*24*Supuestos!$B$16) -> 572.95041 | G55: =MIN(F40,C55) -> 808.1652 | H55: =MIN(F40,F55) -> 572.95041 | I55: =(G55-H55)*K40 -> 92318.277 | J55: =IF(P40=0,0,MIN($D$6,$H$6/P40)) -> 0 | K55: =MIN(MAX(F40-J55,0),F55) -> 572.95041 | L55: =(H55-K55)*K40 -> 0 | M55: =IF(P40=0,0,MIN($H$6*Q40,D40)) -> 0 | N55: =M55*J40-(M55/Supuestos!$B$18)*I40 -> 0 | O55: 1 | P55: =M40+B40*I40+C40*H40+D40*J40+G55*K40+MIN(G40,C55)*L40 -> 1015424.5 | Q55: =(E55+I55)+(L55+N55) -> 293148.59
A56: =A41 -> Dic | B56: =$B$6*N41 -> 94517.566 | C56: =(B41+C41+D41)/(E41*24*Supuestos!$B$16) -> 924.99057 | D56: =MIN(B56*O41,C41) -> 94517.566 | E56: =D56*H41*O56 -> 196639.07 | F56: =((B41+C41+D41)-D56)/(E41*24*Supuestos!$B$16) -> 702.11383 | G56: =MIN(F41,C56) -> 924.99057 | H56: =MIN(F41,F56) -> 702.11383 | I56: =(G56-H56)*K41 -> 87475.776 | J56: =IF(P41=0,0,MIN($D$6,$H$6/P41)) -> 0 | K56: =MIN(MAX(F41-J56,0),F56) -> 702.11383 | L56: =(H56-K56)*K41 -> 0 | M56: =IF(P41=0,0,MIN($H$6*Q41,D41)) -> 0 | N56: =M56*J41-(M56/Supuestos!$B$18)*I41 -> 0 | O56: 1 | P56: =M41+B41*I41+C41*H41+D41*J41+G56*K41+MIN(G41,C56)*L41 -> 1193581.6 | Q56: =(E56+I56)+(L56+N56) -> 284114.85
A57: Recorte BESS = MIN(kW batería, entrega útil ÷ HrsP). Desc = MIN(entrega×DíasP, kWh punta). Arbitraje carga en base y descarga en punta. Fac.AA aplica el descuento de zafra (sólo Ixtlahuacán, pre-2032).
A58: 5. RESUMEN MENSUAL — Tarifa Actual (CFE pleno) / Ahorros / Costo con proyecto
A59: Mes | B59: kWh Consumo | C59: Gen PV kWh | D59: BESS desc kWh | E59: Tarifa Actual $ | F59: Ahorro PV $ | G59: Ahorro BESS $ | H59: Ahorro FP $ | I59: Costo c/proyecto $ | J59: Ahorro $ | K59: Ahorro %
A60: =A30 -> Ene | B60: =B30+C30+D30 -> 390684 | C60: =B45 -> 97623.383 | D60: =M45 -> 0 | E60: =(P45+R30)*$L$6 -> 1319638.9 | F60: =(E45+I45)*(1-IF(R30<0,-R30/P45,0)) -> 293450.77 | G60: =(L45+N45)*(1-IF(R30<0,-R30/P45,0)) -> 0 | H60: =IF($J$6="Sí",MAX(0,R30),0) -> 49039.23 | I60: =E60-F60-G60-H60 -> 977148.9 | J60: =F60+G60+H60 -> 342490 | K60: =J60/E60 -> 0.25953312
A61: =A31 -> Feb | B61: =B31+C31+D31 -> 370470 | C61: =B46 -> 95524.858 | D61: =M46 -> 0 | E61: =(P46+R31)*$L$6 -> 1287234.8 | F61: =(E46+I46)*(1-IF(R31<0,-R31/P46,0)) -> 296615 | G61: =(L46+N46)*(1-IF(R31<0,-R31/P46,0)) -> 0 | H61: =IF($J$6="Sí",MAX(0,R31),0) -> 45533.52 | I61: =E61-F61-G61-H61 -> 945086.23 | J61: =F61+G61+H61 -> 342148.52 | K61: =J61/E61 -> 0.26580118
A62: =A32 -> Mar | B62: =B32+C32+D32 -> 418788 | C62: =B47 -> 118021.05 | D62: =M47 -> 0 | E62: =(P47+R32)*$L$6 -> 1358013.3 | F62: =(E47+I47)*(1-IF(R32<0,-R32/P47,0)) -> 332188.86 | G62: =(L47+N47)*(1-IF(R32<0,-R32/P47,0)) -> 0 | H62: =IF($J$6="Sí",MAX(0,R32),0) -> 44271.61 | I62: =E62-F62-G62-H62 -> 981552.82 | J62: =F62+G62+H62 -> 376460.47 | K62: =J62/E62 -> 0.27721413
A63: =A33 -> Abr | B63: =B33+C33+D33 -> 432201 | C63: =B48 -> 117433.46 | D63: =M48 -> 0 | E63: =(P48+R33)*$L$6 -> 1392967.9 | F63: =(E48+I48)*(1-IF(R33<0,-R33/P48,0)) -> 309868.29 | G63: =(L48+N48)*(1-IF(R33<0,-R33/P48,0)) -> 0 | H63: =IF($J$6="Sí",MAX(0,R33),0) -> 47050.61 | I63: =E63-F63-G63-H63 -> 1036049 | J63: =F63+G63+H63 -> 356918.9 | K63: =J63/E63 -> 0.25622909
A64: =A34 -> May | B64: =B34+C34+D34 -> 433179 | C64: =B49 -> 117181.64 | D64: =M49 -> 0 | E64: =(P49+R34)*$L$6 -> 1440459.3 | F64: =(E49+I49)*(1-IF(R34<0,-R34/P49,0)) -> 352241.85 | G64: =(L49+N49)*(1-IF(R34<0,-R34/P49,0)) -> 0 | H64: =IF($J$6="Sí",MAX(0,R34),0) -> 48308.02 | I64: =E64-F64-G64-H64 -> 1039909.4 | J64: =F64+G64+H64 -> 400549.87 | K64: =J64/E64 -> 0.27807094
A65: =A35 -> Jun | B65: =B35+C35+D35 -> 434064 | C65: =B50 -> 106940.83 | D65: =M50 -> 0 | E65: =(P50+R35)*$L$6 -> 1460901.4 | F65: =(E50+I50)*(1-IF(R35<0,-R35/P50,0)) -> 321358.41 | G65: =(L50+N50)*(1-IF(R35<0,-R35/P50,0)) -> 0 | H65: =IF($J$6="Sí",MAX(0,R35),0) -> 55431.62 | I65: =E65-F65-G65-H65 -> 1084111.3 | J65: =F65+G65+H65 -> 376790.03 | K65: =J65/E65 -> 0.25791613
A66: =A36 -> Jul | B66: =B36+C36+D36 -> 411016 | C66: =B51 -> 110130.59 | D66: =M51 -> 0 | E66: =(P51+R36)*$L$6 -> 1399137.6 | F66: =(E51+I51)*(1-IF(R36<0,-R36/P51,0)) -> 331046.78 | G66: =(L51+N51)*(1-IF(R36<0,-R36/P51,0)) -> 0 | H66: =IF($J$6="Sí",MAX(0,R36),0) -> 55104.56 | I66: =E66-F66-G66-H66 -> 1012986.3 | J66: =F66+G66+H66 -> 386151.34 | K66: =J66/E66 -> 0.2759924
A67: =A37 -> Ago | B67: =B37+C37+D37 -> 420383 | C67: =B52 -> 103499.25 | D67: =M52 -> 0 | E67: =(P52+R37)*$L$6 -> 1414153.6 | F67: =(E52+I52)*(1-IF(R37<0,-R37/P52,0)) -> 311113.33 | G67: =(L52+N52)*(1-IF(R37<0,-R37/P52,0)) -> 0 | H67: =IF($J$6="Sí",MAX(0,R37),0) -> 53076.82 | I67: =E67-F67-G67-H67 -> 1049963.5 | J67: =F67+G67+H67 -> 364190.15 | K67: =J67/E67 -> 0.25753223
A68: =A38 -> Sep | B68: =B38+C38+D38 -> 358426 | C68: =B53 -> 99302.203 | D68: =M53 -> 0 | E68: =(P53+R38)*$L$6 -> 1224335.7 | F68: =(E53+I53)*(1-IF(R38<0,-R38/P53,0)) -> 301560.68 | G68: =(L53+N53)*(1-IF(R38<0,-R38/P53,0)) -> 0 | H68: =IF($J$6="Sí",MAX(0,R38),0) -> 49101.31 | I68: =E68-F68-G68-H68 -> 873673.69 | J68: =F68+G68+H68 -> 350661.99 | K68: =J68/E68 -> 0.28641
A69: =A39 -> Oct | B69: =B39+C39+D39 -> 359080 | C69: =B54 -> 102240.14 | D69: =M54 -> 0 | E69: =(P54+R39)*$L$6 -> 1220064.8 | F69: =(E54+I54)*(1-IF(R39<0,-R39/P54,0)) -> 307328.49 | G69: =(L54+N54)*(1-IF(R39<0,-R39/P54,0)) -> 0 | H69: =IF($J$6="Sí",MAX(0,R39),0) -> 53035.23 | I69: =E69-F69-G69-H69 -> 859701.08 | J69: =F69+G69+H69 -> 360363.72 | K69: =J69/E69 -> 0.29536441
A70: =A40 -> Nov | B70: =B40+C40+D40 -> 331671 | C70: =B55 -> 96532.15 | D70: =M55 -> 0 | E70: =(P55+R40)*$L$6 -> 1141824.4 | F70: =(E55+I55)*(1-IF(R40<0,-R40/P55,0)) -> 293148.59 | G70: =(L55+N55)*(1-IF(R40<0,-R40/P55,0)) -> 0 | H70: =IF($J$6="Sí",MAX(0,R40),0) -> 47771.27 | I70: =E70-F70-G70-H70 -> 800904.5 | J70: =F70+G70+H70 -> 340919.86 | K70: =J70/E70 -> 0.29857469
A71: =A41 -> Dic | B71: =B41+C41+D41 -> 392270 | C71: =B56 -> 94517.566 | D71: =M56 -> 0 | E71: =(P56+R41)*$L$6 -> 1335585.2 | F71: =(E56+I56)*(1-IF(R41<0,-R41/P56,0)) -> 284114.85 | G71: =(L56+N56)*(1-IF(R41<0,-R41/P56,0)) -> 0 | H71: =IF($J$6="Sí",MAX(0,R41),0) -> 50032.17 | I71: =E71-F71-G71-H71 -> 1001438.2 | J71: =F71+G71+H71 -> 334147.02 | K71: =J71/E71 -> 0.25018772
A72: TOTAL | B72: =SUM(B60:B71) -> 4752232 | C72: =SUM(C60:C71) -> 1258947.1 | D72: =SUM(D60:D71) -> 0 | E72: =SUM(E60:E71) -> 15994317 | F72: =SUM(F60:F71) -> 3734035.9 | G72: =SUM(G60:G71) -> 0 | H72: =SUM(H60:H71) -> 597755.97 | I72: =SUM(I60:I71) -> 11662525 | J72: =SUM(J60:J71) -> 4331791.9 | K72: =J72/E72 -> 0.27083319
A73: Tarifa Actual (Σ) = recibo a CFE pleno $15,994,317 (dato workbook GEPP, calibrado del motor ×1.074). Ahorro = motor (golden 18/18).
A75: 6. PROYECCIÓN 20 AÑOS — Tarifa Actual con escalón 2032 · ahorros persisten · PPA se transfiere al cliente al término
A76: Bases año-0 (motor): | B76: PV con AA | C76: =F72 -> 3734035.9 | D76: PV CFE pleno | E76: =F72+SUMPRODUCT(E45:E56*(1/O45:O56-1)) -> 3734035.9 | F76: BESS | G76: =G72 -> 0 | H76: FP | I76: =H72 -> 597755.97 | J76: Gen PV kWh | K76: =C72 -> 1258947.1
A77: Año | B77: Régimen | C77: Tarifa Actual $ | D77: Ah PV $ | E77: Ah BESS $ | F77: Ah FP $ | G77: Costo c/proy $ | H77: Flujo Compra $ | I77: Pago PPA $ | J77: Comisión $ | K77: Flujo Cliente PPA $ | L77: Flujo Financiador $
A78: 0 | B78: Inversión | H78: =-B26-B25-D25 -> -11298734 | K78: 0 | L78: =-B26-B25-D25 -> -11298734
A79: 1 | B79: =IF(A79<=(Supuestos!$B$22-Supuestos!$B$24),"Autoabasto","CFE pleno") -> Autoabasto | C79: =IF(A79<=(Supuestos!$B$22-Supuestos!$B$24),$B$12,$B$10)*(1+Supuestos!$B$8)^A79 -> 16953976 | D79: =IF(A79<=(Supuestos!$B$22-Supuestos!$B$24),$C$76,$E$76)*(1+Supuestos!$B$8)^A79*(1-Supuestos!$B$11)^A79 -> 3938287.7 | E79: =$G$76*(1+Supuestos!$B$8)^A79*(1-Supuestos!$B$12)^A79*Supuestos!$B$10 -> 0 | F79: =$I$76*(1+Supuestos!$B$8)^A79 -> 633621.33 | G79: =C79-D79-E79-F79 -> 12382067 | H79: =D79+E79+F79-(Supuestos!$B$19*$B$6+Supuestos!$B$20*$F$6)*(1+Supuestos!$B$8)^(A79-1) -> 4311691.9 | I79: =IF(A79<=Supuestos!$J$30,$K$76*(1-Supuestos!$B$11)^A79*Supuestos!$I$30*(1+Supuestos!$B$9)^(A79-1),0) -> 2109216.1 | J79: =E79*Supuestos!$K$30 -> 0 | K79: =D79-I79+E79-J79+F79-IF(A79<=Supuestos!$J$30,0,Supuestos!$B$19*$B$6*(1+Supuestos!$B$8)^(A79-1)) -> 2462692.9 | L79: =I79+J79-IF(A79<=Supuestos!$J$30,(Supuestos!$B$19*$B$6+Supuestos!$B$20*$F$6),Supuestos!$B$20*$F$6)*(1+Supuestos!$B$8)^(A79-1) -> 1848999
A80: 2 | B80: =IF(A80<=(Supuestos!$B$22-Supuestos!$B$24),"Autoabasto","CFE pleno") -> Autoabasto | C80: =IF(A80<=(Supuestos!$B$22-Supuestos!$B$24),$B$12,$B$10)*(1+Supuestos!$B$8)^A80 -> 17971214 | D80: =IF(A80<=(Supuestos!$B$22-Supuestos!$B$24),$C$76,$E$76)*(1+Supuestos!$B$8)^A80*(1-Supuestos!$B$11)^A80 -> 4153712 | E80: =$G$76*(1+Supuestos!$B$8)^A80*(1-Supuestos!$B$12)^A80*Supuestos!$B$10 -> 0 | F80: =$I$76*(1+Supuestos!$B$8)^A80 -> 671638.61 | G80: =C80-D80-E80-F80 -> 13145864 | H80: =D80+E80+F80-(Supuestos!$B$19*$B$6+Supuestos!$B$20*$F$6)*(1+Supuestos!$B$8)^(A80-1) -> 4549520.5 | I80: =IF(A80<=Supuestos!$J$30,$K$76*(1-Supuestos!$B$11)^A80*Supuestos!$I$30*(1+Supuestos!$B$9)^(A80-1),0) -> 2203603.5 | J80: =E80*Supuestos!$K$30 -> 0 | K80: =D80-I80+E80-J80+F80-IF(A80<=Supuestos!$J$30,0,Supuestos!$B$19*$B$6*(1+Supuestos!$B$8)^(A80-1)) -> 2621747.1 | L80: =I80+J80-IF(A80<=Supuestos!$J$30,(Supuestos!$B$19*$B$6+Supuestos!$B$20*$F$6),Supuestos!$B$20*$F$6)*(1+Supuestos!$B$8)^(A80-1) -> 1927773.4
A81: 3 | B81: =IF(A81<=(Supuestos!$B$22-Supuestos!$B$24),"Autoabasto","CFE pleno") -> Autoabasto | C81: =IF(A81<=(Supuestos!$B$22-Supuestos!$B$24),$B$12,$B$10)*(1+Supuestos!$B$8)^A81 -> 19049487 | D81: =IF(A81<=(Supuestos!$B$22-Supuestos!$B$24),$C$76,$E$76)*(1+Supuestos!$B$8)^A81*(1-Supuestos!$B$11)^A81 -> 4380920 | E81: =$G$76*(1+Supuestos!$B$8)^A81*(1-Supuestos!$B$12)^A81*Supuestos!$B$10 -> 0 | F81: =$I$76*(1+Supuestos!$B$8)^A81 -> 711936.92 | G81: =C81-D81-E81-F81 -> 13956630 | H81: =D81+E81+F81-(Supuestos!$B$19*$B$6+Supuestos!$B$20*$F$6)*(1+Supuestos!$B$8)^(A81-1) -> 4800477 | I81: =IF(A81<=Supuestos!$J$30,$K$76*(1-Supuestos!$B$11)^A81*Supuestos!$I$30*(1+Supuestos!$B$9)^(A81-1),0) -> 2302214.8 | J81: =E81*Supuestos!$K$30 -> 0 | K81: =D81-I81+E81-J81+F81-IF(A81<=Supuestos!$J$30,0,Supuestos!$B$19*$B$6*(1+Supuestos!$B$8)^(A81-1)) -> 2790642.2 | L81: =I81+J81-IF(A81<=Supuestos!$J$30,(Supuestos!$B$19*$B$6+Supuestos!$B$20*$F$6),Supuestos!$B$20*$F$6)*(1+Supuestos!$B$8)^(A81-1) -> 2009834.8
A82: 4 | B82: =IF(A82<=(Supuestos!$B$22-Supuestos!$B$24),"Autoabasto","CFE pleno") -> Autoabasto | C82: =IF(A82<=(Supuestos!$B$22-Supuestos!$B$24),$B$12,$B$10)*(1+Supuestos!$B$8)^A82 -> 20192456 | D82: =IF(A82<=(Supuestos!$B$22-Supuestos!$B$24),$C$76,$E$76)*(1+Supuestos!$B$8)^A82*(1-Supuestos!$B$11)^A82 -> 4620556.4 | E82: =$G$76*(1+Supuestos!$B$8)^A82*(1-Supuestos!$B$12)^A82*Supuestos!$B$10 -> 0 | F82: =$I$76*(1+Supuestos!$B$8)^A82 -> 754653.14 | G82: =C82-D82-E82-F82 -> 14817247 | H82: =D82+E82+F82-(Supuestos!$B$19*$B$6+Supuestos!$B$20*$F$6)*(1+Supuestos!$B$8)^(A82-1) -> 5065286.8 | I82: =IF(A82<=Supuestos!$J$30,$K$76*(1-Supuestos!$B$11)^A82*Supuestos!$I$30*(1+Supuestos!$B$9)^(A82-1),0) -> 2405238.9 | J82: =E82*Supuestos!$K$30 -> 0 | K82: =D82-I82+E82-J82+F82-IF(A82<=Supuestos!$J$30,0,Supuestos!$B$19*$B$6*(1+Supuestos!$B$8)^(A82-1)) -> 2969970.6 | L82: =I82+J82-IF(A82<=Supuestos!$J$30,(Supuestos!$B$19*$B$6+Supuestos!$B$20*$F$6),Supuestos!$B$20*$F$6)*(1+Supuestos!$B$8)^(A82-1) -> 2095316.1
A83: 5 | B83: =IF(A83<=(Supuestos!$B$22-Supuestos!$B$24),"Autoabasto","CFE pleno") -> Autoabasto | C83: =IF(A83<=(Supuestos!$B$22-Supuestos!$B$24),$B$12,$B$10)*(1+Supuestos!$B$8)^A83 -> 21404004 | D83: =IF(A83<=(Supuestos!$B$22-Supuestos!$B$24),$C$76,$E$76)*(1+Supuestos!$B$8)^A83*(1-Supuestos!$B$11)^A83 -> 4873300.8 | E83: =$G$76*(1+Supuestos!$B$8)^A83*(1-Supuestos!$B$12)^A83*Supuestos!$B$10 -> 0 | F83: =$I$76*(1+Supuestos!$B$8)^A83 -> 799932.33 | G83: =C83-D83-E83-F83 -> 15730771 | H83: =D83+E83+F83-(Supuestos!$B$19*$B$6+Supuestos!$B$20*$F$6)*(1+Supuestos!$B$8)^(A83-1) -> 5344715 | I83: =IF(A83<=Supuestos!$J$30,$K$76*(1-Supuestos!$B$11)^A83*Supuestos!$I$30*(1+Supuestos!$B$9)^(A83-1),0) -> 2512873.3 | J83: =E83*Supuestos!$K$30 -> 0 | K83: =D83-I83+E83-J83+F83-IF(A83<=Supuestos!$J$30,0,Supuestos!$B$19*$B$6*(1+Supuestos!$B$8)^(A83-1)) -> 3160359.8 | L83: =I83+J83-IF(A83<=Supuestos!$J$30,(Supuestos!$B$19*$B$6+Supuestos!$B$20*$F$6),Supuestos!$B$20*$F$6)*(1+Supuestos!$B$8)^(A83-1) -> 2184355.2
A84: 6 | B84: =IF(A84<=(Supuestos!$B$22-Supuestos!$B$24),"Autoabasto","CFE pleno") -> Autoabasto | C84: =IF(A84<=(Supuestos!$B$22-Supuestos!$B$24),$B$12,$B$10)*(1+Supuestos!$B$8)^A84 -> 22688244 | D84: =IF(A84<=(Supuestos!$B$22-Supuestos!$B$24),$C$76,$E$76)*(1+Supuestos!$B$8)^A84*(1-Supuestos!$B$11)^A84 -> 5139870.3 | E84: =$G$76*(1+Supuestos!$B$8)^A84*(1-Supuestos!$B$12)^A84*Supuestos!$B$10 -> 0 | F84: =$I$76*(1+Supuestos!$B$8)^A84 -> 847928.27 | G84: =C84-D84-E84-F84 -> 16700445 | H84: =D84+E84+F84-(Supuestos!$B$19*$B$6+Supuestos!$B$20*$F$6)*(1+Supuestos!$B$8)^(A84-1) -> 5639569.4 | I84: =IF(A84<=Supuestos!$J$30,$K$76*(1-Supuestos!$B$11)^A84*Supuestos!$I$30*(1+Supuestos!$B$9)^(A84-1),0) -> 2625324.4 | J84: =E84*Supuestos!$K$30 -> 0 | K84: =D84-I84+E84-J84+F84-IF(A84<=Supuestos!$J$30,0,Supuestos!$B$19*$B$6*(1+Supuestos!$B$8)^(A84-1)) -> 3362474.2 | L84: =I84+J84-IF(A84<=Supuestos!$J$30,(Supuestos!$B$19*$B$6+Supuestos!$B$20*$F$6),Supuestos!$B$20*$F$6)*(1+Supuestos!$B$8)^(A84-1) -> 2277095.2
A85: 7 | B85: =IF(A85<=(Supuestos!$B$22-Supuestos!$B$24),"Autoabasto","CFE pleno") -> CFE pleno | C85: =IF(A85<=(Supuestos!$B$22-Supuestos!$B$24),$B$12,$B$10)*(1+Supuestos!$B$8)^A85 -> 24049539 | D85: =IF(A85<=(Supuestos!$B$22-Supuestos!$B$24),$C$76,$E$76)*(1+Supuestos!$B$8)^A85*(1-Supuestos!$B$11)^A85 -> 5421021.3 | E85: =$G$76*(1+Supuestos!$B$8)^A85*(1-Supuestos!$B$12)^A85*Supuestos!$B$10 -> 0 | F85: =$I$76*(1+Supuestos!$B$8)^A85 -> 898803.96 | G85: =C85-D85-E85-F85 -> 17729713 | H85: =D85+E85+F85-(Supuestos!$B$19*$B$6+Supuestos!$B$20*$F$6)*(1+Supuestos!$B$8)^(A85-1) -> 5950702.3 | I85: =IF(A85<=Supuestos!$J$30,$K$76*(1-Supuestos!$B$11)^A85*Supuestos!$I$30*(1+Supuestos!$B$9)^(A85-1),0) -> 2742807.7 | J85: =E85*Supuestos!$K$30 -> 0 | K85: =D85-I85+E85-J85+F85-IF(A85<=Supuestos!$J$30,0,Supuestos!$B$19*$B$6*(1+Supuestos!$B$8)^(A85-1)) -> 3577017.6 | L85: =I85+J85-IF(A85<=Supuestos!$J$30,(Supuestos!$B$19*$B$6+Supuestos!$B$20*$F$6),Supuestos!$B$20*$F$6)*(1+Supuestos!$B$8)^(A85-1) -> 2373684.7
A86: 8 | B86: =IF(A86<=(Supuestos!$B$22-Supuestos!$B$24),"Autoabasto","CFE pleno") -> CFE pleno | C86: =IF(A86<=(Supuestos!$B$22-Supuestos!$B$24),$B$12,$B$10)*(1+Supuestos!$B$8)^A86 -> 25492511 | D86: =IF(A86<=(Supuestos!$B$22-Supuestos!$B$24),$C$76,$E$76)*(1+Supuestos!$B$8)^A86*(1-Supuestos!$B$11)^A86 -> 5717551.1 | E86: =$G$76*(1+Supuestos!$B$8)^A86*(1-Supuestos!$B$12)^A86*Supuestos!$B$10 -> 0 | F86: =$I$76*(1+Supuestos!$B$8)^A86 -> 952732.2 | G86: =C86-D86-E86-F86 -> 18822228 | H86: =D86+E86+F86-(Supuestos!$B$19*$B$6+Supuestos!$B$20*$F$6)*(1+Supuestos!$B$8)^(A86-1) -> 6279013 | I86: =IF(A86<=Supuestos!$J$30,$K$76*(1-Supuestos!$B$11)^A86*Supuestos!$I$30*(1+Supuestos!$B$9)^(A86-1),0) -> 2865548.3 | J86: =E86*Supuestos!$K$30 -> 0 | K86: =D86-I86+E86-J86+F86-IF(A86<=Supuestos!$J$30,0,Supuestos!$B$19*$B$6*(1+Supuestos!$B$8)^(A86-1)) -> 3804735 | L86: =I86+J86-IF(A86<=Supuestos!$J$30,(Supuestos!$B$19*$B$6+Supuestos!$B$20*$F$6),Supuestos!$B$20*$F$6)*(1+Supuestos!$B$8)^(A86-1) -> 2474278
A87: 9 | B87: =IF(A87<=(Supuestos!$B$22-Supuestos!$B$24),"Autoabasto","CFE pleno") -> CFE pleno | C87: =IF(A87<=(Supuestos!$B$22-Supuestos!$B$24),$B$12,$B$10)*(1+Supuestos!$B$8)^A87 -> 27022062 | D87: =IF(A87<=(Supuestos!$B$22-Supuestos!$B$24),$C$76,$E$76)*(1+Supuestos!$B$8)^A87*(1-Supuestos!$B$11)^A87 -> 6030301.2 | E87: =$G$76*(1+Supuestos!$B$8)^A87*(1-Supuestos!$B$12)^A87*Supuestos!$B$10 -> 0 | F87: =$I$76*(1+Supuestos!$B$8)^A87 -> 1009896.1 | G87: =C87-D87-E87-F87 -> 19981864 | H87: =D87+E87+F87-(Supuestos!$B$19*$B$6+Supuestos!$B$20*$F$6)*(1+Supuestos!$B$8)^(A87-1) -> 6625450.8 | I87: =IF(A87<=Supuestos!$J$30,$K$76*(1-Supuestos!$B$11)^A87*Supuestos!$I$30*(1+Supuestos!$B$9)^(A87-1),0) -> 2993781.6 | J87: =E87*Supuestos!$K$30 -> 0 | K87: =D87-I87+E87-J87+F87-IF(A87<=Supuestos!$J$30,0,Supuestos!$B$19*$B$6*(1+Supuestos!$B$8)^(A87-1)) -> 4046415.7 | L87: =I87+J87-IF(A87<=Supuestos!$J$30,(Supuestos!$B$19*$B$6+Supuestos!$B$20*$F$6),Supuestos!$B$20*$F$6)*(1+Supuestos!$B$8)^(A87-1) -> 2579035.1
A88: 10 | B88: =IF(A88<=(Supuestos!$B$22-Supuestos!$B$24),"Autoabasto","CFE pleno") -> CFE pleno | C88: =IF(A88<=(Supuestos!$B$22-Supuestos!$B$24),$B$12,$B$10)*(1+Supuestos!$B$8)^A88 -> 28643385 | D88: =IF(A88<=(Supuestos!$B$22-Supuestos!$B$24),$C$76,$E$76)*(1+Supuestos!$B$8)^A88*(1-Supuestos!$B$11)^A88 -> 6360158.6 | E88: =$G$76*(1+Supuestos!$B$8)^A88*(1-Supuestos!$B$12)^A88*Supuestos!$B$10 -> 0 | F88: =$I$76*(1+Supuestos!$B$8)^A88 -> 1070489.9 | G88: =C88-D88-E88-F88 -> 21212737 | H88: =D88+E88+F88-(Supuestos!$B$19*$B$6+Supuestos!$B$20*$F$6)*(1+Supuestos!$B$8)^(A88-1) -> 6991017.2 | I88: =IF(A88<=Supuestos!$J$30,$K$76*(1-Supuestos!$B$11)^A88*Supuestos!$I$30*(1+Supuestos!$B$9)^(A88-1),0) -> 3127753.3 | J88: =E88*Supuestos!$K$30 -> 0 | K88: =D88-I88+E88-J88+F88-IF(A88<=Supuestos!$J$30,0,Supuestos!$B$19*$B$6*(1+Supuestos!$B$8)^(A88-1)) -> 4302895.2 | L88: =I88+J88-IF(A88<=Supuestos!$J$30,(Supuestos!$B$19*$B$6+Supuestos!$B$20*$F$6),Supuestos!$B$20*$F$6)*(1+Supuestos!$B$8)^(A88-1) -> 2688122
A89: 11 | B89: =IF(A89<=(Supuestos!$B$22-Supuestos!$B$24),"Autoabasto","CFE pleno") -> CFE pleno | C89: =IF(A89<=(Supuestos!$B$22-Supuestos!$B$24),$B$12,$B$10)*(1+Supuestos!$B$8)^A89 -> 30361989 | D89: =IF(A89<=(Supuestos!$B$22-Supuestos!$B$24),$C$76,$E$76)*(1+Supuestos!$B$8)^A89*(1-Supuestos!$B$11)^A89 -> 6708059.3 | E89: =$G$76*(1+Supuestos!$B$8)^A89*(1-Supuestos!$B$12)^A89*Supuestos!$B$10 -> 0 | F89: =$I$76*(1+Supuestos!$B$8)^A89 -> 1134719.3 | G89: =C89-D89-E89-F89 -> 22519210 | H89: =D89+E89+F89-(Supuestos!$B$19*$B$6+Supuestos!$B$20*$F$6)*(1+Supuestos!$B$8)^(A89-1) -> 7376769.4 | I89: =IF(A89<=Supuestos!$J$30,$K$76*(1-Supuestos!$B$11)^A89*Supuestos!$I$30*(1+Supuestos!$B$9)^(A89-1),0) -> 3267720.3 | J89: =E89*Supuestos!$K$30 -> 0 | K89: =D89-I89+E89-J89+F89-IF(A89<=Supuestos!$J$30,0,Supuestos!$B$19*$B$6*(1+Supuestos!$B$8)^(A89-1)) -> 4575058.3 | L89: =I89+J89-IF(A89<=Supuestos!$J$30,(Supuestos!$B$19*$B$6+Supuestos!$B$20*$F$6),Supuestos!$B$20*$F$6)*(1+Supuestos!$B$8)^(A89-1) -> 2801711.1
A90: 12 | B90: =IF(A90<=(Supuestos!$B$22-Supuestos!$B$24),"Autoabasto","CFE pleno") -> CFE pleno | C90: =IF(A90<=(Supuestos!$B$22-Supuestos!$B$24),$B$12,$B$10)*(1+Supuestos!$B$8)^A90 -> 32183708 | D90: =IF(A90<=(Supuestos!$B$22-Supuestos!$B$24),$C$76,$E$76)*(1+Supuestos!$B$8)^A90*(1-Supuestos!$B$11)^A90 -> 7074990.2 | E90: =$G$76*(1+Supuestos!$B$8)^A90*(1-Supuestos!$B$12)^A90*Supuestos!$B$10 -> 0 | F90: =$I$76*(1+Supuestos!$B$8)^A90 -> 1202802.5 | G90: =C90-D90-E90-F90 -> 23905915 | H90: =D90+E90+F90-(Supuestos!$B$19*$B$6+Supuestos!$B$20*$F$6)*(1+Supuestos!$B$8)^(A90-1) -> 7783822.9 | I90: =IF(A90<=Supuestos!$J$30,$K$76*(1-Supuestos!$B$11)^A90*Supuestos!$I$30*(1+Supuestos!$B$9)^(A90-1),0) -> 3413950.8 | J90: =E90*Supuestos!$K$30 -> 0 | K90: =D90-I90+E90-J90+F90-IF(A90<=Supuestos!$J$30,0,Supuestos!$B$19*$B$6*(1+Supuestos!$B$8)^(A90-1)) -> 4863841.9 | L90: =I90+J90-IF(A90<=Supuestos!$J$30,(Supuestos!$B$19*$B$6+Supuestos!$B$20*$F$6),Supuestos!$B$20*$F$6)*(1+Supuestos!$B$8)^(A90-1) -> 2919981
... A98: 20 | B98: =IF(A98<=(Supuestos!$B$22-Supuestos!$B$24),"Autoabasto","CFE pleno") -> CFE pleno | C98: =IF(A98<=(Supuestos!$B$22-Supuestos!$B$24),$B$12,$B$10)*(1+Supuestos!$B$8)^A98 -> 51295941 | D98: =IF(A98<=(Supuestos!$B$22-Supuestos!$B$24),$C$76,$E$76)*(1+Supuestos!$B$8)^A98*(1-Supuestos!$B$11)^A98 -> 10833216 | E98: =$G$76*(1+Supuestos!$B$8)^A98*(1-Supuestos!$B$12)^A98*Supuestos!$B$10 -> 0 | F98: =$I$76*(1+Supuestos!$B$8)^A98 -> 1917084.4 | G98: =C98-D98-E98-F98 -> 38545640 | H98: =D98+E98+F98-(Supuestos!$B$19*$B$6+Supuestos!$B$20*$F$6)*(1+Supuestos!$B$8)^(A98-1) -> 11962988 | I98: =IF(A98<=Supuestos!$J$30,$K$76*(1-Supuestos!$B$11)^A98*Supuestos!$I$30*(1+Supuestos!$B$9)^(A98-1),0) -> 0 | J98: =E98*Supuestos!$K$30 -> 0 | K98: =D98-I98+E98-J98+F98-IF(A98<=Supuestos!$J$30,0,Supuestos!$B$19*$B$6*(1+Supuestos!$B$8)^(A98-1)) -> 11962988 | L98: =I98+J98-IF(A98<=Supuestos!$J$30,(Supuestos!$B$19*$B$6+Supuestos!$B$20*$F$6),Supuestos!$B$20*$F$6)*(1+Supuestos!$B$8)^(A98-1) -> 0
A99: Σ | H99: =SUM(H79:H98) -> 1.5061899e+08 | K99: =SUM(K79:K98) -> 1.1291961e+08 | L99: =SUM(L79:L98) -> 37699378
F100: TIR compra: | G100: =IRR(H78:H98) -> 0.43596923 | I100: VPN compra @WACC: | K100: =NPV(Supuestos!$B$7,H79:H98)+H78 -> 35027264
F101: TIR financiador: | G101: =IRR(L78:L98) -> 0.18090212 | I101: VPN cliente PPA @WACC: | K101: =NPV(Supuestos!$B$7,K79:K98)+K78 -> 30609436
A102: Régimen: Autoabasto años 1-6 (2026-2031); CFE pleno desde 2032 (escalón en Tarifa Actual). El ahorro PV/BESS/FP persiste los 20 años; tras el plazo PPA el PV se transfiere a GEPP y conserva el 100% del ahorro.
A104: 7. COMPRAR vs PPA / AHORRO COMPARTIDO
A105: Métrica | B105: GEPP COMPRA | C105: PPA / Ahorro compartido
A106: Inversión GEPP $ | B106: =B26+B25+D25 -> 11298734 | C106: 0 | D106: Financiador funda todo (incl. capacitor)
A107: Beneficio GEPP año 1 $ | B107: =H79 -> 4311691.9 | C107: =K79 -> 2462692.9
A108: Beneficio 20 años acum. $ | B108: =H99 -> 1.5061899e+08 | C108: =SUM(K79:K98) -> 1.1291961e+08
A109: TIR (proyecto / financiador) | B109: =G100 -> 0.43596923 | C109: =G101 -> 0.18090212
A110: Tarifa PPA $/kWh (editable en Supuestos) | B110: — | C110: =Supuestos!$I$30 -> 1.6838
A111: Plazo PPA años / PV se transfiere al cliente al término | C111: =Supuestos!$J$30 -> 15
A113: 8. POR QUÉ ESTE DIMENSIONAMIENTO ES EL ÓPTIMO PARA ESTE SITIO
A114: PV 699 kWp se mantiene DELIBERADAMENTE bajo 0.7 MW para calificar como generador EXENTO (medición neta, sin permiso CNE) — la vía más rápida y barata, y el mejor ROI de la cartera (TIR 44%). SIN BESS: el umbral satura 9/12 meses, así que una batería no recortaría demanda facturable y no se pagaría. FP corrige la multa (FP 89%). Subir el PV cruzaría a permiso y exportaría sin crédito: este tamaño es el óptimo regulatorio y económico.

Sheet Proplasa PR1
A1: PROPLASA PR1 — Memoria de cálculo trazable y propuesta
A2: Medidor 806DYN · GDMTH SIN · Demanda contratada 2,600 kW · AUTOCONSUMO interconectado (>0.7 MW) — permiso SIMPLIFICADO CNE
A3: GEPP pide: Combinar autoabasto (ENEL) con generación solar en sitio
A5: PARÁMETROS DEL SISTEMA (desde Supuestos — edítalos allí)
A6: PV kWp | B6: =Supuestos!$B$31 -> 839.41 | C6: BESS kW | D6: =Supuestos!$C$31 -> 501 | E6: BESS kWh | F6: =Supuestos!$D$31 -> 980 | G6: Entrega útil kWh | H6: =Supuestos!$D$31*Supuestos!$B$17*SQRT(Supuestos!$B$18) -> 921.79198 | I6: FP corr. | J6: =Supuestos!$E$31 -> No | K6: Calib→recibo | L6: =$B$10/(SUM(P45:P56)+SUM(R30:R41)) -> 1
A8: 1. ESTRUCTURA DE COSTO Y AHORRO (2025, pre-IVA · datos del workbook GEPP + motor)
A9: Concepto | B9: $ / año | C9: $ / kWh | D9: kWh | E9: Nota
A10: CFE BRUTO = Tarifa Actual (todo a CFE pleno, sin autoabasto) | B10: 36585609 | C10: =B10/D10 -> 2.2459909 | D10: 16289295 | E10: Lo que pagarían 100% en CFE sin ENEL/Tala ni PV/BESS
A11: (−) Ahorro autoabasto (ENEL) | B11: 4407279.5 | E11: Beneficio ENEL ($1.78/kWh vs CFE; validado por colapso 2026)
A12: (=) Costo actual que paga GEPP hoy | B12: =B10-B11 -> 32178329 | C12: =B12/D12 -> 1.975428 | D12: =D10 -> 16289295
A13: › CFE (tarifa CFE plena) | B13: 5255585.9 | C13: =B13/D13 -> 2.4595534 | D13: 2136805
A14: › ENEL | B14: 26922743 | C14: =B14/D14 -> 1.9023326 | D14: 14152490
A15: › Mezcla de suministro 2025 | B15: =D13/D12 -> 0.13117848 | C15: CFE | D15: =D14/D12 -> 0.86882152 | E15: ENEL (en 2026 ENEL ya colapsó → CFE ~85%)
A16: Ahorros del proyecto (motor 2025, sobre la carga física):
A17: (−) Ahorro PV (energía intermedia + demanda vía umbral) | B17: =F72 -> 2532058.3 | D17: =C72 -> 1393504.5 | E17: Gen solar kWh/año →
A18: (−) Ahorro BESS (recorte de punta + arbitraje) | B18: =G72 -> 1985137
A19: (−) Ahorro FP (corrección factor de potencia) | B19: =H72 -> 0 | E19: FP sano — sin multa
A20: (=) Costo neto con proyecto (hoy) | B20: =B12-B17-B18-B19 -> 27661134
A21: Ahorro proyecto PV+BESS+FP (vs costo hoy) | B21: =B17+B18+B19 -> 4517195.3 | C21: =B21/B12 -> 0.14038004
A22: Ahorro TOTAL vs CFE bruto (incl. autoabasto+proyecto) | B22: =B10-B20 -> 8924474.8 | C22: =B22/B10 -> 0.24393403
A24: 2. CAPEX (fórmulas vivas desde Supuestos)
A25: CAPEX PV = kWp×1000×USD/Wp×FX | B25: =$B$6*1000*Supuestos!$F$31*Supuestos!$B$5 -> 11048734 | C25: CAPEX BESS = kWh×USD/kWh×FX | D25: =$F$6*Supuestos!$G$31*Supuestos!$B$5 -> 4815720
A26: CAPEX Capacitor FP (financiador en PPA) | B26: =Supuestos!$H$31 -> 0 | C26: CAPEX TOTAL (compra) | D26: =B25+D25+B26 -> 15864454 | E26: Bajo PPA, el capacitor lo paga el financiador → el cliente no desembolsa
A28: 3. ENTRADAS MENSUALES (AZUL = datos del recibo / recurso 2025)
A29: Mes | B29: kWh Base | C29: kWh Int | D29: kWh Punta | E29: Días | F29: Dem Pta kW | G29: Dem Máx kW | H29: T.Int $ | I29: T.Base $ | J29: T.Pta $ | K29: T.Cap $ | L29: T.Dist $ | M29: T.Fijo $ | N29: Rend | O29: %AC | P29: HrsP | Q29: DíasP | R29: Bonif FP
A30: Ene | B30: 455237 | C30: 729971 | D30: 183178 | E30: 31 | F30: 1892 | G30: 1930 | H30: 1.819675 | I30: 1.10665 | J30: 2.1272 | K30: 402.0725 | L30: 86.15 | M30: 703.36 | N30: 142.8 | O30: 1 | P30: 4 | Q30: 22 | R30: 0
A31: Feb | B31: 476589 | C31: 681958 | D31: 167798 | E31: 28 | F31: 1903 | G31: 1936 | H31: 1.819675 | I31: 1.10665 | J31: 2.1272 | K31: 402.0725 | L31: 86.15 | M31: 703.36 | N31: 139.1 | O31: 1 | P31: 4 | Q31: 19 | R31: 0
A32: Mar | B32: 535513 | C32: 750251 | D32: 182294 | E32: 31 | F32: 1771 | G32: 1793 | H32: 1.819675 | I32: 1.10665 | J32: 2.1272 | K32: 402.0725 | L32: 86.15 | M32: 703.36 | N32: 170.1 | O32: 1 | P32: 4 | Q32: 20 | R32: 0
A33: Abr | B33: 497333 | C33: 867045 | D33: 108027 | E33: 30 | F33: 1579 | G33: 1622 | H33: 1.819675 | I33: 1.10665 | J33: 2.1272 | K33: 402.0725 | L33: 86.15 | M33: 703.36 | N33: 150.7 | O33: 1 | P33: 2 | Q33: 22 | R33: -15843.7
A34: May | B34: 546627 | C34: 924218 | D34: 89553 | E34: 31 | F34: 1654 | G34: 1700 | H34: 1.819675 | I34: 1.10665 | J34: 2.1272 | K34: 402.0725 | L34: 86.15 | M34: 703.36 | N34: 143.1 | O34: 1 | P34: 2 | Q34: 21 | R34: -18059.94
A35: Jun | B35: 467527 | C35: 810870 | D35: 82141 | E35: 30 | F35: 1465 | G35: 1532 | H35: 1.819675 | I35: 1.10665 | J35: 2.1272 | K35: 402.0725 | L35: 86.15 | M35: 703.36 | N35: 133.9 | O35: 1 | P35: 2 | Q35: 21 | R35: -6803.62
A36: Jul | B36: 414209 | C36: 746631 | D36: 74300 | E36: 31 | F36: 1582 | G36: 1672 | H36: 1.819675 | I36: 1.10665 | J36: 2.1272 | K36: 402.0725 | L36: 86.15 | M36: 703.36 | N36: 135.2 | O36: 1 | P36: 2 | Q36: 23 | R36: -3279.85
A37: Ago | B37: 511027 | C37: 868483 | D37: 84864 | E37: 31 | F37: 1515 | G37: 1568 | H37: 1.819675 | I37: 1.10665 | J37: 2.1272 | K37: 402.0725 | L37: 86.15 | M37: 703.36 | N37: 126.5 | O37: 1 | P37: 2 | Q37: 21 | R37: -8395.35
A38: Sep | B38: 471225 | C38: 799977 | D38: 80458 | E38: 30 | F38: 2279 | G38: 2356 | H38: 1.819675 | I38: 1.10665 | J38: 2.1272 | K38: 402.0725 | L38: 86.15 | M38: 703.36 | N38: 119.5 | O38: 1 | P38: 2 | Q38: 21 | R38: -486.12
A39: Oct | B39: 435183 | C39: 788394 | D39: 98384 | E39: 31 | F39: 1750 | G39: 1832 | H39: 1.819675 | I39: 1.10665 | J39: 2.1272 | K39: 402.0725 | L39: 86.15 | M39: 703.36 | N39: 131.7 | O39: 1 | P39: 2 | Q39: 23 | R39: -289.26
A40: Nov | B40: 431457 | C40: 617240 | D40: 150654 | E40: 30 | F40: 2026 | G40: 2026 | H40: 1.819675 | I40: 1.10665 | J40: 2.1272 | K40: 402.0725 | L40: 86.15 | M40: 703.36 | N40: 136.6 | O40: 1 | P40: 4 | Q40: 19 | R40: 0
A41: Dic | B41: 395911 | C41: 618556 | D41: 146212 | E41: 31 | F41: 2124 | G41: 2124 | H41: 1.819675 | I41: 1.10665 | J41: 2.1272 | K41: 402.0725 | L41: 86.15 | M41: 703.36 | N41: 130.9 | O41: 1 | P41: 4 | Q41: 22 | R41: -12.55
A42: 4. CÁLCULO DE AHORRO MENSUAL (motor — fórmulas que referencian las ENTRADAS)
A43: Mes | B43: Gen kWh | C43: Umbral kW | D43: Autocons | E43: Ah PV ener | F43: Umbral post | G43: Cap base | H43: Cap pre-B | I43: Ah PV dem | J43: Recorte BESS | K43: Cap post | L43: Ah BESS dem | M43: Desc kWh | N43: Arbitraje $ | O43: Fac.AA | P43: mem $ | Q43: Ah PV+BESS
A45: =A30 -> Ene | B45: =$B$6*N30 -> 119867.75 | C45: =(B30+C30+D30)/(E30*24*Supuestos!$B$16) -> 3226.7167 | D45: =MIN(B45*O30,C30) -> 119867.75 | E45: =D45*H30*O45 -> 218120.34 | F45: =((B30+C30+D30)-D45)/(E30*24*Supuestos!$B$16) -> 2944.063 | G45: =MIN(F30,C45) -> 1892 | H45: =MIN(F30,F45) -> 1892 | I45: =(G45-H45)*K30 -> 0 | J45: =IF(P30=0,0,MIN($D$6,$H$6/P30)) -> 230.448 | K45: =MIN(MAX(F30-J45,0),F45) -> 1661.552 | L45: =(H45-K45)*K30 -> 92656.801 | M45: =IF(P30=0,0,MIN($H$6*Q30,D30)) -> 20279.424 | N45: =M45*J30-(M45/Supuestos!$B$18)*I30 -> 19761.073 | O45: 1 | P45: =M30+B30*I30+C30*H30+D30*J30+G45*K30+MIN(G30,C45)*L30 -> 3149448.3 | Q45: =(E45+I45)+(L45+N45) -> 330538.22
A46: =A31 -> Feb | B46: =$B$6*N31 -> 116761.93 | C46: =(B31+C31+D31)/(E31*24*Supuestos!$B$16) -> 3462.6801 | D46: =MIN(B46*O31,C31) -> 116761.93 | E46: =D46*H31*O46 -> 212468.77 | F46: =((B31+C31+D31)-D46)/(E31*24*Supuestos!$B$16) -> 3157.8505 | G46: =MIN(F31,C46) -> 1903 | H46: =MIN(F31,F46) -> 1903 | I46: =(G46-H46)*K31 -> 0 | J46: =IF(P31=0,0,MIN($D$6,$H$6/P31)) -> 230.448 | K46: =MIN(MAX(F31-J46,0),F46) -> 1672.552 | L46: =(H46-K46)*K31 -> 92656.801 | M46: =IF(P31=0,0,MIN($H$6*Q31,D31)) -> 17514.048 | N46: =M46*J31-(M46/Supuestos!$B$18)*I31 -> 17066.381 | O46: 1 | P46: =M31+B31*I31+C31*H31+D31*J31+G46*K31+MIN(G31,C46)*L31 -> 3057932.8 | Q46: =(E46+I46)+(L46+N46) -> 322191.95
A47: =A32 -> Mar | B47: =$B$6*N32 -> 142783.64 | C47: =(B32+C32+D32)/(E32*24*Supuestos!$B$16) -> 3461.7478 | D47: =MIN(B47*O32,C32) -> 142783.64 | E47: =D47*H32*O47 -> 259819.82 | F47: =((B32+C32+D32)-D47)/(E32*24*Supuestos!$B$16) -> 3125.0574 | G47: =MIN(F32,C47) -> 1771 | H47: =MIN(F32,F47) -> 1771 | I47: =(G47-H47)*K32 -> 0 | J47: =IF(P32=0,0,MIN($D$6,$H$6/P32)) -> 230.448 | K47: =MIN(MAX(F32-J47,0),F47) -> 1540.552 | L47: =(H47-K47)*K32 -> 92656.801 | M47: =IF(P32=0,0,MIN($H$6*Q32,D32)) -> 18435.84 | N47: =M47*J32-(M47/Supuestos!$B$18)*I32 -> 17964.612 | O47: 1 | P47: =M32+B32*I32+C32*H32+D32*J32+G47*K32+MIN(G32,C47)*L32 -> 3212855 | Q47: =(E47+I47)+(L47+N47) -> 370441.24
A48: =A33 -> Abr | B48: =$B$6*N33 -> 126499.09 | C48: =(B33+C33+D33)/(E33*24*Supuestos!$B$16) -> 3587.7315 | D48: =MIN(B48*O33,C33) -> 126499.09 | E48: =D48*H33*O48 -> 230187.23 | F48: =((B33+C33+D33)-D48)/(E33*24*Supuestos!$B$16) -> 3279.4978 | G48: =MIN(F33,C48) -> 1579 | H48: =MIN(F33,F48) -> 1579 | I48: =(G48-H48)*K33 -> 0 | J48: =IF(P33=0,0,MIN($D$6,$H$6/P33)) -> 460.89599 | K48: =MIN(MAX(F33-J48,0),F48) -> 1118.104 | L48: =(H48-K48)*K33 -> 185313.6 | M48: =IF(P33=0,0,MIN($H$6*Q33,D33)) -> 20279.424 | N48: =M48*J33-(M48/Supuestos!$B$18)*I33 -> 19761.073 | O48: 1 | P48: =M33+B33*I33+C33*H33+D33*J33+G48*K33+MIN(G33,C48)*L33 -> 3133219.8 | Q48: =(E48+I48)+(L48+N48) -> 435261.9
A49: =A34 -> May | B49: =$B$6*N34 -> 120119.57 | C49: =(B34+C34+D34)/(E34*24*Supuestos!$B$16) -> 3679.4897 | D49: =MIN(B49*O34,C34) -> 120119.57 | E49: =D49*H34*O49 -> 218578.58 | F49: =((B34+C34+D34)-D49)/(E34*24*Supuestos!$B$16) -> 3396.2423 | G49: =MIN(F34,C49) -> 1654 | H49: =MIN(F34,F49) -> 1654 | I49: =(G49-H49)*K34 -> 0 | J49: =IF(P34=0,0,MIN($D$6,$H$6/P34)) -> 460.89599 | K49: =MIN(MAX(F34-J49,0),F49) -> 1193.104 | L49: =(H49-K49)*K34 -> 185313.6 | M49: =IF(P34=0,0,MIN($H$6*Q34,D34)) -> 19357.632 | N49: =M49*J34-(M49/Supuestos!$B$18)*I34 -> 18862.842 | O49: 1 | P49: =M34+B34*I34+C34*H34+D34*J34+G49*K34+MIN(G34,C49)*L34 -> 3289384.6 | Q49: =(E49+I49)+(L49+N49) -> 422755.03
A50: =A35 -> Jun | B50: =$B$6*N35 -> 112397 | C50: =(B35+C35+D35)/(E35*24*Supuestos!$B$16) -> 3315.1511 | D50: =MIN(B50*O35,C35) -> 112397 | E50: =D50*H35*O50 -> 204526.01 | F50: =((B35+C35+D35)-D50)/(E35*24*Supuestos!$B$16) -> 3041.2792 | G50: =MIN(F35,C50) -> 1465 | H50: =MIN(F35,F50) -> 1465 | I50: =(G50-H50)*K35 -> 0 | J50: =IF(P35=0,0,MIN($D$6,$H$6/P35)) -> 460.89599 | K50: =MIN(MAX(F35-J50,0),F50) -> 1004.104 | L50: =(H50-K50)*K35 -> 185313.6 | M50: =IF(P35=0,0,MIN($H$6*Q35,D35)) -> 19357.632 | N50: =M50*J35-(M50/Supuestos!$B$18)*I35 -> 18862.842 | O50: 1 | P50: =M35+B35*I35+C35*H35+D35*J35+G50*K35+MIN(G35,C50)*L35 -> 2889360.3 | Q50: =(E50+I50)+(L50+N50) -> 408702.45
A51: =A36 -> Jul | B51: =$B$6*N36 -> 113488.23 | C51: =(B36+C36+D36)/(E36*24*Supuestos!$B$16) -> 2912.5165 | D51: =MIN(B51*O36,C36) -> 113488.23 | E51: =D51*H36*O51 -> 206511.7 | F51: =((B36+C36+D36)-D51)/(E36*24*Supuestos!$B$16) -> 2644.9061 | G51: =MIN(F36,C51) -> 1582 | H51: =MIN(F36,F51) -> 1582 | I51: =(G51-H51)*K36 -> 0 | J51: =IF(P36=0,0,MIN($D$6,$H$6/P36)) -> 460.89599 | K51: =MIN(MAX(F36-J51,0),F51) -> 1121.104 | L51: =(H51-K51)*K36 -> 185313.6 | M51: =IF(P36=0,0,MIN($H$6*Q36,D36)) -> 21201.216 | N51: =M51*J36-(M51/Supuestos!$B$18)*I36 -> 20659.304 | O51: 1 | P51: =M36+B36*I36+C36*H36+D36*J36+G51*K36+MIN(G36,C51)*L36 -> 2755886 | Q51: =(E51+I51)+(L51+N51) -> 412484.61
A52: =A37 -> Ago | B52: =$B$6*N37 -> 106185.36 | C52: =(B37+C37+D37)/(E37*24*Supuestos!$B$16) -> 3453.0607 | D52: =MIN(B52*O37,C37) -> 106185.36 | E52: =D52*H37*O52 -> 193222.85 | F52: =((B37+C37+D37)-D52)/(E37*24*Supuestos!$B$16) -> 3202.6708 | G52: =MIN(F37,C52) -> 1515 | H52: =MIN(F37,F52) -> 1515 | I52: =(G52-H52)*K37 -> 0 | J52: =IF(P37=0,0,MIN($D$6,$H$6/P37)) -> 460.89599 | K52: =MIN(MAX(F37-J52,0),F52) -> 1054.104 | L52: =(H52-K52)*K37 -> 185313.6 | M52: =IF(P37=0,0,MIN($H$6*Q37,D37)) -> 19357.632 | N52: =M52*J37-(M52/Supuestos!$B$18)*I37 -> 18862.842 | O52: 1 | P52: =M37+B37*I37+C37*H37+D37*J37+G52*K37+MIN(G37,C52)*L37 -> 3071333.9 | Q52: =(E52+I52)+(L52+N52) -> 397399.3
A53: =A38 -> Sep | B53: =$B$6*N38 -> 100309.49 | C53: =(B38+C38+D38)/(E38*24*Supuestos!$B$16) -> 3293.5185 | D53: =MIN(B53*O38,C38) -> 100309.49 | E53: =D53*H38*O53 -> 182530.68 | F53: =((B38+C38+D38)-D53)/(E38*24*Supuestos!$B$16) -> 3049.0997 | G53: =MIN(F38,C53) -> 2279 | H53: =MIN(F38,F53) -> 2279 | I53: =(G53-H53)*K38 -> 0 | J53: =IF(P38=0,0,MIN($D$6,$H$6/P38)) -> 460.89599 | K53: =MIN(MAX(F38-J53,0),F53) -> 1818.104 | L53: =(H53-K53)*K38 -> 185313.6 | M53: =IF(P38=0,0,MIN($H$6*Q38,D38)) -> 19357.632 | N53: =M53*J38-(M53/Supuestos!$B$18)*I38 -> 18862.842 | O53: 1 | P53: =M38+B38*I38+C38*H38+D38*J38+G53*K38+MIN(G38,C53)*L38 -> 3268325.5 | Q53: =(E53+I53)+(L53+N53) -> 386707.13
A54: =A39 -> Oct | B54: =$B$6*N39 -> 110550.3 | C54: =(B39+C39+D39)/(E39*24*Supuestos!$B$16) -> 3117.2444 | D54: =MIN(B54*O39,C39) -> 110550.3 | E54: =D54*H39*O54 -> 201165.61 | F54: =((B39+C39+D39)-D54)/(E39*24*Supuestos!$B$16) -> 2856.5617 | G54: =MIN(F39,C54) -> 1750 | H54: =MIN(F39,F54) -> 1750 | I54: =(G54-H54)*K39 -> 0 | J54: =IF(P39=0,0,MIN($D$6,$H$6/P39)) -> 460.89599 | K54: =MIN(MAX(F39-J54,0),F54) -> 1289.104 | L54: =(H54-K54)*K39 -> 185313.6 | M54: =IF(P39=0,0,MIN($H$6*Q39,D39)) -> 21201.216 | N54: =M54*J39-(M54/Supuestos!$B$18)*I39 -> 20659.304 | O54: 1 | P54: =M39+B39*I39+C39*H39+D39*J39+G54*K39+MIN(G39,C54)*L39 -> 2987655.6 | Q54: =(E54+I54)+(L54+N54) -> 407138.52
A55: =A40 -> Nov | B55: =$B$6*N40 -> 114663.41 | C55: =(B40+C40+D40)/(E40*24*Supuestos!$B$16) -> 2922.3952 | D55: =MIN(B55*O40,C40) -> 114663.41 | E55: =D55*H40*O55 -> 208650.13 | F55: =((B40+C40+D40)-D55)/(E40*24*Supuestos!$B$16) -> 2643.001 | G55: =MIN(F40,C55) -> 2026 | H55: =MIN(F40,F55) -> 2026 | I55: =(G55-H55)*K40 -> 0 | J55: =IF(P40=0,0,MIN($D$6,$H$6/P40)) -> 230.448 | K55: =MIN(MAX(F40-J55,0),F55) -> 1795.552 | L55: =(H55-K55)*K40 -> 92656.801 | M55: =IF(P40=0,0,MIN($H$6*Q40,D40)) -> 17514.048 | N55: =M55*J40-(M55/Supuestos!$B$18)*I40 -> 17066.381 | O55: 1 | P55: =M40+B40*I40+C40*H40+D40*J40+G55*K40+MIN(G40,C55)*L40 -> 2910961.4 | Q55: =(E55+I55)+(L55+N55) -> 318373.32
A56: =A41 -> Dic | B56: =$B$6*N41 -> 109878.77 | C56: =(B41+C41+D41)/(E41*24*Supuestos!$B$16) -> 2736.9341 | D56: =MIN(B56*O41,C41) -> 109878.77 | E56: =D56*H41*O56 -> 199943.65 | F56: =((B41+C41+D41)-D56)/(E41*24*Supuestos!$B$16) -> 2477.8349 | G56: =MIN(F41,C56) -> 2124 | H56: =MIN(F41,F56) -> 2124 | I56: =(G56-H56)*K41 -> 0 | J56: =IF(P41=0,0,MIN($D$6,$H$6/P41)) -> 230.448 | K56: =MIN(MAX(F41-J56,0),F56) -> 1893.552 | L56: =(H56-K56)*K41 -> 92656.801 | M56: =IF(P41=0,0,MIN($H$6*Q41,D41)) -> 20279.424 | N56: =M56*J41-(M56/Supuestos!$B$18)*I41 -> 19761.073 | O56: 1 | P56: =M41+B41*I41+C41*H41+D41*J41+G56*K41+MIN(G41,C56)*L41 -> 2912415.9 | Q56: =(E56+I56)+(L56+N56) -> 312361.52
A57: Recorte BESS = MIN(kW batería, entrega útil ÷ HrsP). Desc = MIN(entrega×DíasP, kWh punta). Arbitraje carga en base y descarga en punta. Fac.AA aplica el descuento de zafra (sólo Ixtlahuacán, pre-2032).
A58: 5. RESUMEN MENSUAL — Tarifa Actual (CFE pleno) / Ahorros / Costo con proyecto
A59: Mes | B59: kWh Consumo | C59: Gen PV kWh | D59: BESS desc kWh | E59: Tarifa Actual $ | F59: Ahorro PV $ | G59: Ahorro BESS $ | H59: Ahorro FP $ | I59: Costo c/proyecto $ | J59: Ahorro $ | K59: Ahorro %
A60: =A30 -> Ene | B60: =B30+C30+D30 -> 1368386 | C60: =B45 -> 119867.75 | D60: =M45 -> 20279.424 | E60: =(P45+R30)*$L$6 -> 3149448.3 | F60: =(E45+I45)*(1-IF(R30<0,-R30/P45,0)) -> 218120.34 | G60: =(L45+N45)*(1-IF(R30<0,-R30/P45,0)) -> 112417.87 | H60: =IF($J$6="Sí",MAX(0,R30),0) -> 0 | I60: =E60-F60-G60-H60 -> 2818910.1 | J60: =F60+G60+H60 -> 330538.22 | K60: =J60/E60 -> 0.10495115
A61: =A31 -> Feb | B61: =B31+C31+D31 -> 1326345 | C61: =B46 -> 116761.93 | D61: =M46 -> 17514.048 | E61: =(P46+R31)*$L$6 -> 3057932.8 | F61: =(E46+I46)*(1-IF(R31<0,-R31/P46,0)) -> 212468.77 | G61: =(L46+N46)*(1-IF(R31<0,-R31/P46,0)) -> 109723.18 | H61: =IF($J$6="Sí",MAX(0,R31),0) -> 0 | I61: =E61-F61-G61-H61 -> 2735740.8 | J61: =F61+G61+H61 -> 322191.95 | K61: =J61/E61 -> 0.10536267
A62: =A32 -> Mar | B62: =B32+C32+D32 -> 1468058 | C62: =B47 -> 142783.64 | D62: =M47 -> 18435.84 | E62: =(P47+R32)*$L$6 -> 3212855 | F62: =(E47+I47)*(1-IF(R32<0,-R32/P47,0)) -> 259819.82 | G62: =(L47+N47)*(1-IF(R32<0,-R32/P47,0)) -> 110621.41 | H62: =IF($J$6="Sí",MAX(0,R32),0) -> 0 | I62: =E62-F62-G62-H62 -> 2842413.7 | J62: =F62+G62+H62 -> 370441.24 | K62: =J62/E62 -> 0.11529971
A63: =A33 -> Abr | B63: =B33+C33+D33 -> 1472405 | C63: =B48 -> 126499.09 | D63: =M48 -> 20279.424 | E63: =(P48+R33)*$L$6 -> 3117376.1 | F63: =(E48+I48)*(1-IF(R33<0,-R33/P48,0)) -> 229023.24 | G63: =(L48+N48)*(1-IF(R33<0,-R33/P48,0)) -> 204037.68 | H63: =IF($J$6="Sí",MAX(0,R33),0) -> 0 | I63: =E63-F63-G63-H63 -> 2684315.2 | J63: =F63+G63+H63 -> 433060.92 | K63: =J63/E63 -> 0.1389184
A64: =A34 -> May | B64: =B34+C34+D34 -> 1560398 | C64: =B49 -> 120119.57 | D64: =M49 -> 19357.632 | E64: =(P49+R34)*$L$6 -> 3271324.6 | F64: =(E49+I49)*(1-IF(R34<0,-R34/P49,0)) -> 217378.5 | G64: =(L49+N49)*(1-IF(R34<0,-R34/P49,0)) -> 203055.44 | H64: =IF($J$6="Sí",MAX(0,R34),0) -> 0 | I64: =E64-F64-G64-H64 -> 2850890.7 | J64: =F64+G64+H64 -> 420433.94 | K64: =J64/E64 -> 0.12852101
A65: =A35 -> Jun | B65: =B35+C35+D35 -> 1360538 | C65: =B50 -> 112397 | D65: =M50 -> 19357.632 | E65: =(P50+R35)*$L$6 -> 2882556.7 | F65: =(E50+I50)*(1-IF(R35<0,-R35/P50,0)) -> 204044.41 | G65: =(L50+N50)*(1-IF(R35<0,-R35/P50,0)) -> 203695.67 | H65: =IF($J$6="Sí",MAX(0,R35),0) -> 0 | I65: =E65-F65-G65-H65 -> 2474816.6 | J65: =F65+G65+H65 -> 407740.08 | K65: =J65/E65 -> 0.14145084
A66: =A36 -> Jul | B66: =B36+C36+D36 -> 1235140 | C66: =B51 -> 113488.23 | D66: =M51 -> 21201.216 | E66: =(P51+R36)*$L$6 -> 2752606.1 | F66: =(E51+I51)*(1-IF(R36<0,-R36/P51,0)) -> 206265.92 | G66: =(L51+N51)*(1-IF(R36<0,-R36/P51,0)) -> 205727.77 | H66: =IF($J$6="Sí",MAX(0,R36),0) -> 0 | I66: =E66-F66-G66-H66 -> 2340612.4 | J66: =F66+G66+H66 -> 411993.7 | K66: =J66/E66 -> 0.14967405
A67: =A37 -> Ago | B67: =B37+C37+D37 -> 1464374 | C67: =B52 -> 106185.36 | D67: =M52 -> 19357.632 | E67: =(P52+R37)*$L$6 -> 3062938.6 | F67: =(E52+I52)*(1-IF(R37<0,-R37/P52,0)) -> 192694.69 | G67: =(L52+N52)*(1-IF(R37<0,-R37/P52,0)) -> 203618.34 | H67: =IF($J$6="Sí",MAX(0,R37),0) -> 0 | I67: =E67-F67-G67-H67 -> 2666625.6 | J67: =F67+G67+H67 -> 396313.03 | K67: =J67/E67 -> 0.12938981
A68: =A38 -> Sep | B68: =B38+C38+D38 -> 1351660 | C68: =B53 -> 100309.49 | D68: =M53 -> 19357.632 | E68: =(P53+R38)*$L$6 -> 3267839.4 | F68: =(E53+I53)*(1-IF(R38<0,-R38/P53,0)) -> 182503.53 | G68: =(L53+N53)*(1-IF(R38<0,-R38/P53,0)) -> 204146.08 | H68: =IF($J$6="Sí",MAX(0,R38),0) -> 0 | I68: =E68-F68-G68-H68 -> 2881189.8 | J68: =F68+G68+H68 -> 386649.61 | K68: =J68/E68 -> 0.11831965
A69: =A39 -> Oct | B69: =B39+C39+D39 -> 1321961 | C69: =B54 -> 110550.3 | D69: =M54 -> 21201.216 | E69: =(P54+R39)*$L$6 -> 2987366.3 | F69: =(E54+I54)*(1-IF(R39<0,-R39/P54,0)) -> 201146.14 | G69: =(L54+N54)*(1-IF(R39<0,-R39/P54,0)) -> 205952.96 | H69: =IF($J$6="Sí",MAX(0,R39),0) -> 0 | I69: =E69-F69-G69-H69 -> 2580267.2 | J69: =F69+G69+H69 -> 407099.1 | K69: =J69/E69 -> 0.13627358
A70: =A40 -> Nov | B70: =B40+C40+D40 -> 1199351 | C70: =B55 -> 114663.41 | D70: =M55 -> 17514.048 | E70: =(P55+R40)*$L$6 -> 2910961.4 | F70: =(E55+I55)*(1-IF(R40<0,-R40/P55,0)) -> 208650.13 | G70: =(L55+N55)*(1-IF(R40<0,-R40/P55,0)) -> 109723.18 | H70: =IF($J$6="Sí",MAX(0,R40),0) -> 0 | I70: =E70-F70-G70-H70 -> 2592588.1 | J70: =F70+G70+H70 -> 318373.32 | K70: =J70/E70 -> 0.1093705
A71: =A41 -> Dic | B71: =B41+C41+D41 -> 1160679 | C71: =B56 -> 109878.77 | D71: =M56 -> 20279.424 | E71: =(P56+R41)*$L$6 -> 2912403.4 | F71: =(E56+I56)*(1-IF(R41<0,-R41/P56,0)) -> 199942.79 | G71: =(L56+N56)*(1-IF(R41<0,-R41/P56,0)) -> 112417.39 | H71: =IF($J$6="Sí",MAX(0,R41),0) -> 0 | I71: =E71-F71-G71-H71 -> 2600043.2 | J71: =F71+G71+H71 -> 312360.18 | K71: =J71/E71 -> 0.10725169
A72: TOTAL | B72: =SUM(B60:B71) -> 16289295 | C72: =SUM(C60:C71) -> 1393504.5 | D72: =SUM(D60:D71) -> 234135.16 | E72: =SUM(E60:E71) -> 36585609 | F72: =SUM(F60:F71) -> 2532058.3 | G72: =SUM(G60:G71) -> 1985137 | H72: =SUM(H60:H71) -> 0 | I72: =SUM(I60:I71) -> 32068413 | J72: =SUM(J60:J71) -> 4517195.3 | K72: =J72/E72 -> 0.12346918
A73: Tarifa Actual (Σ) = recibo a CFE pleno $36,585,609 (dato workbook GEPP, calibrado del motor ×1.000). Ahorro = motor (golden 18/18).
A75: 6. PROYECCIÓN 20 AÑOS — Tarifa Actual con escalón 2032 · ahorros persisten · PPA se transfiere al cliente al término
A76: Bases año-0 (motor): | B76: PV con AA | C76: =F72 -> 2532058.3 | D76: PV CFE pleno | E76: =F72+SUMPRODUCT(E45:E56*(1/O45:O56-1)) -> 2532058.3 | F76: BESS | G76: =G72 -> 1985137 | H76: FP | I76: =H72 -> 0 | J76: Gen PV kWh | K76: =C72 -> 1393504.5
A77: Año | B77: Régimen | C77: Tarifa Actual $ | D77: Ah PV $ | E77: Ah BESS $ | F77: Ah FP $ | G77: Costo c/proy $ | H77: Flujo Compra $ | I77: Pago PPA $ | J77: Comisión $ | K77: Flujo Cliente PPA $ | L77: Flujo Financiador $
A78: 0 | B78: Inversión | H78: =-B26-B25-D25 -> -15864454 | K78: 0 | L78: =-B26-B25-D25 -> -15864454
A79: 1 | B79: =IF(A79<=(Supuestos!$B$22-Supuestos!$B$24),"Autoabasto","CFE pleno") -> Autoabasto | C79: =IF(A79<=(Supuestos!$B$22-Supuestos!$B$24),$B$12,$B$10)*(1+Supuestos!$B$8)^A79 -> 34109029 | D79: =IF(A79<=(Supuestos!$B$22-Supuestos!$B$24),$C$76,$E$76)*(1+Supuestos!$B$8)^A79*(1-Supuestos!$B$11)^A79 -> 2670561.9 | E79: =$G$76*(1+Supuestos!$B$8)^A79*(1-Supuestos!$B$12)^A79*Supuestos!$B$10 -> 1558456.6 | F79: =$I$76*(1+Supuestos!$B$8)^A79 -> 0 | G79: =C79-D79-E79-F79 -> 29880010 | H79: =D79+E79+F79-(Supuestos!$B$19*$B$6+Supuestos!$B$20*$F$6)*(1+Supuestos!$B$8)^(A79-1) -> 3792401.4 | I79: =IF(A79<=Supuestos!$J$31,$K$76*(1-Supuestos!$B$11)^A79*Supuestos!$I$31*(1+Supuestos!$B$9)^(A79-1),0) -> 2203346 | J79: =E79*Supuestos!$K$31 -> 779228.3 | K79: =D79-I79+E79-J79+F79-IF(A79<=Supuestos!$J$31,0,Supuestos!$B$19*$B$6*(1+Supuestos!$B$8)^(A79-1)) -> 1246444.2 | L79: =I79+J79-IF(A79<=Supuestos!$J$31,(Supuestos!$B$19*$B$6+Supuestos!$B$20*$F$6),Supuestos!$B$20*$F$6)*(1+Supuestos!$B$8)^(A79-1) -> 2545957.2
A80: 2 | B80: =IF(A80<=(Supuestos!$B$22-Supuestos!$B$24),"Autoabasto","CFE pleno") -> Autoabasto | C80: =IF(A80<=(Supuestos!$B$22-Supuestos!$B$24),$B$12,$B$10)*(1+Supuestos!$B$8)^A80 -> 36155571 | D80: =IF(A80<=(Supuestos!$B$22-Supuestos!$B$24),$C$76,$E$76)*(1+Supuestos!$B$8)^A80*(1-Supuestos!$B$11)^A80 -> 2816641.6 | E80: =$G$76*(1+Supuestos!$B$8)^A80*(1-Supuestos!$B$12)^A80*Supuestos!$B$10 -> 1631314.4 | F80: =$I$76*(1+Supuestos!$B$8)^A80 -> 0 | G80: =C80-D80-E80-F80 -> 31707615 | H80: =D80+E80+F80-(Supuestos!$B$19*$B$6+Supuestos!$B$20*$F$6)*(1+Supuestos!$B$8)^(A80-1) -> 3985141.9 | I80: =IF(A80<=Supuestos!$J$31,$K$76*(1-Supuestos!$B$11)^A80*Supuestos!$I$31*(1+Supuestos!$B$9)^(A80-1),0) -> 2301945.7 | J80: =E80*Supuestos!$K$31 -> 815657.22 | K80: =D80-I80+E80-J80+F80-IF(A80<=Supuestos!$J$31,0,Supuestos!$B$19*$B$6*(1+Supuestos!$B$8)^(A80-1)) -> 1330353.1 | L80: =I80+J80-IF(A80<=Supuestos!$J$31,(Supuestos!$B$19*$B$6+Supuestos!$B$20*$F$6),Supuestos!$B$20*$F$6)*(1+Supuestos!$B$8)^(A80-1) -> 2654788.8
A81: 3 | B81: =IF(A81<=(Supuestos!$B$22-Supuestos!$B$24),"Autoabasto","CFE pleno") -> Autoabasto | C81: =IF(A81<=(Supuestos!$B$22-Supuestos!$B$24),$B$12,$B$10)*(1+Supuestos!$B$8)^A81 -> 38324905 | D81: =IF(A81<=(Supuestos!$B$22-Supuestos!$B$24),$C$76,$E$76)*(1+Supuestos!$B$8)^A81*(1-Supuestos!$B$11)^A81 -> 2970711.9 | E81: =$G$76*(1+Supuestos!$B$8)^A81*(1-Supuestos!$B$12)^A81*Supuestos!$B$10 -> 1707578.4 | F81: =$I$76*(1+Supuestos!$B$8)^A81 -> 0 | G81: =C81-D81-E81-F81 -> 33646615 | H81: =D81+E81+F81-(Supuestos!$B$19*$B$6+Supuestos!$B$20*$F$6)*(1+Supuestos!$B$8)^(A81-1) -> 4187707.3 | I81: =IF(A81<=Supuestos!$J$31,$K$76*(1-Supuestos!$B$11)^A81*Supuestos!$I$31*(1+Supuestos!$B$9)^(A81-1),0) -> 2404957.8 | J81: =E81*Supuestos!$K$31 -> 853789.2 | K81: =D81-I81+E81-J81+F81-IF(A81<=Supuestos!$J$31,0,Supuestos!$B$19*$B$6*(1+Supuestos!$B$8)^(A81-1)) -> 1419543.3 | L81: =I81+J81-IF(A81<=Supuestos!$J$31,(Supuestos!$B$19*$B$6+Supuestos!$B$20*$F$6),Supuestos!$B$20*$F$6)*(1+Supuestos!$B$8)^(A81-1) -> 2768164
A82: 4 | B82: =IF(A82<=(Supuestos!$B$22-Supuestos!$B$24),"Autoabasto","CFE pleno") -> Autoabasto | C82: =IF(A82<=(Supuestos!$B$22-Supuestos!$B$24),$B$12,$B$10)*(1+Supuestos!$B$8)^A82 -> 40624399 | D82: =IF(A82<=(Supuestos!$B$22-Supuestos!$B$24),$C$76,$E$76)*(1+Supuestos!$B$8)^A82*(1-Supuestos!$B$11)^A82 -> 3133209.8 | E82: =$G$76*(1+Supuestos!$B$8)^A82*(1-Supuestos!$B$12)^A82*Supuestos!$B$10 -> 1787407.7 | F82: =$I$76*(1+Supuestos!$B$8)^A82 -> 0 | G82: =C82-D82-E82-F82 -> 35703782 | H82: =D82+E82+F82-(Supuestos!$B$19*$B$6+Supuestos!$B$20*$F$6)*(1+Supuestos!$B$8)^(A82-1) -> 4400599.6 | I82: =IF(A82<=Supuestos!$J$31,$K$76*(1-Supuestos!$B$11)^A82*Supuestos!$I$31*(1+Supuestos!$B$9)^(A82-1),0) -> 2512579.6 | J82: =E82*Supuestos!$K$31 -> 893703.85 | K82: =D82-I82+E82-J82+F82-IF(A82<=Supuestos!$J$31,0,Supuestos!$B$19*$B$6*(1+Supuestos!$B$8)^(A82-1)) -> 1514334.1 | L82: =I82+J82-IF(A82<=Supuestos!$J$31,(Supuestos!$B$19*$B$6+Supuestos!$B$20*$F$6),Supuestos!$B$20*$F$6)*(1+Supuestos!$B$8)^(A82-1) -> 2886265.5
A83: 5 | B83: =IF(A83<=(Supuestos!$B$22-Supuestos!$B$24),"Autoabasto","CFE pleno") -> Autoabasto | C83: =IF(A83<=(Supuestos!$B$22-Supuestos!$B$24),$B$12,$B$10)*(1+Supuestos!$B$8)^A83 -> 43061863 | D83: =IF(A83<=(Supuestos!$B$22-Supuestos!$B$24),$C$76,$E$76)*(1+Supuestos!$B$8)^A83*(1-Supuestos!$B$11)^A83 -> 3304596.4 | E83: =$G$76*(1+Supuestos!$B$8)^A83*(1-Supuestos!$B$12)^A83*Supuestos!$B$10 -> 1870969 | F83: =$I$76*(1+Supuestos!$B$8)^A83 -> 0 | G83: =C83-D83-E83-F83 -> 37886298 | H83: =D83+E83+F83-(Supuestos!$B$19*$B$6+Supuestos!$B$20*$F$6)*(1+Supuestos!$B$8)^(A83-1) -> 4624346.4 | I83: =IF(A83<=Supuestos!$J$31,$K$76*(1-Supuestos!$B$11)^A83*Supuestos!$I$31*(1+Supuestos!$B$9)^(A83-1),0) -> 2625017.6 | J83: =E83*Supuestos!$K$31 -> 935484.5 | K83: =D83-I83+E83-J83+F83-IF(A83<=Supuestos!$J$31,0,Supuestos!$B$19*$B$6*(1+Supuestos!$B$8)^(A83-1)) -> 1615063.3 | L83: =I83+J83-IF(A83<=Supuestos!$J$31,(Supuestos!$B$19*$B$6+Supuestos!$B$20*$F$6),Supuestos!$B$20*$F$6)*(1+Supuestos!$B$8)^(A83-1) -> 3009283
A84: 6 | B84: =IF(A84<=(Supuestos!$B$22-Supuestos!$B$24),"Autoabasto","CFE pleno") -> Autoabasto | C84: =IF(A84<=(Supuestos!$B$22-Supuestos!$B$24),$B$12,$B$10)*(1+Supuestos!$B$8)^A84 -> 45645575 | D84: =IF(A84<=(Supuestos!$B$22-Supuestos!$B$24),$C$76,$E$76)*(1+Supuestos!$B$8)^A84*(1-Supuestos!$B$11)^A84 -> 3485357.8 | E84: =$G$76*(1+Supuestos!$B$8)^A84*(1-Supuestos!$B$12)^A84*Supuestos!$B$10 -> 1958436.8 | F84: =$I$76*(1+Supuestos!$B$8)^A84 -> 0 | G84: =C84-D84-E84-F84 -> 40201780 | H84: =D84+E84+F84-(Supuestos!$B$19*$B$6+Supuestos!$B$20*$F$6)*(1+Supuestos!$B$8)^(A84-1) -> 4859502.5 | I84: =IF(A84<=Supuestos!$J$31,$K$76*(1-Supuestos!$B$11)^A84*Supuestos!$I$31*(1+Supuestos!$B$9)^(A84-1),0) -> 2742487.1 | J84: =E84*Supuestos!$K$31 -> 979218.4 | K84: =D84-I84+E84-J84+F84-IF(A84<=Supuestos!$J$31,0,Supuestos!$B$19*$B$6*(1+Supuestos!$B$8)^(A84-1)) -> 1722089.1 | L84: =I84+J84-IF(A84<=Supuestos!$J$31,(Supuestos!$B$19*$B$6+Supuestos!$B$20*$F$6),Supuestos!$B$20*$F$6)*(1+Supuestos!$B$8)^(A84-1) -> 3137413.3
A85: 7 | B85: =IF(A85<=(Supuestos!$B$22-Supuestos!$B$24),"Autoabasto","CFE pleno") -> CFE pleno | C85: =IF(A85<=(Supuestos!$B$22-Supuestos!$B$24),$B$12,$B$10)*(1+Supuestos!$B$8)^A85 -> 55011228 | D85: =IF(A85<=(Supuestos!$B$22-Supuestos!$B$24),$C$76,$E$76)*(1+Supuestos!$B$8)^A85*(1-Supuestos!$B$11)^A85 -> 3676006.9 | E85: =$G$76*(1+Supuestos!$B$8)^A85*(1-Supuestos!$B$12)^A85*Supuestos!$B$10 -> 2049993.7 | F85: =$I$76*(1+Supuestos!$B$8)^A85 -> 0 | G85: =C85-D85-E85-F85 -> 49285228 | H85: =D85+E85+F85-(Supuestos!$B$19*$B$6+Supuestos!$B$20*$F$6)*(1+Supuestos!$B$8)^(A85-1) -> 5106650.9 | I85: =IF(A85<=Supuestos!$J$31,$K$76*(1-Supuestos!$B$11)^A85*Supuestos!$I$31*(1+Supuestos!$B$9)^(A85-1),0) -> 2865213.4 | J85: =E85*Supuestos!$K$31 -> 1024996.9 | K85: =D85-I85+E85-J85+F85-IF(A85<=Supuestos!$J$31,0,Supuestos!$B$19*$B$6*(1+Supuestos!$B$8)^(A85-1)) -> 1835790.4 | L85: =I85+J85-IF(A85<=Supuestos!$J$31,(Supuestos!$B$19*$B$6+Supuestos!$B$20*$F$6),Supuestos!$B$20*$F$6)*(1+Supuestos!$B$8)^(A85-1) -> 3270860.6
A86: 8 | B86: =IF(A86<=(Supuestos!$B$22-Supuestos!$B$24),"Autoabasto","CFE pleno") -> CFE pleno | C86: =IF(A86<=(Supuestos!$B$22-Supuestos!$B$24),$B$12,$B$10)*(1+Supuestos!$B$8)^A86 -> 58311902 | D86: =IF(A86<=(Supuestos!$B$22-Supuestos!$B$24),$C$76,$E$76)*(1+Supuestos!$B$8)^A86*(1-Supuestos!$B$11)^A86 -> 3877084.5 | E86: =$G$76*(1+Supuestos!$B$8)^A86*(1-Supuestos!$B$12)^A86*Supuestos!$B$10 -> 2145830.9 | F86: =$I$76*(1+Supuestos!$B$8)^A86 -> 0 | G86: =C86-D86-E86-F86 -> 52288987 | H86: =D86+E86+F86-(Supuestos!$B$19*$B$6+Supuestos!$B$20*$F$6)*(1+Supuestos!$B$8)^(A86-1) -> 5366404.7 | I86: =IF(A86<=Supuestos!$J$31,$K$76*(1-Supuestos!$B$11)^A86*Supuestos!$I$31*(1+Supuestos!$B$9)^(A86-1),0) -> 2993431.7 | J86: =E86*Supuestos!$K$31 -> 1072915.5 | K86: =D86-I86+E86-J86+F86-IF(A86<=Supuestos!$J$31,0,Supuestos!$B$19*$B$6*(1+Supuestos!$B$8)^(A86-1)) -> 1956568.3 | L86: =I86+J86-IF(A86<=Supuestos!$J$31,(Supuestos!$B$19*$B$6+Supuestos!$B$20*$F$6),Supuestos!$B$20*$F$6)*(1+Supuestos!$B$8)^(A86-1) -> 3409836.5
A87: 9 | B87: =IF(A87<=(Supuestos!$B$22-Supuestos!$B$24),"Autoabasto","CFE pleno") -> CFE pleno | C87: =IF(A87<=(Supuestos!$B$22-Supuestos!$B$24),$B$12,$B$10)*(1+Supuestos!$B$8)^A87 -> 61810616 | D87: =IF(A87<=(Supuestos!$B$22-Supuestos!$B$24),$C$76,$E$76)*(1+Supuestos!$B$8)^A87*(1-Supuestos!$B$11)^A87 -> 4089161 | E87: =$G$76*(1+Supuestos!$B$8)^A87*(1-Supuestos!$B$12)^A87*Supuestos!$B$10 -> 2246148.5 | F87: =$I$76*(1+Supuestos!$B$8)^A87 -> 0 | G87: =C87-D87-E87-F87 -> 55475307 | H87: =D87+E87+F87-(Supuestos!$B$19*$B$6+Supuestos!$B$20*$F$6)*(1+Supuestos!$B$8)^(A87-1) -> 5639408.2 | I87: =IF(A87<=Supuestos!$J$31,$K$76*(1-Supuestos!$B$11)^A87*Supuestos!$I$31*(1+Supuestos!$B$9)^(A87-1),0) -> 3127387.8 | J87: =E87*Supuestos!$K$31 -> 1123074.3 | K87: =D87-I87+E87-J87+F87-IF(A87<=Supuestos!$J$31,0,Supuestos!$B$19*$B$6*(1+Supuestos!$B$8)^(A87-1)) -> 2084847.5 | L87: =I87+J87-IF(A87<=Supuestos!$J$31,(Supuestos!$B$19*$B$6+Supuestos!$B$20*$F$6),Supuestos!$B$20*$F$6)*(1+Supuestos!$B$8)^(A87-1) -> 3554560.7
A88: 10 | B88: =IF(A88<=(Supuestos!$B$22-Supuestos!$B$24),"Autoabasto","CFE pleno") -> CFE pleno | C88: =IF(A88<=(Supuestos!$B$22-Supuestos!$B$24),$B$12,$B$10)*(1+Supuestos!$B$8)^A88 -> 65519253 | D88: =IF(A88<=(Supuestos!$B$22-Supuestos!$B$24),$C$76,$E$76)*(1+Supuestos!$B$8)^A88*(1-Supuestos!$B$11)^A88 -> 4312838.1 | E88: =$G$76*(1+Supuestos!$B$8)^A88*(1-Supuestos!$B$12)^A88*Supuestos!$B$10 -> 2351156 | F88: =$I$76*(1+Supuestos!$B$8)^A88 -> 0 | G88: =C88-D88-E88-F88 -> 58855259 | H88: =D88+E88+F88-(Supuestos!$B$19*$B$6+Supuestos!$B$20*$F$6)*(1+Supuestos!$B$8)^(A88-1) -> 5926338.7 | I88: =IF(A88<=Supuestos!$J$31,$K$76*(1-Supuestos!$B$11)^A88*Supuestos!$I$31*(1+Supuestos!$B$9)^(A88-1),0) -> 3267338.4 | J88: =E88*Supuestos!$K$31 -> 1175578 | K88: =D88-I88+E88-J88+F88-IF(A88<=Supuestos!$J$31,0,Supuestos!$B$19*$B$6*(1+Supuestos!$B$8)^(A88-1)) -> 2221077.7 | L88: =I88+J88-IF(A88<=Supuestos!$J$31,(Supuestos!$B$19*$B$6+Supuestos!$B$20*$F$6),Supuestos!$B$20*$F$6)*(1+Supuestos!$B$8)^(A88-1) -> 3705261
A89: 11 | B89: =IF(A89<=(Supuestos!$B$22-Supuestos!$B$24),"Autoabasto","CFE pleno") -> CFE pleno | C89: =IF(A89<=(Supuestos!$B$22-Supuestos!$B$24),$B$12,$B$10)*(1+Supuestos!$B$8)^A89 -> 69450408 | D89: =IF(A89<=(Supuestos!$B$22-Supuestos!$B$24),$C$76,$E$76)*(1+Supuestos!$B$8)^A89*(1-Supuestos!$B$11)^A89 -> 4548750.4 | E89: =$G$76*(1+Supuestos!$B$8)^A89*(1-Supuestos!$B$12)^A89*Supuestos!$B$10 -> 2461072.5 | F89: =$I$76*(1+Supuestos!$B$8)^A89 -> 0 | G89: =C89-D89-E89-F89 -> 62440585 | H89: =D89+E89+F89-(Supuestos!$B$19*$B$6+Supuestos!$B$20*$F$6)*(1+Supuestos!$B$8)^(A89-1) -> 6227908.2 | I89: =IF(A89<=Supuestos!$J$31,$K$76*(1-Supuestos!$B$11)^A89*Supuestos!$I$31*(1+Supuestos!$B$9)^(A89-1),0) -> 3413551.8 | J89: =E89*Supuestos!$K$31 -> 1230536.3 | K89: =D89-I89+E89-J89+F89-IF(A89<=Supuestos!$J$31,0,Supuestos!$B$19*$B$6*(1+Supuestos!$B$8)^(A89-1)) -> 2365734.9 | L89: =I89+J89-IF(A89<=Supuestos!$J$31,(Supuestos!$B$19*$B$6+Supuestos!$B$20*$F$6),Supuestos!$B$20*$F$6)*(1+Supuestos!$B$8)^(A89-1) -> 3862173.3
A90: 12 | B90: =IF(A90<=(Supuestos!$B$22-Supuestos!$B$24),"Autoabasto","CFE pleno") -> CFE pleno | C90: =IF(A90<=(Supuestos!$B$22-Supuestos!$B$24),$B$12,$B$10)*(1+Supuestos!$B$8)^A90 -> 73617433 | D90: =IF(A90<=(Supuestos!$B$22-Supuestos!$B$24),$C$76,$E$76)*(1+Supuestos!$B$8)^A90*(1-Supuestos!$B$11)^A90 -> 4797567 | E90: =$G$76*(1+Supuestos!$B$8)^A90*(1-Supuestos!$B$12)^A90*Supuestos!$B$10 -> 2576127.6 | F90: =$I$76*(1+Supuestos!$B$8)^A90 -> 0 | G90: =C90-D90-E90-F90 -> 66243738 | H90: =D90+E90+F90-(Supuestos!$B$19*$B$6+Supuestos!$B$20*$F$6)*(1+Supuestos!$B$8)^(A90-1) -> 6544865.1 | I90: =IF(A90<=Supuestos!$J$31,$K$76*(1-Supuestos!$B$11)^A90*Supuestos!$I$31*(1+Supuestos!$B$9)^(A90-1),0) -> 3566308.2 | J90: =E90*Supuestos!$K$31 -> 1288063.8 | K90: =D90-I90+E90-J90+F90-IF(A90<=Supuestos!$J$31,0,Supuestos!$B$19*$B$6*(1+Supuestos!$B$8)^(A90-1)) -> 2519322.6 | L90: =I90+J90-IF(A90<=Supuestos!$J$31,(Supuestos!$B$19*$B$6+Supuestos!$B$20*$F$6),Supuestos!$B$20*$F$6)*(1+Supuestos!$B$8)^(A90-1) -> 4025542.4
... A98: 20 | B98: =IF(A98<=(Supuestos!$B$22-Supuestos!$B$24),"Autoabasto","CFE pleno") -> CFE pleno | C98: =IF(A98<=(Supuestos!$B$22-Supuestos!$B$24),$B$12,$B$10)*(1+Supuestos!$B$8)^A98 -> 1.17335e+08 | D98: =IF(A98<=(Supuestos!$B$22-Supuestos!$B$24),$C$76,$E$76)*(1+Supuestos!$B$8)^A98*(1-Supuestos!$B$11)^A98 -> 7346028.7 | E98: =$G$76*(1+Supuestos!$B$8)^A98*(1-Supuestos!$B$12)^A98*Supuestos!$B$10 -> 3712881.9 | F98: =$I$76*(1+Supuestos!$B$8)^A98 -> 0 | G98: =C98-D98-E98-F98 -> 1.0627609e+08 | H98: =D98+E98+F98-(Supuestos!$B$19*$B$6+Supuestos!$B$20*$F$6)*(1+Supuestos!$B$8)^(A98-1) -> 9737882.1 | I98: =IF(A98<=Supuestos!$J$31,$K$76*(1-Supuestos!$B$11)^A98*Supuestos!$I$31*(1+Supuestos!$B$9)^(A98-1),0) -> 0 | J98: =E98*Supuestos!$K$31 -> 1856440.9 | K98: =D98-I98+E98-J98+F98-IF(A98<=Supuestos!$J$31,0,Supuestos!$B$19*$B$6*(1+Supuestos!$B$8)^(A98-1)) -> 8415156.9 | L98: =I98+J98-IF(A98<=Supuestos!$J$31,(Supuestos!$B$19*$B$6+Supuestos!$B$20*$F$6),Supuestos!$B$20*$F$6)*(1+Supuestos!$B$8)^(A98-1) -> 1322725.2
A99: Σ | H99: =SUM(H79:H98) -> 1.2655637e+08 | K99: =SUM(K79:K98) -> 68494800 | L99: =SUM(L79:L98) -> 58061569
F100: TIR compra: | G100: =IRR(H78:H98) -> 0.28566512 | I100: VPN compra @WACC: | K100: =NPV(Supuestos!$B$7,H79:H98)+H78 -> 23650282
F101: TIR financiador: | G101: =IRR(L78:L98) -> 0.18105675 | I101: VPN cliente PPA @WACC: | K101: =NPV(Supuestos!$B$7,K79:K98)+K78 -> 17062719
A102: Régimen: Autoabasto años 1-6 (2026-2031); CFE pleno desde 2032 (escalón en Tarifa Actual). El ahorro PV/BESS/FP persiste los 20 años; tras el plazo PPA el PV se transfiere a GEPP y conserva el 100% del ahorro.
A104: 7. COMPRAR vs PPA / AHORRO COMPARTIDO
A105: Métrica | B105: GEPP COMPRA | C105: PPA / Ahorro compartido
A106: Inversión GEPP $ | B106: =B26+B25+D25 -> 15864454 | C106: 0 | D106: Financiador funda todo (incl. capacitor)
A107: Beneficio GEPP año 1 $ | B107: =H79 -> 3792401.4 | C107: =K79 -> 1246444.2
A108: Beneficio 20 años acum. $ | B108: =H99 -> 1.2655637e+08 | C108: =SUM(K79:K98) -> 68494800
A109: TIR (proyecto / financiador) | B109: =G100 -> 0.28566512 | C109: =G101 -> 0.18105675
A110: Tarifa PPA $/kWh (editable en Supuestos) | B110: — | C110: =Supuestos!$I$31 -> 1.5891
A111: Plazo PPA años / PV se transfiere al cliente al término | C111: =Supuestos!$J$31 -> 15
A113: 8. POR QUÉ ESTE DIMENSIONAMIENTO ES EL ÓPTIMO PARA ESTE SITIO
A114: RESTRICCIÓN: el techo TOTAL de Proplasa se limita a 3.15 MW (sin espacio). Se reparte proporcional al consumo de cada medidor para autoconsumir el 100% (sin exportar): PR1 = 557 kWp (~18% del consumo Proplasa). El PV/kWp ahorra casi igual en los 3 medidores (misma división), así que el reparto proporcional es ~óptimo en ahorro. Desplaza la energía CFE cara; BESS 360 kW recorta punta. COMPRAR conserva el 100% del ahorro para GEPP.

Sheet Proplasa PR2
A1: PROPLASA PR2 — Memoria de cálculo trazable y propuesta
A2: Medidor 805DYN · GDMTH SIN · Demanda contratada 5,625 kW · AUTOCONSUMO interconectado (>0.7 MW) — permiso SIMPLIFICADO CNE
A3: GEPP pide: Combinar autoabasto (ENEL) con generación solar en sitio
A5: PARÁMETROS DEL SISTEMA (desde Supuestos — edítalos allí)
A6: PV kWp | B6: =Supuestos!$B$32 -> 1565.135 | C6: BESS kW | D6: =Supuestos!$C$32 -> 1252.5 | E6: BESS kWh | F6: =Supuestos!$D$32 -> 2450 | G6: Entrega útil kWh | H6: =Supuestos!$D$32*Supuestos!$B$17*SQRT(Supuestos!$B$18) -> 2304.48 | I6: FP corr. | J6: =Supuestos!$E$32 -> No | K6: Calib→recibo | L6: =$B$10/(SUM(P45:P56)+SUM(R30:R41)) -> 1
A8: 1. ESTRUCTURA DE COSTO Y AHORRO (2025, pre-IVA · datos del workbook GEPP + motor)
A9: Concepto | B9: $ / año | C9: $ / kWh | D9: kWh | E9: Nota
A10: CFE BRUTO = Tarifa Actual (todo a CFE pleno, sin autoabasto) | B10: 1.088104e+08 | C10: =B10/D10 -> 2.3799542 | D10: 45719537 | E10: Lo que pagarían 100% en CFE sin ENEL/Tala ni PV/BESS
A11: (−) Ahorro autoabasto (ENEL) | B11: 6673632.8 | E11: Beneficio ENEL ($1.78/kWh vs CFE; validado por colapso 2026)
A12: (=) Costo actual que paga GEPP hoy | B12: =B10-B11 -> 1.0213677e+08 | C12: =B12/D12 -> 2.2339852 | D12: =D10 -> 45719537
A13: › CFE (tarifa CFE plena) | B13: 55799375 | C13: =B13/D13 -> 2.8304056 | D13: 19714268
A14: › ENEL | B14: 46337395 | C14: =B14/D14 -> 1.7818464 | D14: 26005269
A15: › Mezcla de suministro 2025 | B15: =D13/D12 -> 0.43120008 | C15: CFE | D15: =D14/D12 -> 0.56879992 | E15: ENEL (en 2026 ENEL ya colapsó → CFE ~85%)
A16: Ahorros del proyecto (motor 2025, sobre la carga física):
A17: (−) Ahorro PV (energía intermedia + demanda vía umbral) | B17: =F72 -> 4713237.5 | D17: =C72 -> 2598280.6 | E17: Gen solar kWh/año →
A18: (−) Ahorro BESS (recorte de punta + arbitraje) | B18: =G72 -> 4954128.6
A19: (−) Ahorro FP (corrección factor de potencia) | B19: =H72 -> 0 | E19: FP sano — sin multa
A20: (=) Costo neto con proyecto (hoy) | B20: =B12-B17-B18-B19 -> 92469404
A21: Ahorro proyecto PV+BESS+FP (vs costo hoy) | B21: =B17+B18+B19 -> 9667366.1 | C21: =B21/B12 -> 0.094651183
A22: Ahorro TOTAL vs CFE bruto (incl. autoabasto+proyecto) | B22: =B10-B20 -> 16340999 | C22: =B22/B10 -> 0.15017865
A24: 2. CAPEX (fórmulas vivas desde Supuestos)
A25: CAPEX PV = kWp×1000×USD/Wp×FX | B25: =$B$6*1000*Supuestos!$F$32*Supuestos!$B$5 -> 20601089 | C25: CAPEX BESS = kWh×USD/kWh×FX | D25: =$F$6*Supuestos!$G$32*Supuestos!$B$5 -> 12039300
A26: CAPEX Capacitor FP (financiador en PPA) | B26: =Supuestos!$H$32 -> 0 | C26: CAPEX TOTAL (compra) | D26: =B25+D25+B26 -> 32640389 | E26: Bajo PPA, el capacitor lo paga el financiador → el cliente no desembolsa
A28: 3. ENTRADAS MENSUALES (AZUL = datos del recibo / recurso 2025)
A29: Mes | B29: kWh Base | C29: kWh Int | D29: kWh Punta | E29: Días | F29: Dem Pta kW | G29: Dem Máx kW | H29: T.Int $ | I29: T.Base $ | J29: T.Pta $ | K29: T.Cap $ | L29: T.Dist $ | M29: T.Fijo $ | N29: Rend | O29: %AC | P29: HrsP | Q29: DíasP | R29: Bonif FP
A30: Ene | B30: 1127389 | C30: 1795542 | D30: 466031 | E30: 31 | F30: 6670 | G30: 6718 | H30: 1.819675 | I30: 1.10665 | J30: 2.1272 | K30: 402.0725 | L30: 86.15 | M30: 703.36 | N30: 142.8 | O30: 1 | P30: 4 | Q30: 22 | R30: -3068.41
A31: Feb | B31: 1258745 | C31: 1870728 | D31: 471567 | E31: 28 | F31: 6525 | G31: 6557 | H31: 1.819675 | I31: 1.10665 | J31: 2.1272 | K31: 402.0725 | L31: 86.15 | M31: 703.36 | N31: 139.1 | O31: 1 | P31: 4 | Q31: 19 | R31: -1746.75
A32: Mar | B32: 1582579 | C32: 2238743 | D32: 538917 | E32: 31 | F32: 6470 | G32: 6470 | H32: 1.819675 | I32: 1.10665 | J32: 2.1272 | K32: 402.0725 | L32: 86.15 | M32: 703.36 | N32: 170.1 | O32: 1 | P32: 4 | Q32: 20 | R32: -2882.66
A33: Abr | B33: 1391931 | C33: 2472488 | D33: 308716 | E33: 30 | F33: 6489 | G33: 6597 | H33: 1.819675 | I33: 1.10665 | J33: 2.1272 | K33: 402.0725 | L33: 86.15 | M33: 703.36 | N33: 150.7 | O33: 1 | P33: 2 | Q33: 22 | R33: -5739.34
A34: May | B34: 1554976 | C34: 2674916 | D34: 252409 | E34: 31 | F34: 6509 | G34: 6565 | H34: 1.819675 | I34: 1.10665 | J34: 2.1272 | K34: 402.0725 | L34: 86.15 | M34: 703.36 | N34: 143.1 | O34: 1 | P34: 2 | Q34: 21 | R34: -9014.39
A35: Jun | B35: 1461034 | C35: 2511016 | D35: 251483 | E35: 30 | F35: 6634 | G35: 6744 | H35: 1.819675 | I35: 1.10665 | J35: 2.1272 | K35: 402.0725 | L35: 86.15 | M35: 703.36 | N35: 133.9 | O35: 1 | P35: 2 | Q35: 21 | R35: -31375.9
A36: Jul | B36: 1213977 | C36: 2229430 | D36: 229493 | E36: 31 | F36: 5851 | G36: 5873 | H36: 1.819675 | I36: 1.10665 | J36: 2.1272 | K36: 402.0725 | L36: 86.15 | M36: 703.36 | N36: 135.2 | O36: 1 | P36: 2 | Q36: 23 | R36: -47885.63
A37: Ago | B37: 1460355 | C37: 2480903 | D37: 235656 | E37: 31 | F37: 6354 | G37: 6492 | H37: 1.819675 | I37: 1.10665 | J37: 2.1272 | K37: 402.0725 | L37: 86.15 | M37: 703.36 | N37: 126.5 | O37: 1 | P37: 2 | Q37: 21 | R37: -45455.49
A38: Sep | B38: 1257774 | C38: 2130853 | D38: 208228 | E38: 30 | F38: 5562 | G38: 6311 | H38: 1.819675 | I38: 1.10665 | J38: 2.1272 | K38: 402.0725 | L38: 86.15 | M38: 703.36 | N38: 119.5 | O38: 1 | P38: 2 | Q38: 21 | R38: -48968.46
A39: Oct | B39: 1080780 | C39: 2010757 | D39: 247787 | E39: 31 | F39: 4470 | G39: 4522 | H39: 1.819675 | I39: 1.10665 | J39: 2.1272 | K39: 402.0725 | L39: 86.15 | M39: 703.36 | N39: 131.7 | O39: 1 | P39: 2 | Q39: 23 | R39: -53687.85
A40: Nov | B40: 1215444 | C40: 1781412 | D40: 435452 | E40: 30 | F40: 6123 | G40: 6215 | H40: 1.819675 | I40: 1.10665 | J40: 2.1272 | K40: 402.0725 | L40: 86.15 | M40: 703.36 | N40: 136.6 | O40: 1 | P40: 4 | Q40: 19 | R40: -48131.55
A41: Dic | B41: 1136000 | C41: 1717671 | D41: 418355 | E41: 31 | F41: 5588 | G41: 6070 | H41: 1.819675 | I41: 1.10665 | J41: 2.1272 | K41: 402.0725 | L41: 86.15 | M41: 703.36 | N41: 130.9 | O41: 1 | P41: 4 | Q41: 22 | R41: -43469.54
A42: 4. CÁLCULO DE AHORRO MENSUAL (motor — fórmulas que referencian las ENTRADAS)
A43: Mes | B43: Gen kWh | C43: Umbral kW | D43: Autocons | E43: Ah PV ener | F43: Umbral post | G43: Cap base | H43: Cap pre-B | I43: Ah PV dem | J43: Recorte BESS | K43: Cap post | L43: Ah BESS dem | M43: Desc kWh | N43: Arbitraje $ | O43: Fac.AA | P43: mem $ | Q43: Ah PV+BESS
A45: =A30 -> Ene | B45: =$B$6*N30 -> 223501.28 | C45: =(B30+C30+D30)/(E30*24*Supuestos!$B$16) -> 7991.3271 | D45: =MIN(B45*O30,C30) -> 223501.28 | E45: =D45*H30*O45 -> 406699.69 | F45: =((B30+C30+D30)-D45)/(E30*24*Supuestos!$B$16) -> 7464.3009 | G45: =MIN(F30,C45) -> 6670 | H45: =MIN(F30,F45) -> 6670 | I45: =(G45-H45)*K30 -> 0 | J45: =IF(P30=0,0,MIN($D$6,$H$6/P30)) -> 576.11999 | K45: =MIN(MAX(F30-J45,0),F45) -> 6093.88 | L45: =(H45-K45)*K30 -> 231642 | M45: =IF(P30=0,0,MIN($H$6*Q30,D30)) -> 50698.559 | N45: =M45*J30-(M45/Supuestos!$B$18)*I30 -> 49402.683 | O45: 1 | P45: =M30+B30*I30+C30*H30+D30*J30+G45*K30+MIN(G30,C45)*L30 -> 8767551.7 | Q45: =(E45+I45)+(L45+N45) -> 687744.37
A46: =A31 -> Feb | B46: =$B$6*N31 -> 217710.28 | C46: =(B31+C31+D31)/(E31*24*Supuestos!$B$16) -> 9401.2114 | D46: =MIN(B46*O31,C31) -> 217710.28 | E46: =D46*H31*O46 -> 396161.95 | F46: =((B31+C31+D31)-D46)/(E31*24*Supuestos!$B$16) -> 8832.8366 | G46: =MIN(F31,C46) -> 6525 | H46: =MIN(F31,F46) -> 6525 | I46: =(G46-H46)*K31 -> 0 | J46: =IF(P31=0,0,MIN($D$6,$H$6/P31)) -> 576.11999 | K46: =MIN(MAX(F31-J46,0),F46) -> 5948.88 | L46: =(H46-K46)*K31 -> 231642 | M46: =IF(P31=0,0,MIN($H$6*Q31,D31)) -> 43785.119 | N46: =M46*J31-(M46/Supuestos!$B$18)*I31 -> 42665.953 | O46: 1 | P46: =M31+B31*I31+C31*H31+D31*J31+G46*K31+MIN(G31,C46)*L31 -> 8989336.4 | Q46: =(E46+I46)+(L46+N46) -> 670469.91
A47: =A32 -> Mar | B47: =$B$6*N32 -> 266229.46 | C47: =(B32+C32+D32)/(E32*24*Supuestos!$B$16) -> 10281.643 | D47: =MIN(B47*O32,C32) -> 266229.46 | E47: =D47*H32*O47 -> 484451.1 | F47: =((B32+C32+D32)-D47)/(E32*24*Supuestos!$B$16) -> 9653.8614 | G47: =MIN(F32,C47) -> 6470 | H47: =MIN(F32,F47) -> 6470 | I47: =(G47-H47)*K32 -> 0 | J47: =IF(P32=0,0,MIN($D$6,$H$6/P32)) -> 576.11999 | K47: =MIN(MAX(F32-J47,0),F47) -> 5893.88 | L47: =(H47-K47)*K32 -> 231642 | M47: =IF(P32=0,0,MIN($H$6*Q32,D32)) -> 46089.599 | N47: =M47*J32-(M47/Supuestos!$B$18)*I32 -> 44911.53 | O47: 1 | P47: =M32+B32*I32+C32*H32+D32*J32+G47*K32+MIN(G32,C47)*L32 -> 10131033 | Q47: =(E47+I47)+(L47+N47) -> 761004.63
A48: =A33 -> Abr | B48: =$B$6*N33 -> 235865.84 | C48: =(B33+C33+D33)/(E33*24*Supuestos!$B$16) -> 10168.458 | D48: =MIN(B48*O33,C33) -> 235865.84 | E48: =D48*H33*O48 -> 429199.18 | F48: =((B33+C33+D33)-D48)/(E33*24*Supuestos!$B$16) -> 9593.7358 | G48: =MIN(F33,C48) -> 6489 | H48: =MIN(F33,F48) -> 6489 | I48: =(G48-H48)*K33 -> 0 | J48: =IF(P33=0,0,MIN($D$6,$H$6/P33)) -> 1152.24 | K48: =MIN(MAX(F33-J48,0),F48) -> 5336.76 | L48: =(H48-K48)*K33 -> 463284.01 | M48: =IF(P33=0,0,MIN($H$6*Q33,D33)) -> 50698.559 | N48: =M48*J33-(M48/Supuestos!$B$18)*I33 -> 49402.683 | O48: 1 | P48: =M33+B33*I33+C33*H33+D33*J33+G48*K33+MIN(G33,C48)*L33 -> 9874289.1 | Q48: =(E48+I48)+(L48+N48) -> 941885.87
A49: =A34 -> May | B49: =$B$6*N34 -> 223970.82 | C49: =(B34+C34+D34)/(E34*24*Supuestos!$B$16) -> 10569.47 | D49: =MIN(B49*O34,C34) -> 223970.82 | E49: =D49*H34*O49 -> 407554.1 | F49: =((B34+C34+D34)-D49)/(E34*24*Supuestos!$B$16) -> 10041.337 | G49: =MIN(F34,C49) -> 6509 | H49: =MIN(F34,F49) -> 6509 | I49: =(G49-H49)*K34 -> 0 | J49: =IF(P34=0,0,MIN($D$6,$H$6/P34)) -> 1152.24 | K49: =MIN(MAX(F34-J49,0),F49) -> 5356.76 | L49: =(H49-K49)*K34 -> 463284.01 | M49: =IF(P34=0,0,MIN($H$6*Q34,D34)) -> 48394.079 | N49: =M49*J34-(M49/Supuestos!$B$18)*I34 -> 47157.106 | O49: 1 | P49: =M34+B34*I34+C34*H34+D34*J34+G49*K34+MIN(G34,C49)*L34 -> 10308584 | Q49: =(E49+I49)+(L49+N49) -> 917995.21
A50: =A35 -> Jun | B50: =$B$6*N35 -> 209571.58 | C50: =(B35+C35+D35)/(E35*24*Supuestos!$B$16) -> 10291.26 | D50: =MIN(B50*O35,C35) -> 209571.58 | E50: =D50*H35*O50 -> 381352.16 | F50: =((B35+C35+D35)-D50)/(E35*24*Supuestos!$B$16) -> 9780.6078 | G50: =MIN(F35,C50) -> 6634 | H50: =MIN(F35,F50) -> 6634 | I50: =(G50-H50)*K35 -> 0 | J50: =IF(P35=0,0,MIN($D$6,$H$6/P35)) -> 1152.24 | K50: =MIN(MAX(F35-J50,0),F50) -> 5481.76 | L50: =(H50-K50)*K35 -> 463284.01 | M50: =IF(P35=0,0,MIN($H$6*Q35,D35)) -> 48394.079 | N50: =M50*J35-(M50/Supuestos!$B$18)*I35 -> 47157.106 | O50: 1 | P50: =M35+B35*I35+C35*H35+D35*J35+G50*K35+MIN(G35,C50)*L35 -> 9970088.9 | Q50: =(E50+I50)+(L50+N50) -> 891793.27
A51: =A36 -> Jul | B51: =$B$6*N36 -> 211606.25 | C51: =(B36+C36+D36)/(E36*24*Supuestos!$B$16) -> 8660.8659 | D51: =MIN(B51*O36,C36) -> 211606.25 | E51: =D51*H36*O51 -> 385054.61 | F51: =((B36+C36+D36)-D51)/(E36*24*Supuestos!$B$16) -> 8161.8887 | G51: =MIN(F36,C51) -> 5851 | H51: =MIN(F36,F51) -> 5851 | I51: =(G51-H51)*K36 -> 0 | J51: =IF(P36=0,0,MIN($D$6,$H$6/P36)) -> 1152.24 | K51: =MIN(MAX(F36-J51,0),F51) -> 4698.76 | L51: =(H51-K51)*K36 -> 463284.01 | M51: =IF(P36=0,0,MIN($H$6*Q36,D36)) -> 53003.039 | N51: =M51*J36-(M51/Supuestos!$B$18)*I36 -> 51648.259 | O51: 1 | P51: =M36+B36*I36+C36*H36+D36*J36+G51*K36+MIN(G36,C51)*L36 -> 8747651.7 | Q51: =(E51+I51)+(L51+N51) -> 899986.87
A52: =A37 -> Ago | B52: =$B$6*N37 -> 197989.58 | C52: =(B37+C37+D37)/(E37*24*Supuestos!$B$16) -> 9849.3539 | D52: =MIN(B52*O37,C37) -> 197989.58 | E52: =D52*H37*O52 -> 360276.68 | F52: =((B37+C37+D37)-D52)/(E37*24*Supuestos!$B$16) -> 9382.4854 | G52: =MIN(F37,C52) -> 6354 | H52: =MIN(F37,F52) -> 6354 | I52: =(G52-H52)*K37 -> 0 | J52: =IF(P37=0,0,MIN($D$6,$H$6/P37)) -> 1152.24 | K52: =MIN(MAX(F37-J52,0),F52) -> 5201.76 | L52: =(H52-K52)*K37 -> 463284.01 | M52: =IF(P37=0,0,MIN($H$6*Q37,D37)) -> 48394.079 | N52: =M52*J37-(M52/Supuestos!$B$18)*I37 -> 47157.106 | O52: 1 | P52: =M37+B37*I37+C37*H37+D37*J37+G52*K37+MIN(G37,C52)*L37 -> 9746584.3 | Q52: =(E52+I52)+(L52+N52) -> 870717.8
A53: =A38 -> Sep | B53: =$B$6*N38 -> 187033.63 | C53: =(B38+C38+D38)/(E38*24*Supuestos!$B$16) -> 8764.2666 | D53: =MIN(B53*O38,C38) -> 187033.63 | E53: =D53*H38*O53 -> 340340.43 | F53: =((B38+C38+D38)-D53)/(E38*24*Supuestos!$B$16) -> 8308.5316 | G53: =MIN(F38,C53) -> 5562 | H53: =MIN(F38,F53) -> 5562 | I53: =(G53-H53)*K38 -> 0 | J53: =IF(P38=0,0,MIN($D$6,$H$6/P38)) -> 1152.24 | K53: =MIN(MAX(F38-J53,0),F53) -> 4409.76 | L53: =(H53-K53)*K38 -> 463284.01 | M53: =IF(P38=0,0,MIN($H$6*Q38,D38)) -> 48394.079 | N53: =M53*J38-(M53/Supuestos!$B$18)*I38 -> 47157.106 | O53: 1 | P53: =M38+B38*I38+C38*H38+D38*J38+G53*K38+MIN(G38,C53)*L38 -> 8493041.4 | Q53: =(E53+I53)+(L53+N53) -> 850781.54
A54: =A39 -> Oct | B54: =$B$6*N39 -> 206128.28 | C54: =(B39+C39+D39)/(E39*24*Supuestos!$B$16) -> 7874.2784 | D54: =MIN(B54*O39,C39) -> 206128.28 | E54: =D54*H39*O54 -> 375086.48 | F54: =((B39+C39+D39)-D54)/(E39*24*Supuestos!$B$16) -> 7388.2185 | G54: =MIN(F39,C54) -> 4470 | H54: =MIN(F39,F54) -> 4470 | I54: =(G54-H54)*K39 -> 0 | J54: =IF(P39=0,0,MIN($D$6,$H$6/P39)) -> 1152.24 | K54: =MIN(MAX(F39-J54,0),F54) -> 3317.76 | L54: =(H54-K54)*K39 -> 463284.01 | M54: =IF(P39=0,0,MIN($H$6*Q39,D39)) -> 53003.039 | N54: =M54*J39-(M54/Supuestos!$B$18)*I39 -> 51648.259 | O54: 1 | P54: =M39+B39*I39+C39*H39+D39*J39+G54*K39+MIN(G39,C54)*L39 -> 7569599.7 | Q54: =(E54+I54)+(L54+N54) -> 890018.74
A55: =A40 -> Nov | B55: =$B$6*N40 -> 213797.44 | C55: =(B40+C40+D40)/(E40*24*Supuestos!$B$16) -> 8363.3236 | D55: =MIN(B55*O40,C40) -> 213797.44 | E55: =D55*H40*O55 -> 389041.86 | F55: =((B40+C40+D40)-D55)/(E40*24*Supuestos!$B$16) -> 7842.3747 | G55: =MIN(F40,C55) -> 6123 | H55: =MIN(F40,F55) -> 6123 | I55: =(G55-H55)*K40 -> 0 | J55: =IF(P40=0,0,MIN($D$6,$H$6/P40)) -> 576.11999 | K55: =MIN(MAX(F40-J55,0),F55) -> 5546.88 | L55: =(H55-K55)*K40 -> 231642 | M55: =IF(P40=0,0,MIN($H$6*Q40,D40)) -> 43785.119 | N55: =M55*J40-(M55/Supuestos!$B$18)*I40 -> 42665.953 | O55: 1 | P55: =M40+B40*I40+C40*H40+D40*J40+G55*K40+MIN(G40,C55)*L40 -> 8510971 | Q55: =(E55+I55)+(L55+N55) -> 663349.82
A56: =A41 -> Dic | B56: =$B$6*N41 -> 204876.17 | C56: =(B41+C41+D41)/(E41*24*Supuestos!$B$16) -> 7715.5867 | D56: =MIN(B56*O41,C41) -> 204876.17 | E56: =D56*H41*O56 -> 372808.05 | F56: =((B41+C41+D41)-D56)/(E41*24*Supuestos!$B$16) -> 7232.4793 | G56: =MIN(F41,C56) -> 5588 | H56: =MIN(F41,F56) -> 5588 | I56: =(G56-H56)*K41 -> 0 | J56: =IF(P41=0,0,MIN($D$6,$H$6/P41)) -> 576.11999 | K56: =MIN(MAX(F41-J56,0),F56) -> 5011.88 | L56: =(H56-K56)*K41 -> 231642 | M56: =IF(P41=0,0,MIN($H$6*Q41,D41)) -> 50698.559 | N56: =M56*J41-(M56/Supuestos!$B$18)*I41 -> 49402.683 | O56: 1 | P56: =M41+B41*I41+C41*H41+D41*J41+G56*K41+MIN(G41,C56)*L41 -> 8043097.1 | Q56: =(E56+I56)+(L56+N56) -> 653852.73
A57: Recorte BESS = MIN(kW batería, entrega útil ÷ HrsP). Desc = MIN(entrega×DíasP, kWh punta). Arbitraje carga en base y descarga en punta. Fac.AA aplica el descuento de zafra (sólo Ixtlahuacán, pre-2032).
A58: 5. RESUMEN MENSUAL — Tarifa Actual (CFE pleno) / Ahorros / Costo con proyecto
A59: Mes | B59: kWh Consumo | C59: Gen PV kWh | D59: BESS desc kWh | E59: Tarifa Actual $ | F59: Ahorro PV $ | G59: Ahorro BESS $ | H59: Ahorro FP $ | I59: Costo c/proyecto $ | J59: Ahorro $ | K59: Ahorro %
A60: =A30 -> Ene | B60: =B30+C30+D30 -> 3388962 | C60: =B45 -> 223501.28 | D60: =M45 -> 50698.559 | E60: =(P45+R30)*$L$6 -> 8764483.3 | F60: =(E45+I45)*(1-IF(R30<0,-R30/P45,0)) -> 406557.35 | G60: =(L45+N45)*(1-IF(R30<0,-R30/P45,0)) -> 280946.33 | H60: =IF($J$6="Sí",MAX(0,R30),0) -> 0 | I60: =E60-F60-G60-H60 -> 8076979.6 | J60: =F60+G60+H60 -> 687503.68 | K60: =J60/E60 -> 0.07844201
A61: =A31 -> Feb | B61: =B31+C31+D31 -> 3601040 | C61: =B46 -> 217710.28 | D61: =M46 -> 43785.119 | E61: =(P46+R31)*$L$6 -> 8987589.7 | F61: =(E46+I46)*(1-IF(R31<0,-R31/P46,0)) -> 396084.97 | G61: =(L46+N46)*(1-IF(R31<0,-R31/P46,0)) -> 274254.66 | H61: =IF($J$6="Sí",MAX(0,R31),0) -> 0 | I61: =E61-F61-G61-H61 -> 8317250 | J61: =F61+G61+H61 -> 670339.63 | K61: =J61/E61 -> 0.074585028
A62: =A32 -> Mar | B62: =B32+C32+D32 -> 4360239 | C62: =B47 -> 266229.46 | D62: =M47 -> 46089.599 | E62: =(P47+R32)*$L$6 -> 10128150 | F62: =(E47+I47)*(1-IF(R32<0,-R32/P47,0)) -> 484313.25 | G62: =(L47+N47)*(1-IF(R32<0,-R32/P47,0)) -> 276474.84 | H62: =IF($J$6="Sí",MAX(0,R32),0) -> 0 | I62: =E62-F62-G62-H62 -> 9367362.1 | J62: =F62+G62+H62 -> 760788.1 | K62: =J62/E62 -> 0.075116194
A63: =A33 -> Abr | B63: =B33+C33+D33 -> 4173135 | C63: =B48 -> 235865.84 | D63: =M48 -> 50698.559 | E63: =(P48+R33)*$L$6 -> 9868549.7 | F63: =(E48+I48)*(1-IF(R33<0,-R33/P48,0)) -> 428949.71 | G63: =(L48+N48)*(1-IF(R33<0,-R33/P48,0)) -> 512388.7 | H63: =IF($J$6="Sí",MAX(0,R33),0) -> 0 | I63: =E63-F63-G63-H63 -> 8927211.3 | J63: =F63+G63+H63 -> 941338.41 | K63: =J63/E63 -> 0.095387715
A64: =A34 -> May | B64: =B34+C34+D34 -> 4482301 | C64: =B49 -> 223970.82 | D64: =M49 -> 48394.079 | E64: =(P49+R34)*$L$6 -> 10299570 | F64: =(E49+I49)*(1-IF(R34<0,-R34/P49,0)) -> 407197.71 | G64: =(L49+N49)*(1-IF(R34<0,-R34/P49,0)) -> 509994.76 | H64: =IF($J$6="Sí",MAX(0,R34),0) -> 0 | I64: =E64-F64-G64-H64 -> 9382377.5 | J64: =F64+G64+H64 -> 917192.47 | K64: =J64/E64 -> 0.08905153
A65: =A35 -> Jun | B65: =B35+C35+D35 -> 4223533 | C65: =B50 -> 209571.58 | D65: =M50 -> 48394.079 | E65: =(P50+R35)*$L$6 -> 9938713 | F65: =(E50+I50)*(1-IF(R35<0,-R35/P50,0)) -> 380152.04 | G65: =(L50+N50)*(1-IF(R35<0,-R35/P50,0)) -> 508834.75 | H65: =IF($J$6="Sí",MAX(0,R35),0) -> 0 | I65: =E65-F65-G65-H65 -> 9049726.2 | J65: =F65+G65+H65 -> 888986.8 | K65: =J65/E65 -> 0.089446873
A66: =A36 -> Jul | B66: =B36+C36+D36 -> 3672900 | C66: =B51 -> 211606.25 | D66: =M51 -> 53003.039 | E66: =(P51+R36)*$L$6 -> 8699766.1 | F66: =(E51+I51)*(1-IF(R36<0,-R36/P51,0)) -> 382946.77 | G66: =(L51+N51)*(1-IF(R36<0,-R36/P51,0)) -> 512113.47 | H66: =IF($J$6="Sí",MAX(0,R36),0) -> 0 | I66: =E66-F66-G66-H66 -> 7804705.8 | J66: =F66+G66+H66 -> 895060.24 | K66: =J66/E66 -> 0.10288325
A67: =A37 -> Ago | B67: =B37+C37+D37 -> 4176914 | C67: =B52 -> 197989.58 | D67: =M52 -> 48394.079 | E67: =(P52+R37)*$L$6 -> 9701128.8 | F67: =(E52+I52)*(1-IF(R37<0,-R37/P52,0)) -> 358596.45 | G67: =(L52+N52)*(1-IF(R37<0,-R37/P52,0)) -> 508060.55 | H67: =IF($J$6="Sí",MAX(0,R37),0) -> 0 | I67: =E67-F67-G67-H67 -> 8834471.8 | J67: =F67+G67+H67 -> 866657 | K67: =J67/E67 -> 0.089335686
A68: =A38 -> Sep | B68: =B38+C38+D38 -> 3596855 | C68: =B53 -> 187033.63 | D68: =M53 -> 48394.079 | E68: =(P53+R38)*$L$6 -> 8444072.9 | F68: =(E53+I53)*(1-IF(R38<0,-R38/P53,0)) -> 338378.12 | G68: =(L53+N53)*(1-IF(R38<0,-R38/P53,0)) -> 507498.06 | H68: =IF($J$6="Sí",MAX(0,R38),0) -> 0 | I68: =E68-F68-G68-H68 -> 7598196.8 | J68: =F68+G68+H68 -> 845876.17 | K68: =J68/E68 -> 0.10017395
A69: =A39 -> Oct | B69: =B39+C39+D39 -> 3339324 | C69: =B54 -> 206128.28 | D69: =M54 -> 53003.039 | E69: =(P54+R39)*$L$6 -> 7515911.8 | F69: =(E54+I54)*(1-IF(R39<0,-R39/P54,0)) -> 372426.15 | G69: =(L54+N54)*(1-IF(R39<0,-R39/P54,0)) -> 511280.08 | H69: =IF($J$6="Sí",MAX(0,R39),0) -> 0 | I69: =E69-F69-G69-H69 -> 6632205.6 | J69: =F69+G69+H69 -> 883706.23 | K69: =J69/E69 -> 0.11757805
A70: =A40 -> Nov | B70: =B40+C40+D40 -> 3432308 | C70: =B55 -> 213797.44 | D70: =M55 -> 43785.119 | E70: =(P55+R40)*$L$6 -> 8462839.5 | F70: =(E55+I55)*(1-IF(R40<0,-R40/P55,0)) -> 386841.73 | G70: =(L55+N55)*(1-IF(R40<0,-R40/P55,0)) -> 272756.68 | H70: =IF($J$6="Sí",MAX(0,R40),0) -> 0 | I70: =E70-F70-G70-H70 -> 7803241 | J70: =F70+G70+H70 -> 659598.42 | K70: =J70/E70 -> 0.077940556
A71: =A41 -> Dic | B71: =B41+C41+D41 -> 3272026 | C71: =B56 -> 204876.17 | D71: =M56 -> 50698.559 | E71: =(P56+R41)*$L$6 -> 7999627.6 | F71: =(E56+I56)*(1-IF(R41<0,-R41/P56,0)) -> 370793.18 | G71: =(L56+N56)*(1-IF(R41<0,-R41/P56,0)) -> 279525.76 | H71: =IF($J$6="Sí",MAX(0,R41),0) -> 0 | I71: =E71-F71-G71-H71 -> 7349308.6 | J71: =F71+G71+H71 -> 650318.94 | K71: =J71/E71 -> 0.081293651
A72: TOTAL | B72: =SUM(B60:B71) -> 45719537 | C72: =SUM(C60:C71) -> 2598280.6 | D72: =SUM(D60:D71) -> 585337.91 | E72: =SUM(E60:E71) -> 1.088104e+08 | F72: =SUM(F60:F71) -> 4713237.5 | G72: =SUM(G60:G71) -> 4954128.6 | H72: =SUM(H60:H71) -> 0 | I72: =SUM(I60:I71) -> 99143037 | J72: =SUM(J60:J71) -> 9667366.1 | K72: =J72/E72 -> 0.088845973
A73: Tarifa Actual (Σ) = recibo a CFE pleno $108,810,403 (dato workbook GEPP, calibrado del motor ×1.000). Ahorro = motor (golden 18/18).
A75: 6. PROYECCIÓN 20 AÑOS — Tarifa Actual con escalón 2032 · ahorros persisten · PPA se transfiere al cliente al término
A76: Bases año-0 (motor): | B76: PV con AA | C76: =F72 -> 4713237.5 | D76: PV CFE pleno | E76: =F72+SUMPRODUCT(E45:E56*(1/O45:O56-1)) -> 4713237.5 | F76: BESS | G76: =G72 -> 4954128.6 | H76: FP | I76: =H72 -> 0 | J76: Gen PV kWh | K76: =C72 -> 2598280.6
A77: Año | B77: Régimen | C77: Tarifa Actual $ | D77: Ah PV $ | E77: Ah BESS $ | F77: Ah FP $ | G77: Costo c/proy $ | H77: Flujo Compra $ | I77: Pago PPA $ | J77: Comisión $ | K77: Flujo Cliente PPA $ | L77: Flujo Financiador $
A78: 0 | B78: Inversión | H78: =-B26-B25-D25 -> -32640389 | K78: 0 | L78: =-B26-B25-D25 -> -32640389
A79: 1 | B79: =IF(A79<=(Supuestos!$B$22-Supuestos!$B$24),"Autoabasto","CFE pleno") -> Autoabasto | C79: =IF(A79<=(Supuestos!$B$22-Supuestos!$B$24),$B$12,$B$10)*(1+Supuestos!$B$8)^A79 -> 1.0826498e+08 | D79: =IF(A79<=(Supuestos!$B$22-Supuestos!$B$24),$C$76,$E$76)*(1+Supuestos!$B$8)^A79*(1-Supuestos!$B$11)^A79 -> 4971051.5 | E79: =$G$76*(1+Supuestos!$B$8)^A79*(1-Supuestos!$B$12)^A79*Supuestos!$B$10 -> 3889300.6 | F79: =$I$76*(1+Supuestos!$B$8)^A79 -> 0 | G79: =C79-D79-E79-F79 -> 99404624 | H79: =D79+E79+F79-(Supuestos!$B$19*$B$6+Supuestos!$B$20*$F$6)*(1+Supuestos!$B$8)^(A79-1) -> 7934160.3 | I79: =IF(A79<=Supuestos!$J$32,$K$76*(1-Supuestos!$B$11)^A79*Supuestos!$I$32*(1+Supuestos!$B$9)^(A79-1),0) -> 4166710.6 | J79: =E79*Supuestos!$K$32 -> 1944650.3 | K79: =D79-I79+E79-J79+F79-IF(A79<=Supuestos!$J$32,0,Supuestos!$B$19*$B$6*(1+Supuestos!$B$8)^(A79-1)) -> 2748991.2 | L79: =I79+J79-IF(A79<=Supuestos!$J$32,(Supuestos!$B$19*$B$6+Supuestos!$B$20*$F$6),Supuestos!$B$20*$F$6)*(1+Supuestos!$B$8)^(A79-1) -> 5185169.1
A80: 2 | B80: =IF(A80<=(Supuestos!$B$22-Supuestos!$B$24),"Autoabasto","CFE pleno") -> Autoabasto | C80: =IF(A80<=(Supuestos!$B$22-Supuestos!$B$24),$B$12,$B$10)*(1+Supuestos!$B$8)^A80 -> 1.1476087e+08 | D80: =IF(A80<=(Supuestos!$B$22-Supuestos!$B$24),$C$76,$E$76)*(1+Supuestos!$B$8)^A80*(1-Supuestos!$B$11)^A80 -> 5242968.1 | E80: =$G$76*(1+Supuestos!$B$8)^A80*(1-Supuestos!$B$12)^A80*Supuestos!$B$10 -> 4071125.4 | F80: =$I$76*(1+Supuestos!$B$8)^A80 -> 0 | G80: =C80-D80-E80-F80 -> 1.0544678e+08 | H80: =D80+E80+F80-(Supuestos!$B$19*$B$6+Supuestos!$B$20*$F$6)*(1+Supuestos!$B$8)^(A80-1) -> 8332330.1 | I80: =IF(A80<=Supuestos!$J$32,$K$76*(1-Supuestos!$B$11)^A80*Supuestos!$I$32*(1+Supuestos!$B$9)^(A80-1),0) -> 4353170.9 | J80: =E80*Supuestos!$K$32 -> 2035562.7 | K80: =D80-I80+E80-J80+F80-IF(A80<=Supuestos!$J$32,0,Supuestos!$B$19*$B$6*(1+Supuestos!$B$8)^(A80-1)) -> 2925359.8 | L80: =I80+J80-IF(A80<=Supuestos!$J$32,(Supuestos!$B$19*$B$6+Supuestos!$B$20*$F$6),Supuestos!$B$20*$F$6)*(1+Supuestos!$B$8)^(A80-1) -> 5406970.3
A81: 3 | B81: =IF(A81<=(Supuestos!$B$22-Supuestos!$B$24),"Autoabasto","CFE pleno") -> Autoabasto | C81: =IF(A81<=(Supuestos!$B$22-Supuestos!$B$24),$B$12,$B$10)*(1+Supuestos!$B$8)^A81 -> 1.2164653e+08 | D81: =IF(A81<=(Supuestos!$B$22-Supuestos!$B$24),$C$76,$E$76)*(1+Supuestos!$B$8)^A81*(1-Supuestos!$B$11)^A81 -> 5529758.4 | E81: =$G$76*(1+Supuestos!$B$8)^A81*(1-Supuestos!$B$12)^A81*Supuestos!$B$10 -> 4261450.5 | F81: =$I$76*(1+Supuestos!$B$8)^A81 -> 0 | G81: =C81-D81-E81-F81 -> 1.1185532e+08 | H81: =D81+E81+F81-(Supuestos!$B$19*$B$6+Supuestos!$B$20*$F$6)*(1+Supuestos!$B$8)^(A81-1) -> 8750539.8 | I81: =IF(A81<=Supuestos!$J$32,$K$76*(1-Supuestos!$B$11)^A81*Supuestos!$I$32*(1+Supuestos!$B$9)^(A81-1),0) -> 4547975.3 | J81: =E81*Supuestos!$K$32 -> 2130725.3 | K81: =D81-I81+E81-J81+F81-IF(A81<=Supuestos!$J$32,0,Supuestos!$B$19*$B$6*(1+Supuestos!$B$8)^(A81-1)) -> 3112508.4 | L81: =I81+J81-IF(A81<=Supuestos!$J$32,(Supuestos!$B$19*$B$6+Supuestos!$B$20*$F$6),Supuestos!$B$20*$F$6)*(1+Supuestos!$B$8)^(A81-1) -> 5638031.4
A82: 4 | B82: =IF(A82<=(Supuestos!$B$22-Supuestos!$B$24),"Autoabasto","CFE pleno") -> Autoabasto | C82: =IF(A82<=(Supuestos!$B$22-Supuestos!$B$24),$B$12,$B$10)*(1+Supuestos!$B$8)^A82 -> 1.2894532e+08 | D82: =IF(A82<=(Supuestos!$B$22-Supuestos!$B$24),$C$76,$E$76)*(1+Supuestos!$B$8)^A82*(1-Supuestos!$B$11)^A82 -> 5832236.2 | E82: =$G$76*(1+Supuestos!$B$8)^A82*(1-Supuestos!$B$12)^A82*Supuestos!$B$10 -> 4460673.3 | F82: =$I$76*(1+Supuestos!$B$8)^A82 -> 0 | G82: =C82-D82-E82-F82 -> 1.1865241e+08 | H82: =D82+E82+F82-(Supuestos!$B$19*$B$6+Supuestos!$B$20*$F$6)*(1+Supuestos!$B$8)^(A82-1) -> 9189800.2 | I82: =IF(A82<=Supuestos!$J$32,$K$76*(1-Supuestos!$B$11)^A82*Supuestos!$I$32*(1+Supuestos!$B$9)^(A82-1),0) -> 4751497.2 | J82: =E82*Supuestos!$K$32 -> 2230336.7 | K82: =D82-I82+E82-J82+F82-IF(A82<=Supuestos!$J$32,0,Supuestos!$B$19*$B$6*(1+Supuestos!$B$8)^(A82-1)) -> 3311075.7 | L82: =I82+J82-IF(A82<=Supuestos!$J$32,(Supuestos!$B$19*$B$6+Supuestos!$B$20*$F$6),Supuestos!$B$20*$F$6)*(1+Supuestos!$B$8)^(A82-1) -> 5878724.6
A83: 5 | B83: =IF(A83<=(Supuestos!$B$22-Supuestos!$B$24),"Autoabasto","CFE pleno") -> Autoabasto | C83: =IF(A83<=(Supuestos!$B$22-Supuestos!$B$24),$B$12,$B$10)*(1+Supuestos!$B$8)^A83 -> 1.3668204e+08 | D83: =IF(A83<=(Supuestos!$B$22-Supuestos!$B$24),$C$76,$E$76)*(1+Supuestos!$B$8)^A83*(1-Supuestos!$B$11)^A83 -> 6151259.5 | E83: =$G$76*(1+Supuestos!$B$8)^A83*(1-Supuestos!$B$12)^A83*Supuestos!$B$10 -> 4669209.8 | F83: =$I$76*(1+Supuestos!$B$8)^A83 -> 0 | G83: =C83-D83-E83-F83 -> 1.2586157e+08 | H83: =D83+E83+F83-(Supuestos!$B$19*$B$6+Supuestos!$B$20*$F$6)*(1+Supuestos!$B$8)^(A83-1) -> 9651173.5 | I83: =IF(A83<=Supuestos!$J$32,$K$76*(1-Supuestos!$B$11)^A83*Supuestos!$I$32*(1+Supuestos!$B$9)^(A83-1),0) -> 4964126.7 | J83: =E83*Supuestos!$K$32 -> 2334604.9 | K83: =D83-I83+E83-J83+F83-IF(A83<=Supuestos!$J$32,0,Supuestos!$B$19*$B$6*(1+Supuestos!$B$8)^(A83-1)) -> 3521737.7 | L83: =I83+J83-IF(A83<=Supuestos!$J$32,(Supuestos!$B$19*$B$6+Supuestos!$B$20*$F$6),Supuestos!$B$20*$F$6)*(1+Supuestos!$B$8)^(A83-1) -> 6129435.7
A84: 6 | B84: =IF(A84<=(Supuestos!$B$22-Supuestos!$B$24),"Autoabasto","CFE pleno") -> Autoabasto | C84: =IF(A84<=(Supuestos!$B$22-Supuestos!$B$24),$B$12,$B$10)*(1+Supuestos!$B$8)^A84 -> 1.4488296e+08 | D84: =IF(A84<=(Supuestos!$B$22-Supuestos!$B$24),$C$76,$E$76)*(1+Supuestos!$B$8)^A84*(1-Supuestos!$B$11)^A84 -> 6487733.4 | E84: =$G$76*(1+Supuestos!$B$8)^A84*(1-Supuestos!$B$12)^A84*Supuestos!$B$10 -> 4887495.4 | F84: =$I$76*(1+Supuestos!$B$8)^A84 -> 0 | G84: =C84-D84-E84-F84 -> 1.3350773e+08 | H84: =D84+E84+F84-(Supuestos!$B$19*$B$6+Supuestos!$B$20*$F$6)*(1+Supuestos!$B$8)^(A84-1) -> 10135775 | I84: =IF(A84<=Supuestos!$J$32,$K$76*(1-Supuestos!$B$11)^A84*Supuestos!$I$32*(1+Supuestos!$B$9)^(A84-1),0) -> 5186271.4 | J84: =E84*Supuestos!$K$32 -> 2443747.7 | K84: =D84-I84+E84-J84+F84-IF(A84<=Supuestos!$J$32,0,Supuestos!$B$19*$B$6*(1+Supuestos!$B$8)^(A84-1)) -> 3745209.7 | L84: =I84+J84-IF(A84<=Supuestos!$J$32,(Supuestos!$B$19*$B$6+Supuestos!$B$20*$F$6),Supuestos!$B$20*$F$6)*(1+Supuestos!$B$8)^(A84-1) -> 6390565.4
A85: 7 | B85: =IF(A85<=(Supuestos!$B$22-Supuestos!$B$24),"Autoabasto","CFE pleno") -> CFE pleno | C85: =IF(A85<=(Supuestos!$B$22-Supuestos!$B$24),$B$12,$B$10)*(1+Supuestos!$B$8)^A85 -> 1.6361061e+08 | D85: =IF(A85<=(Supuestos!$B$22-Supuestos!$B$24),$C$76,$E$76)*(1+Supuestos!$B$8)^A85*(1-Supuestos!$B$11)^A85 -> 6842612.4 | E85: =$G$76*(1+Supuestos!$B$8)^A85*(1-Supuestos!$B$12)^A85*Supuestos!$B$10 -> 5115985.8 | F85: =$I$76*(1+Supuestos!$B$8)^A85 -> 0 | G85: =C85-D85-E85-F85 -> 1.5165202e+08 | H85: =D85+E85+F85-(Supuestos!$B$19*$B$6+Supuestos!$B$20*$F$6)*(1+Supuestos!$B$8)^(A85-1) -> 10644777 | I85: =IF(A85<=Supuestos!$J$32,$K$76*(1-Supuestos!$B$11)^A85*Supuestos!$I$32*(1+Supuestos!$B$9)^(A85-1),0) -> 5418357 | J85: =E85*Supuestos!$K$32 -> 2557992.9 | K85: =D85-I85+E85-J85+F85-IF(A85<=Supuestos!$J$32,0,Supuestos!$B$19*$B$6*(1+Supuestos!$B$8)^(A85-1)) -> 3982248.3 | L85: =I85+J85-IF(A85<=Supuestos!$J$32,(Supuestos!$B$19*$B$6+Supuestos!$B$20*$F$6),Supuestos!$B$20*$F$6)*(1+Supuestos!$B$8)^(A85-1) -> 6662529.1
A86: 8 | B86: =IF(A86<=(Supuestos!$B$22-Supuestos!$B$24),"Autoabasto","CFE pleno") -> CFE pleno | C86: =IF(A86<=(Supuestos!$B$22-Supuestos!$B$24),$B$12,$B$10)*(1+Supuestos!$B$8)^A86 -> 1.7342725e+08 | D86: =IF(A86<=(Supuestos!$B$22-Supuestos!$B$24),$C$76,$E$76)*(1+Supuestos!$B$8)^A86*(1-Supuestos!$B$11)^A86 -> 7216903.3 | E86: =$G$76*(1+Supuestos!$B$8)^A86*(1-Supuestos!$B$12)^A86*Supuestos!$B$10 -> 5355158.1 | F86: =$I$76*(1+Supuestos!$B$8)^A86 -> 0 | G86: =C86-D86-E86-F86 -> 1.6085519e+08 | H86: =D86+E86+F86-(Supuestos!$B$19*$B$6+Supuestos!$B$20*$F$6)*(1+Supuestos!$B$8)^(A86-1) -> 11179411 | I86: =IF(A86<=Supuestos!$J$32,$K$76*(1-Supuestos!$B$11)^A86*Supuestos!$I$32*(1+Supuestos!$B$9)^(A86-1),0) -> 5660828.5 | J86: =E86*Supuestos!$K$32 -> 2677579.1 | K86: =D86-I86+E86-J86+F86-IF(A86<=Supuestos!$J$32,0,Supuestos!$B$19*$B$6*(1+Supuestos!$B$8)^(A86-1)) -> 4233653.9 | L86: =I86+J86-IF(A86<=Supuestos!$J$32,(Supuestos!$B$19*$B$6+Supuestos!$B$20*$F$6),Supuestos!$B$20*$F$6)*(1+Supuestos!$B$8)^(A86-1) -> 6945757.5
A87: 9 | B87: =IF(A87<=(Supuestos!$B$22-Supuestos!$B$24),"Autoabasto","CFE pleno") -> CFE pleno | C87: =IF(A87<=(Supuestos!$B$22-Supuestos!$B$24),$B$12,$B$10)*(1+Supuestos!$B$8)^A87 -> 1.8383289e+08 | D87: =IF(A87<=(Supuestos!$B$22-Supuestos!$B$24),$C$76,$E$76)*(1+Supuestos!$B$8)^A87*(1-Supuestos!$B$11)^A87 -> 7611667.9 | E87: =$G$76*(1+Supuestos!$B$8)^A87*(1-Supuestos!$B$12)^A87*Supuestos!$B$10 -> 5605511.8 | F87: =$I$76*(1+Supuestos!$B$8)^A87 -> 0 | G87: =C87-D87-E87-F87 -> 1.7061571e+08 | H87: =D87+E87+F87-(Supuestos!$B$19*$B$6+Supuestos!$B$20*$F$6)*(1+Supuestos!$B$8)^(A87-1) -> 11740971 | I87: =IF(A87<=Supuestos!$J$32,$K$76*(1-Supuestos!$B$11)^A87*Supuestos!$I$32*(1+Supuestos!$B$9)^(A87-1),0) -> 5914150.6 | J87: =E87*Supuestos!$K$32 -> 2802755.9 | K87: =D87-I87+E87-J87+F87-IF(A87<=Supuestos!$J$32,0,Supuestos!$B$19*$B$6*(1+Supuestos!$B$8)^(A87-1)) -> 4500273.2 | L87: =I87+J87-IF(A87<=Supuestos!$J$32,(Supuestos!$B$19*$B$6+Supuestos!$B$20*$F$6),Supuestos!$B$20*$F$6)*(1+Supuestos!$B$8)^(A87-1) -> 7240697.4
A88: 10 | B88: =IF(A88<=(Supuestos!$B$22-Supuestos!$B$24),"Autoabasto","CFE pleno") -> CFE pleno | C88: =IF(A88<=(Supuestos!$B$22-Supuestos!$B$24),$B$12,$B$10)*(1+Supuestos!$B$8)^A88 -> 1.9486286e+08 | D88: =IF(A88<=(Supuestos!$B$22-Supuestos!$B$24),$C$76,$E$76)*(1+Supuestos!$B$8)^A88*(1-Supuestos!$B$11)^A88 -> 8028026.2 | E88: =$G$76*(1+Supuestos!$B$8)^A88*(1-Supuestos!$B$12)^A88*Supuestos!$B$10 -> 5867569.4 | F88: =$I$76*(1+Supuestos!$B$8)^A88 -> 0 | G88: =C88-D88-E88-F88 -> 1.8096726e+08 | H88: =D88+E88+F88-(Supuestos!$B$19*$B$6+Supuestos!$B$20*$F$6)*(1+Supuestos!$B$8)^(A88-1) -> 12330814 | I88: =IF(A88<=Supuestos!$J$32,$K$76*(1-Supuestos!$B$11)^A88*Supuestos!$I$32*(1+Supuestos!$B$9)^(A88-1),0) -> 6178808.8 | J88: =E88*Supuestos!$K$32 -> 2933784.7 | K88: =D88-I88+E88-J88+F88-IF(A88<=Supuestos!$J$32,0,Supuestos!$B$19*$B$6*(1+Supuestos!$B$8)^(A88-1)) -> 4783002.1 | L88: =I88+J88-IF(A88<=Supuestos!$J$32,(Supuestos!$B$19*$B$6+Supuestos!$B$20*$F$6),Supuestos!$B$20*$F$6)*(1+Supuestos!$B$8)^(A88-1) -> 7547811.9
A89: 11 | B89: =IF(A89<=(Supuestos!$B$22-Supuestos!$B$24),"Autoabasto","CFE pleno") -> CFE pleno | C89: =IF(A89<=(Supuestos!$B$22-Supuestos!$B$24),$B$12,$B$10)*(1+Supuestos!$B$8)^A89 -> 2.0655463e+08 | D89: =IF(A89<=(Supuestos!$B$22-Supuestos!$B$24),$C$76,$E$76)*(1+Supuestos!$B$8)^A89*(1-Supuestos!$B$11)^A89 -> 8467159.2 | E89: =$G$76*(1+Supuestos!$B$8)^A89*(1-Supuestos!$B$12)^A89*Supuestos!$B$10 -> 6141878.3 | F89: =$I$76*(1+Supuestos!$B$8)^A89 -> 0 | G89: =C89-D89-E89-F89 -> 1.9194559e+08 | H89: =D89+E89+F89-(Supuestos!$B$19*$B$6+Supuestos!$B$20*$F$6)*(1+Supuestos!$B$8)^(A89-1) -> 12950369 | I89: =IF(A89<=Supuestos!$J$32,$K$76*(1-Supuestos!$B$11)^A89*Supuestos!$I$32*(1+Supuestos!$B$9)^(A89-1),0) -> 6455310.5 | J89: =E89*Supuestos!$K$32 -> 3070939.1 | K89: =D89-I89+E89-J89+F89-IF(A89<=Supuestos!$J$32,0,Supuestos!$B$19*$B$6*(1+Supuestos!$B$8)^(A89-1)) -> 5082787.8 | L89: =I89+J89-IF(A89<=Supuestos!$J$32,(Supuestos!$B$19*$B$6+Supuestos!$B$20*$F$6),Supuestos!$B$20*$F$6)*(1+Supuestos!$B$8)^(A89-1) -> 7867581.1
A90: 12 | B90: =IF(A90<=(Supuestos!$B$22-Supuestos!$B$24),"Autoabasto","CFE pleno") -> CFE pleno | C90: =IF(A90<=(Supuestos!$B$22-Supuestos!$B$24),$B$12,$B$10)*(1+Supuestos!$B$8)^A90 -> 2.1894791e+08 | D90: =IF(A90<=(Supuestos!$B$22-Supuestos!$B$24),$C$76,$E$76)*(1+Supuestos!$B$8)^A90*(1-Supuestos!$B$11)^A90 -> 8930312.8 | E90: =$G$76*(1+Supuestos!$B$8)^A90*(1-Supuestos!$B$12)^A90*Supuestos!$B$10 -> 6429011.1 | F90: =$I$76*(1+Supuestos!$B$8)^A90 -> 0 | G90: =C90-D90-E90-F90 -> 2.0358858e+08 | H90: =D90+E90+F90-(Supuestos!$B$19*$B$6+Supuestos!$B$20*$F$6)*(1+Supuestos!$B$8)^(A90-1) -> 13601135 | I90: =IF(A90<=Supuestos!$J$32,$K$76*(1-Supuestos!$B$11)^A90*Supuestos!$I$32*(1+Supuestos!$B$9)^(A90-1),0) -> 6744185.7 | J90: =E90*Supuestos!$K$32 -> 3214505.6 | K90: =D90-I90+E90-J90+F90-IF(A90<=Supuestos!$J$32,0,Supuestos!$B$19*$B$6*(1+Supuestos!$B$8)^(A90-1)) -> 5400632.7 | L90: =I90+J90-IF(A90<=Supuestos!$J$32,(Supuestos!$B$19*$B$6+Supuestos!$B$20*$F$6),Supuestos!$B$20*$F$6)*(1+Supuestos!$B$8)^(A90-1) -> 8200502.6
... A98: 20 | B98: =IF(A98<=(Supuestos!$B$22-Supuestos!$B$24),"Autoabasto","CFE pleno") -> CFE pleno | C98: =IF(A98<=(Supuestos!$B$22-Supuestos!$B$24),$B$12,$B$10)*(1+Supuestos!$B$8)^A98 -> 3.489697e+08 | D98: =IF(A98<=(Supuestos!$B$22-Supuestos!$B$24),$C$76,$E$76)*(1+Supuestos!$B$8)^A98*(1-Supuestos!$B$11)^A98 -> 13674084 | E98: =$G$76*(1+Supuestos!$B$8)^A98*(1-Supuestos!$B$12)^A98*Supuestos!$B$10 -> 9265906.9 | F98: =$I$76*(1+Supuestos!$B$8)^A98 -> 0 | G98: =C98-D98-E98-F98 -> 3.2602971e+08 | H98: =D98+E98+F98-(Supuestos!$B$19*$B$6+Supuestos!$B$20*$F$6)*(1+Supuestos!$B$8)^(A98-1) -> 20137705 | I98: =IF(A98<=Supuestos!$J$32,$K$76*(1-Supuestos!$B$11)^A98*Supuestos!$I$32*(1+Supuestos!$B$9)^(A98-1),0) -> 0 | J98: =E98*Supuestos!$K$32 -> 4632953.5 | K98: =D98-I98+E98-J98+F98-IF(A98<=Supuestos!$J$32,0,Supuestos!$B$19*$B$6*(1+Supuestos!$B$8)^(A98-1)) -> 16839041 | L98: =I98+J98-IF(A98<=Supuestos!$J$32,(Supuestos!$B$19*$B$6+Supuestos!$B$20*$F$6),Supuestos!$B$20*$F$6)*(1+Supuestos!$B$8)^(A98-1) -> 3298664.1
A99: Σ | H99: =SUM(H79:H98) -> 2.6298189e+08 | K99: =SUM(K79:K98) -> 1.419215e+08 | L99: =SUM(L79:L98) -> 1.210604e+08
F100: TIR compra: | G100: =IRR(H78:H98) -> 0.28926483 | I100: VPN compra @WACC: | K100: =NPV(Supuestos!$B$7,H79:H98)+H78 -> 49655657
F101: TIR financiador: | G101: =IRR(L78:L98) -> 0.17995412 | I101: VPN cliente PPA @WACC: | K101: =NPV(Supuestos!$B$7,K79:K98)+K78 -> 36199400
A102: Régimen: Autoabasto años 1-6 (2026-2031); CFE pleno desde 2032 (escalón en Tarifa Actual). El ahorro PV/BESS/FP persiste los 20 años; tras el plazo PPA el PV se transfiere a GEPP y conserva el 100% del ahorro.
A104: 7. COMPRAR vs PPA / AHORRO COMPARTIDO
A105: Métrica | B105: GEPP COMPRA | C105: PPA / Ahorro compartido
A106: Inversión GEPP $ | B106: =B26+B25+D25 -> 32640389 | C106: 0 | D106: Financiador funda todo (incl. capacitor)
A107: Beneficio GEPP año 1 $ | B107: =H79 -> 7934160.3 | C107: =K79 -> 2748991.2
A108: Beneficio 20 años acum. $ | B108: =H99 -> 2.6298189e+08 | C108: =SUM(K79:K98) -> 1.419215e+08
A109: TIR (proyecto / financiador) | B109: =G100 -> 0.28926483 | C109: =G101 -> 0.17995412
A110: Tarifa PPA $/kWh (editable en Supuestos) | B110: — | C110: =Supuestos!$I$32 -> 1.6117
A111: Plazo PPA años / PV se transfiere al cliente al término | C111: =Supuestos!$J$32 -> 15
A113: 8. POR QUÉ ESTE DIMENSIONAMIENTO ES EL ÓPTIMO PARA ESTE SITIO
A114: Mayor consumidor (45.7 GWh). Bajo el techo total de 3.15 MW recibe la mayor porción: 1,565 kWp (proporcional a su carga). Al reducir el PV el umbral queda más alto y el BESS 1,220 kW/2,440 kWh recorta MÁS demanda → su ahorro BESS sube (~$4.9M). >0.7 MW agregado ⇒ Autoconsumo CNE. COMPRAR = máximo ahorro al cliente (conserva el 100%).

Sheet Proplasa Tapas
A1: PROPLASA TAPAS — Memoria de cálculo trazable y propuesta
A2: Medidor 807DYN · GDMTH SIN · Demanda contratada 2,814 kW · AUTOCONSUMO interconectado (>0.7 MW) — permiso SIMPLIFICADO CNE
A3: GEPP pide: Combinar autoabasto (ENEL) con generación solar en sitio
A5: PARÁMETROS DEL SISTEMA (desde Supuestos — edítalos allí)
A6: PV kWp | B6: =Supuestos!$B$33 -> 839.41 | C6: BESS kW | D6: =Supuestos!$C$33 -> 751.5 | E6: BESS kWh | F6: =Supuestos!$D$33 -> 1470 | G6: Entrega útil kWh | H6: =Supuestos!$D$33*Supuestos!$B$17*SQRT(Supuestos!$B$18) -> 1382.688 | I6: FP corr. | J6: =Supuestos!$E$33 -> No | K6: Calib→recibo | L6: =$B$10/(SUM(P45:P56)+SUM(R30:R41)) -> 1
A8: 1. ESTRUCTURA DE COSTO Y AHORRO (2025, pre-IVA · datos del workbook GEPP + motor)
A9: Concepto | B9: $ / año | C9: $ / kWh | D9: kWh | E9: Nota
A10: CFE BRUTO = Tarifa Actual (todo a CFE pleno, sin autoabasto) | B10: 71319345 | C10: =B10/D10 -> 2.3752187 | D10: 30026433 | E10: Lo que pagarían 100% en CFE sin ENEL/Tala ni PV/BESS
A11: (−) Ahorro autoabasto (ENEL) | B11: 7795742.9 | E11: Beneficio ENEL ($1.78/kWh vs CFE; validado por colapso 2026)
A12: (=) Costo actual que paga GEPP hoy | B12: =B10-B11 -> 63523603 | C12: =B12/D12 -> 2.1155894 | D12: =D10 -> 30026433
A13: › CFE (tarifa CFE plena) | B13: 17688145 | C13: =B13/D13 -> 2.8652615 | D13: 6173309
A14: › ENEL | B14: 45835458 | C14: =B14/D14 -> 1.9215704 | D14: 23853124
A15: › Mezcla de suministro 2025 | B15: =D13/D12 -> 0.20559582 | C15: CFE | D15: =D14/D12 -> 0.79440418 | E15: ENEL (en 2026 ENEL ya colapsó → CFE ~85%)
A16: Ahorros del proyecto (motor 2025, sobre la carga física):
A17: (−) Ahorro PV (energía intermedia + demanda vía umbral) | B17: =F72 -> 2530292.8 | D17: =C72 -> 1393504.5 | E17: Gen solar kWh/año →
A18: (−) Ahorro BESS (recorte de punta + arbitraje) | B18: =G72 -> 2976504.5
A19: (−) Ahorro FP (corrección factor de potencia) | B19: =H72 -> 0 | E19: FP sano — sin multa
A20: (=) Costo neto con proyecto (hoy) | B20: =B12-B17-B18-B19 -> 58016805
A21: Ahorro proyecto PV+BESS+FP (vs costo hoy) | B21: =B17+B18+B19 -> 5506797.3 | C21: =B21/B12 -> 0.086688996
A22: Ahorro TOTAL vs CFE bruto (incl. autoabasto+proyecto) | B22: =B10-B20 -> 13302540 | C22: =B22/B10 -> 0.18652078
A24: 2. CAPEX (fórmulas vivas desde Supuestos)
A25: CAPEX PV = kWp×1000×USD/Wp×FX | B25: =$B$6*1000*Supuestos!$F$33*Supuestos!$B$5 -> 11048734 | C25: CAPEX BESS = kWh×USD/kWh×FX | D25: =$F$6*Supuestos!$G$33*Supuestos!$B$5 -> 7223580
A26: CAPEX Capacitor FP (financiador en PPA) | B26: =Supuestos!$H$33 -> 0 | C26: CAPEX TOTAL (compra) | D26: =B25+D25+B26 -> 18272314 | E26: Bajo PPA, el capacitor lo paga el financiador → el cliente no desembolsa
A28: 3. ENTRADAS MENSUALES (AZUL = datos del recibo / recurso 2025)
A29: Mes | B29: kWh Base | C29: kWh Int | D29: kWh Punta | E29: Días | F29: Dem Pta kW | G29: Dem Máx kW | H29: T.Int $ | I29: T.Base $ | J29: T.Pta $ | K29: T.Cap $ | L29: T.Dist $ | M29: T.Fijo $ | N29: Rend | O29: %AC | P29: HrsP | Q29: DíasP | R29: Bonif FP
A30: Ene | B30: 881325 | C30: 1481542 | D30: 365971 | E30: 31 | F30: 4272 | G30: 4350 | H30: 1.819675 | I30: 1.10665 | J30: 2.1272 | K30: 402.0725 | L30: 86.15 | M30: 703.36 | N30: 142.8 | O30: 1 | P30: 4 | Q30: 22 | R30: -6119.9
A31: Feb | B31: 805606 | C31: 1252899 | D31: 303074 | E31: 28 | F31: 4136 | G31: 4251 | H31: 1.819675 | I31: 1.10665 | J31: 2.1272 | K31: 402.0725 | L31: 86.15 | M31: 703.36 | N31: 139.1 | O31: 1 | P31: 4 | Q31: 19 | R31: -2405.6
A32: Mar | B32: 960995 | C32: 1426117 | D32: 335764 | E32: 31 | F32: 4183 | G32: 4350 | H32: 1.819675 | I32: 1.10665 | J32: 2.1272 | K32: 402.0725 | L32: 86.15 | M32: 703.36 | N32: 170.1 | O32: 1 | P32: 4 | Q32: 20 | R32: -31043.08
A33: Abr | B33: 891289 | C33: 1620825 | D33: 207717 | E33: 30 | F33: 4106 | G33: 4250 | H33: 1.819675 | I33: 1.10665 | J33: 2.1272 | K33: 402.0725 | L33: 86.15 | M33: 703.36 | N33: 150.7 | O33: 1 | P33: 2 | Q33: 22 | R33: -30192.23
A34: May | B34: 960467 | C34: 1696392 | D34: 162699 | E34: 31 | F34: 4081 | G34: 4308 | H34: 1.819675 | I34: 1.10665 | J34: 2.1272 | K34: 402.0725 | L34: 86.15 | M34: 703.36 | N34: 143.1 | O34: 1 | P34: 2 | Q34: 21 | R34: -28885.73
A35: Jun | B35: 923339 | C35: 1593739 | D35: 157968 | E35: 30 | F35: 4146 | G35: 4228 | H35: 1.819675 | I35: 1.10665 | J35: 2.1272 | K35: 402.0725 | L35: 86.15 | M35: 703.36 | N35: 133.9 | O35: 1 | P35: 2 | Q35: 21 | R35: -27370.41
A36: Jul | B36: 765377 | C36: 1464549 | D36: 150284 | E36: 31 | F36: 3935 | G36: 3987 | H36: 1.819675 | I36: 1.10665 | J36: 2.1272 | K36: 402.0725 | L36: 86.15 | M36: 703.36 | N36: 135.2 | O36: 1 | P36: 2 | Q36: 23 | R36: -5877.13
A37: Ago | B37: 900504 | C37: 1602297 | D37: 152370 | E37: 31 | F37: 3868 | G37: 4012 | H37: 1.819675 | I37: 1.10665 | J37: 2.1272 | K37: 402.0725 | L37: 86.15 | M37: 703.36 | N37: 126.5 | O37: 1 | P37: 2 | Q37: 21 | R37: -8586.23
A38: Sep | B38: 746286 | C38: 1358643 | D38: 130996 | E38: 30 | F38: 3761 | G38: 3791 | H38: 1.819675 | I38: 1.10665 | J38: 2.1272 | K38: 402.0725 | L38: 86.15 | M38: 703.36 | N38: 119.5 | O38: 1 | P38: 2 | Q38: 21 | R38: -3056.13
A39: Oct | B39: 754528 | C39: 1417944 | D39: 176270 | E39: 31 | F39: 3121 | G39: 3433 | H39: 1.819675 | I39: 1.10665 | J39: 2.1272 | K39: 402.0725 | L39: 86.15 | M39: 703.36 | N39: 131.7 | O39: 1 | P39: 2 | Q39: 23 | R39: -2237.03
A40: Nov | B40: 756600 | C40: 1150215 | D40: 278429 | E40: 30 | F40: 3661 | G40: 3772 | H40: 1.819675 | I40: 1.10665 | J40: 2.1272 | K40: 402.0725 | L40: 86.15 | M40: 703.36 | N40: 136.6 | O40: 1 | P40: 4 | Q40: 19 | R40: -2622.04
A41: Dic | B41: 741947 | C41: 1178280 | D41: 273186 | E41: 31 | F41: 3968 | G41: 3985 | H41: 1.819675 | I41: 1.10665 | J41: 2.1272 | K41: 402.0725 | L41: 86.15 | M41: 703.36 | N41: 130.9 | O41: 1 | P41: 4 | Q41: 22 | R41: -4631.66
A42: 4. CÁLCULO DE AHORRO MENSUAL (motor — fórmulas que referencian las ENTRADAS)
A43: Mes | B43: Gen kWh | C43: Umbral kW | D43: Autocons | E43: Ah PV ener | F43: Umbral post | G43: Cap base | H43: Cap pre-B | I43: Ah PV dem | J43: Recorte BESS | K43: Cap post | L43: Ah BESS dem | M43: Desc kWh | N43: Arbitraje $ | O43: Fac.AA | P43: mem $ | Q43: Ah PV+BESS
A45: =A30 -> Ene | B45: =$B$6*N30 -> 119867.75 | C45: =(B30+C30+D30)/(E30*24*Supuestos!$B$16) -> 6434.7246 | D45: =MIN(B45*O30,C30) -> 119867.75 | E45: =D45*H30*O45 -> 218120.34 | F45: =((B30+C30+D30)-D45)/(E30*24*Supuestos!$B$16) -> 6152.071 | G45: =MIN(F30,C45) -> 4272 | H45: =MIN(F30,F45) -> 4272 | I45: =(G45-H45)*K30 -> 0 | J45: =IF(P30=0,0,MIN($D$6,$H$6/P30)) -> 345.67199 | K45: =MIN(MAX(F30-J45,0),F45) -> 3926.328 | L45: =(H45-K45)*K30 -> 138985.2 | M45: =IF(P30=0,0,MIN($H$6*Q30,D30)) -> 30419.135 | N45: =M45*J30-(M45/Supuestos!$B$18)*I30 -> 29641.61 | O45: 1 | P45: =M30+B30*I30+C30*H30+D30*J30+G45*K30+MIN(G30,C45)*L30 -> 6542846.3 | Q45: =(E45+I45)+(L45+N45) -> 386747.16
A46: =A31 -> Feb | B46: =$B$6*N31 -> 116761.93 | C46: =(B31+C31+D31)/(E31*24*Supuestos!$B$16) -> 6165.3587 | D46: =MIN(B46*O31,C31) -> 116761.93 | E46: =D46*H31*O46 -> 212468.77 | F46: =((B31+C31+D31)-D46)/(E31*24*Supuestos!$B$16) -> 5860.5291 | G46: =MIN(F31,C46) -> 4136 | H46: =MIN(F31,F46) -> 4136 | I46: =(G46-H46)*K31 -> 0 | J46: =IF(P31=0,0,MIN($D$6,$H$6/P31)) -> 345.67199 | K46: =MIN(MAX(F31-J46,0),F46) -> 3790.328 | L46: =(H46-K46)*K31 -> 138985.2 | M46: =IF(P31=0,0,MIN($H$6*Q31,D31)) -> 26271.071 | N46: =M46*J31-(M46/Supuestos!$B$18)*I31 -> 25599.572 | O46: 1 | P46: =M31+B31*I31+C31*H31+D31*J31+G46*K31+MIN(G31,C46)*L31 -> 5845990.8 | Q46: =(E46+I46)+(L46+N46) -> 377053.54
A47: =A32 -> Mar | B47: =$B$6*N32 -> 142783.64 | C47: =(B32+C32+D32)/(E32*24*Supuestos!$B$16) -> 6420.6659 | D47: =MIN(B47*O32,C32) -> 142783.64 | E47: =D47*H32*O47 -> 259819.82 | F47: =((B32+C32+D32)-D47)/(E32*24*Supuestos!$B$16) -> 6083.9756 | G47: =MIN(F32,C47) -> 4183 | H47: =MIN(F32,F47) -> 4183 | I47: =(G47-H47)*K32 -> 0 | J47: =IF(P32=0,0,MIN($D$6,$H$6/P32)) -> 345.67199 | K47: =MIN(MAX(F32-J47,0),F47) -> 3837.328 | L47: =(H47-K47)*K32 -> 138985.2 | M47: =IF(P32=0,0,MIN($H$6*Q32,D32)) -> 27653.759 | N47: =M47*J32-(M47/Supuestos!$B$18)*I32 -> 26946.918 | O47: 1 | P47: =M32+B32*I32+C32*H32+D32*J32+G47*K32+MIN(G32,C47)*L32 -> 6430116.9 | Q47: =(E47+I47)+(L47+N47) -> 425751.94
A48: =A33 -> Abr | B48: =$B$6*N33 -> 126499.09 | C48: =(B33+C33+D33)/(E33*24*Supuestos!$B$16) -> 6627.2685 | D48: =MIN(B48*O33,C33) -> 126499.09 | E48: =D48*H33*O48 -> 230187.23 | F48: =((B33+C33+D33)-D48)/(E33*24*Supuestos!$B$16) -> 6319.0349 | G48: =MIN(F33,C48) -> 4106 | H48: =MIN(F33,F48) -> 4106 | I48: =(G48-H48)*K33 -> 0 | J48: =IF(P33=0,0,MIN($D$6,$H$6/P33)) -> 691.34399 | K48: =MIN(MAX(F33-J48,0),F48) -> 3414.656 | L48: =(H48-K48)*K33 -> 277970.4 | M48: =IF(P33=0,0,MIN($H$6*Q33,D33)) -> 30419.135 | N48: =M48*J33-(M48/Supuestos!$B$18)*I33 -> 29641.61 | O48: 1 | P48: =M33+B33*I33+C33*H33+D33*J33+G48*K33+MIN(G33,C48)*L33 -> 6395325.9 | Q48: =(E48+I48)+(L48+N48) -> 537799.24
A49: =A34 -> May | B49: =$B$6*N34 -> 120119.57 | C49: =(B34+C34+D34)/(E34*24*Supuestos!$B$16) -> 6648.6465 | D49: =MIN(B49*O34,C34) -> 120119.57 | E49: =D49*H34*O49 -> 218578.58 | F49: =((B34+C34+D34)-D49)/(E34*24*Supuestos!$B$16) -> 6365.399 | G49: =MIN(F34,C49) -> 4081 | H49: =MIN(F34,F49) -> 4081 | I49: =(G49-H49)*K34 -> 0 | J49: =IF(P34=0,0,MIN($D$6,$H$6/P34)) -> 691.34399 | K49: =MIN(MAX(F34-J49,0),F49) -> 3389.656 | L49: =(H49-K49)*K34 -> 277970.4 | M49: =IF(P34=0,0,MIN($H$6*Q34,D34)) -> 29036.447 | N49: =M49*J34-(M49/Supuestos!$B$18)*I34 -> 28294.264 | O49: 1 | P49: =M34+B34*I34+C34*H34+D34*J34+G49*K34+MIN(G34,C49)*L34 -> 6508571.7 | Q49: =(E49+I49)+(L49+N49) -> 524843.25
A50: =A35 -> Jun | B50: =$B$6*N35 -> 112397 | C50: =(B35+C35+D35)/(E35*24*Supuestos!$B$16) -> 6518.1433 | D50: =MIN(B50*O35,C35) -> 112397 | E50: =D50*H35*O50 -> 204526.01 | F50: =((B35+C35+D35)-D50)/(E35*24*Supuestos!$B$16) -> 6244.2714 | G50: =MIN(F35,C50) -> 4146 | H50: =MIN(F35,F50) -> 4146 | I50: =(G50-H50)*K35 -> 0 | J50: =IF(P35=0,0,MIN($D$6,$H$6/P35)) -> 691.34399 | K50: =MIN(MAX(F35-J50,0),F50) -> 3454.656 | L50: =(H50-K50)*K35 -> 277970.4 | M50: =IF(P35=0,0,MIN($H$6*Q35,D35)) -> 29036.447 | N50: =M50*J35-(M50/Supuestos!$B$18)*I35 -> 28294.264 | O50: 1 | P50: =M35+B35*I35+C35*H35+D35*J35+G50*K35+MIN(G35,C50)*L35 -> 6289867.8 | Q50: =(E50+I50)+(L50+N50) -> 510790.68
A51: =A36 -> Jul | B51: =$B$6*N36 -> 113488.23 | C51: =(B36+C36+D36)/(E36*24*Supuestos!$B$16) -> 5612.6438 | D51: =MIN(B51*O36,C36) -> 113488.23 | E51: =D51*H36*O51 -> 206511.7 | F51: =((B36+C36+D36)-D51)/(E36*24*Supuestos!$B$16) -> 5345.0334 | G51: =MIN(F36,C51) -> 3935 | H51: =MIN(F36,F51) -> 3935 | I51: =(G51-H51)*K36 -> 0 | J51: =IF(P36=0,0,MIN($D$6,$H$6/P36)) -> 691.34399 | K51: =MIN(MAX(F36-J51,0),F51) -> 3243.656 | L51: =(H51-K51)*K36 -> 277970.4 | M51: =IF(P36=0,0,MIN($H$6*Q36,D36)) -> 31801.823 | N51: =M51*J36-(M51/Supuestos!$B$18)*I36 -> 30988.955 | O51: 1 | P51: =M36+B36*I36+C36*H36+D36*J36+G51*K36+MIN(G36,C51)*L36 -> 5758030.5 | Q51: =(E51+I51)+(L51+N51) -> 515471.06
A52: =A37 -> Ago | B52: =$B$6*N37 -> 106185.36 | C52: =(B37+C37+D37)/(E37*24*Supuestos!$B$16) -> 6261.0144 | D52: =MIN(B52*O37,C37) -> 106185.36 | E52: =D52*H37*O52 -> 193222.85 | F52: =((B37+C37+D37)-D52)/(E37*24*Supuestos!$B$16) -> 6010.6245 | G52: =MIN(F37,C52) -> 3868 | H52: =MIN(F37,F52) -> 3868 | I52: =(G52-H52)*K37 -> 0 | J52: =IF(P37=0,0,MIN($D$6,$H$6/P37)) -> 691.34399 | K52: =MIN(MAX(F37-J52,0),F52) -> 3176.656 | L52: =(H52-K52)*K37 -> 277970.4 | M52: =IF(P37=0,0,MIN($H$6*Q37,D37)) -> 29036.447 | N52: =M52*J37-(M52/Supuestos!$B$18)*I37 -> 28294.264 | O52: 1 | P52: =M37+B37*I37+C37*H37+D37*J37+G52*K37+MIN(G37,C52)*L37 -> 6137877.6 | Q52: =(E52+I52)+(L52+N52) -> 499487.52
A53: =A38 -> Sep | B53: =$B$6*N38 -> 100309.49 | C53: =(B38+C38+D38)/(E38*24*Supuestos!$B$16) -> 5448.1603 | D53: =MIN(B53*O38,C38) -> 100309.49 | E53: =D53*H38*O53 -> 182530.68 | F53: =((B38+C38+D38)-D53)/(E38*24*Supuestos!$B$16) -> 5203.7415 | G53: =MIN(F38,C53) -> 3761 | H53: =MIN(F38,F53) -> 3761 | I53: =(G53-H53)*K38 -> 0 | J53: =IF(P38=0,0,MIN($D$6,$H$6/P38)) -> 691.34399 | K53: =MIN(MAX(F38-J53,0),F53) -> 3069.656 | L53: =(H53-K53)*K38 -> 277970.4 | M53: =IF(P38=0,0,MIN($H$6*Q38,D38)) -> 29036.447 | N53: =M53*J38-(M53/Supuestos!$B$18)*I38 -> 28294.264 | O53: 1 | P53: =M38+B38*I38+C38*H38+D38*J38+G53*K38+MIN(G38,C53)*L38 -> 5416313.5 | Q53: =(E53+I53)+(L53+N53) -> 488795.35
A54: =A39 -> Oct | B54: =$B$6*N39 -> 110550.3 | C54: =(B39+C39+D39)/(E39*24*Supuestos!$B$16) -> 5538.4409 | D54: =MIN(B54*O39,C39) -> 110550.3 | E54: =D54*H39*O54 -> 201165.61 | F54: =((B39+C39+D39)-D54)/(E39*24*Supuestos!$B$16) -> 5277.7582 | G54: =MIN(F39,C54) -> 3121 | H54: =MIN(F39,F54) -> 3121 | I54: =(G54-H54)*K39 -> 0 | J54: =IF(P39=0,0,MIN($D$6,$H$6/P39)) -> 691.34399 | K54: =MIN(MAX(F39-J54,0),F54) -> 2429.656 | L54: =(H54-K54)*K39 -> 277970.4 | M54: =IF(P39=0,0,MIN($H$6*Q39,D39)) -> 31801.823 | N54: =M54*J39-(M54/Supuestos!$B$18)*I39 -> 30988.955 | O54: 1 | P54: =M39+B39*I39+C39*H39+D39*J39+G54*K39+MIN(G39,C54)*L39 -> 5341481.8 | Q54: =(E54+I54)+(L54+N54) -> 510124.97
A55: =A40 -> Nov | B55: =$B$6*N40 -> 114663.41 | C55: =(B40+C40+D40)/(E40*24*Supuestos!$B$16) -> 5324.6686 | D55: =MIN(B55*O40,C40) -> 114663.41 | E55: =D55*H40*O55 -> 208650.13 | F55: =((B40+C40+D40)-D55)/(E40*24*Supuestos!$B$16) -> 5045.2744 | G55: =MIN(F40,C55) -> 3661 | H55: =MIN(F40,F55) -> 3661 | I55: =(G55-H55)*K40 -> 0 | J55: =IF(P40=0,0,MIN($D$6,$H$6/P40)) -> 345.67199 | K55: =MIN(MAX(F40-J55,0),F55) -> 3315.328 | L55: =(H55-K55)*K40 -> 138985.2 | M55: =IF(P40=0,0,MIN($H$6*Q40,D40)) -> 26271.071 | N55: =M55*J40-(M55/Supuestos!$B$18)*I40 -> 25599.572 | O55: 1 | P55: =M40+B40*I40+C40*H40+D40*J40+G55*K40+MIN(G40,C55)*L40 -> 5320231.6 | Q55: =(E55+I55)+(L55+N55) -> 373234.91
